Workbook
Name Six: '[1]6-Months'!$A$17:$S$1334
Name Sixes2: '[2]MOF 6M'!$A$7:$J$1130
Name Three: '[1]3-Months'!$A$9:$T$1555
Name three1: '[2]MOF 3M'!$A$6:$J$288
Name Twelve: '[1]12-Months'!$A$18:$S$1478
Name Twelves1: '[2]MOF 12M'!$A$7:$J$1662

Sheet Summary
A1: HABIB BANK LIMITED | C1: PKR | E1: PKR | G1: PKR | I1: PKR | K1: PKR
A2: RATIOS | C2: 25 Forecast | E2: 24 | G2: 23 | I2: 22 | K2: 21
A3: Total Assets | C3: =SOFP!$D$14 -> 6.8380813e+09 | E3: =SOFP!$F$14 -> 6055112877 | G3: =SOFP!$H$14 -> 5,534,348,303 | I3: =SOFP!$J$14 -> 4638806111 | K3: =SOFP!$L$14 -> 4317468145
A4: Total Equity | C4: =SOFP!$D$25 -> 4.5145751e+08 | E4: =SOFP!$F$25 -> 410798094 | G4: =SOFP!$H$25 -> 366020653 | I4: =SOFP!$J$25 -> 285021814 | K4: =SOFP!$L$25 -> 283685802
A5: Revenue | C5: ='P&L'!$D$3+$O$64+$O$65+$O$67+$O$68+$O$69 -> 6.0357889e+08 | E5: ='P&L'!$F$3+$O$64+$O$65+$O$67+$O$68+$O$69 -> 813192081 | G5: ='P&L'!$H$3+$Q$64+$Q$65+$Q$67+$Q$68+$Q$69 -> 712345078 | I5: ='P&L'!$J$3+$S$64+$S$65+$S$67+$S$68+$S$69 -> 436101037 | K5: ='P&L'!$L$3+$U$64+$U$65+$U$67+$U$68+$U$69 -> 262253962
A6: EBITDA (PBPT + D&A) | C6: =C7+'P&L'!D144+'P&L'!D148+'P&L'!D154 -> 1.4645576e+08 | E6: =E7+'P&L'!F144+'P&L'!F148+'P&L'!F154 -> 165159168 | G6: =G7+'P&L'!H144+'P&L'!H148+'P&L'!H154 -> 143168520 | I6: =I7+'P&L'!J144+'P&L'!J148+'P&L'!J154 -> 99124697 | K6: =K7+'P&L'!L144+'P&L'!L148+'P&L'!L154 -> 81530017
A7: PBPT (EBIT) | C7: ='P&L'!$D$24 -> 1.272089e+08 | E7: ='P&L'!$F$24 -> 146938167 | G7: ='P&L'!$H$24 -> 126816775 | I7: ='P&L'!$J$24 -> 85511699 | K7: ='P&L'!$L$24 -> 70115016
A8: EBT | C8: ='P&L'!$D$26 -> 1.0844157e+08 | E8: ='P&L'!$F$26 -> 120334380 | G8: ='P&L'!$H$26 -> 113550996 | I8: ='P&L'!$J$26 -> 77029938 | K8: ='P&L'!$L$26 -> 62027911
A9: Net Income | C9: ='P&L'!$D$33 -> 49883121 | E9: ='P&L'!$F$33 -> 57804659 | G9: ='P&L'!$H$33 -> 57757416 | I9: ='P&L'!$J$33 -> 34398330 | K9: ='P&L'!$L$33 -> 35506873
A10: Shares Outstanding | C10: ='P&L'!D35 -> 1466852 | E10: ='P&L'!F35 -> 1466852 | G10: ='P&L'!H35 -> 1466852 | I10: ='P&L'!J35 -> 1466852 | K10: ='P&L'!L35 -> 1466852
A11: EPS | C11: ='P&L'!D36 -> 33.866535 | E11: ='P&L'!F36 -> 39.85 | G11: ='P&L'!H36 -> 39.32 | I11: ='P&L'!J36 -> 23.23 | K11: ='P&L'!L36 -> 23.88
A12: Book Value per share | C12: =C4/C10 -> 307.77304 | E12: =E4/E10 -> 280.05422 | G12: =G4/G10 -> 249.528 | I12: =I4/I10 -> 194.3085 | K12: =K4/K10 -> 193.3977
A13: Sales per share | C13: =C5/C10 -> 411.47907 | E13: =E5/E10 -> 554.37909 | G13: =G5/G10 -> 485.62846 | I13: =I5/I10 -> 297.30405 | K13: =K5/K10 -> 178.78693
A14: Cash Dividend per share | C14: ='P&L'!D37 -> 10.953909 | E14: ='P&L'!F37 -> 16.25 | G14: ='P&L'!H37 -> 9.75 | I14: ='P&L'!J37 -> 6.75 | K14: ='P&L'!L37 -> 7.5
A15: PSX Filing Date of Annual Financial Statements | E15: 19-Feb-2025 02:00PM | G15: 23-Feb-2024 12:25AM | I15: 24-Feb-2023 12:39AM | K15: 24-Feb-2022 02:01PM
A16: Stock Price a day before Filing Date (Closing) | E16: 164.91 | G16: 112.95 | I16: 73.38 | K16: 121.41
A17: Stock Price on Filing Date (Closing) | E17: 162.46 | G17: 113.77 | I17: 69.56 | K17: 116.44
A18: Stock Price a week later from the Filing Date (Closing) | D18: 45742 | E18: 153.74 | F18: 45352 | G18: 117.06 | H18: 44988 | I18: 71.59 | J18: 44988 | K18: 115.16
A19: Stock Price a month later from the Filing Date (Closing) | D19: 45735 | E19: 154.02 | F19: 45376 | G19: 104.13 | H19: 45009 | I19: 72.5 | J19: 45009 | K19: 111.98
A20: Risk-free Rate (PIB Yield 10Y) | C20: ='Pakistan Investment Bonds'!I496 -> 0.1374048 | E20: ='Pakistan Investment Bonds'!I496 -> 0.1374048 | G20: ='Pakistan Investment Bonds'!I496 -> 0.1374048 | I20: ='Pakistan Investment Bonds'!I496 -> 0.1374048 | K20: ='Pakistan Investment Bonds'!I496 -> 0.1374048
A21: Beta | C21: ='Regression Monthly'!B18 -> 1.2900967 | E21: ='Regression Monthly'!B18 -> 1.2900967 | G21: ='Regression Monthly'!B18 -> 1.2900967 | I21: ='Regression Monthly'!B18 -> 1.2900967 | K21: ='Regression Monthly'!B18 -> 1.2900967
A22: Expected return on market (10-year CAGR) | C22: ='HBL Stock Price Monthly'!P9+0.05 -> 0.20742096 | E22: ='HBL Stock Price Monthly'!P9+0.05 -> 0.20742096 | G22: ='HBL Stock Price Monthly'!P9+0.05 -> 0.20742096 | I22: ='HBL Stock Price Monthly'!P9+0.05 -> 0.20742096 | K22: ='HBL Stock Price Monthly'!P9+0.05 -> 0.20742096
A23: Expected return on a security (CAPM) | C23: =C20+(C21*(C22-C20)) -> 0.22773242 | E23: =E20+(E21*(E22-E20)) -> 0.22773242 | G23: =G20+(G21*(G22-G20)) -> 0.22773242 | I23: =I20+(I21*(I22-I20)) -> 0.22773242 | K23: =K20+(K21*(K22-K20)) -> 0.22773242
A24: Retention ratio | C24: =(C11-C14)/C11 -> 0.67655654 | E24: =(E11-E14)/E11 -> 0.59222083 | G24: =(G11-G14)/G11 -> 0.75203459 | I24: =(I11-I14)/I11 -> 0.70942746 | K24: =(K11-K14)/K11 -> 0.68592965
A25: Sustainable Growth Rate | C25: =C24*C62 -> 0.074755102 | E25: =E24*E62 -> 0.083333208 | G25: =G24*G62 -> 0.11866974 | I25: =I24*I62 -> 0.085618429 | K25: =K24*K62 -> 0.085852788
A26: Return on Equity | C26: =C63 -> 0.1104935 | E26: =E63 -> 0.14071307 | G26: =G63 -> 0.15779824 | I26: =I63 -> 0.12068666 | K26: =K63 -> 0.12516267
A27: Effective Tax Rate | C27: ='P&L'!C27 -> 0.54 | E27: ='P&L'!E27 -> 0.51963305 | G27: ='P&L'!G27 -> 0.49135263 | I27: ='P&L'!I27 -> 0.55344207 | K27: ='P&L'!K27 -> 0.4275662
A29: Ratios
A30: P/E Ratio | C30: 25 | E30: 24 | G30: 23 | I30: 22 | K30: 21
A31: Stock Price a day before Filing Date (Closing) Previous Year Earnings | E31: =E16/G11 -> 4.1940488 | G31: =G16/I11 -> 4.8622471 | I31: =I16/K11 -> 3.0728643
A32: Stock Price on Filing Date (Closing) | E32: =E17/E$11 -> 4.076788 | G32: =G17/G$11 -> 2.8934385 | I32: =I17/I$11 -> 2.9944038 | K32: =K17/K$11 -> 4.8760469
A33: Stock Price a week later from the Filing Date (Closing) | E33: =E18/E$11 -> 3.8579674 | G33: =G18/G$11 -> 2.9771109 | I33: =I18/I$11 -> 3.0817908 | K33: =K18/K$11 -> 4.8224456
A34: Stock Price a month later from the Filing Date (Closing) | E34: =E19/E$11 -> 3.8649937 | G34: =G19/G$11 -> 2.6482706 | I34: =I19/I$11 -> 3.1209643 | K34: =K19/K$11 -> 4.6892797
A35: Justified Trailing ratio | C35: =((1-C24)*(1+C25))/(C23-C25) -> 2.2723794 | E35: =((1-E24)*(1+E25))/(E23-E25) -> 3.0593015 | G35: =((1-G24)*(1+G25))/(G23-G25) -> 2.5434126 | I35: =((1-I24)*(1+I25))/(I23-I25) -> 2.2197034 | K35: =((1-K24)*(1+K25))/(K23-K25) -> 2.4036866
A36: Justified Leading ratio | C36: =(1-C24)/(C23-C25) -> 2.114323 | E36: =(1-E24)/(E23-E25) -> 2.8239709 | G36: =(1-G24)/(G23-G25) -> 2.2736046 | I36: =(1-I24)/(I23-I25) -> 2.0446441 | K36: =(1-K24)/(K23-K25) -> 2.2136395
A38: P/B Ratio | C38: 25 | E38: 24 | G38: 23 | I38: 22 | K38: 21
A39: Stock Price a day before Filing Date (Closing) Previous Year Equity | E39: =E16/G12 -> 0.66088774 | G39: =G16/I12 -> 0.58129212 | I39: =I16/K12 -> 0.3794254
A40: Stock Price on Filing Date (Closing) | E40: =E17/E$12 -> 0.58010195 | G40: =G17/G$12 -> 0.45594081 | I40: =I17/I$12 -> 0.35798742 | K40: =K17/K$12 -> 0.60207541
A41: Stock Price a week later from the Filing Date (Closing) | E41: =E18/E$12 -> 0.54896512 | G41: =G18/G$12 -> 0.4691257 | I41: =I18/I$12 -> 0.36843473 | K41: =K18/K$12 -> 0.59545693
A42: Stock Price a month later from the Filing Date (Closing) | E42: =E19/E$12 -> 0.54996493 | G42: =G19/G$12 -> 0.41730787 | I42: =I19/I$12 -> 0.373118 | K42: =K19/K$12 -> 0.57901413
A43: Justified Trailing ratio | C43: =(C26-C25)/(C23-C25) -> 0.23361895 | E43: =(E26-E25)/(E23-E25) -> 0.3973696 | G43: =(G26-G25)/(G23-G25) -> 0.35877081 | I43: =(I26-I25)/(I23-I25) -> 0.24676127 | K43: =(K26-K25)/(K23-K25) -> 0.27706503
A45: P/S Ratio | C45: 25 | E45: 24 | G45: 23 | I45: 22 | K45: 21
A46: Stock Price a day before Filing Date (Closing) Previous Year Sales | E46: =E16/G13 -> 0.33958059 | G46: =G16/I13 -> 0.3799141 | I46: =I16/K13 -> 0.41043269
A47: Stock Price on Filing Date (Closing) | E47: =E17/E$13 -> 0.29304857 | G47: =G17/G$13 -> 0.23427375 | I47: =I17/I$13 -> 0.23396923 | K47: =K17/K$13 -> 0.65127804
A48: Stock Price a week later from the Filing Date (Closing) | E48: =E18/E$13 -> 0.27731926 | G48: =G18/G$13 -> 0.24104848 | I48: =I18/I$13 -> 0.24079726 | K48: =K18/K$13 -> 0.64411868
A49: Stock Price a month later from the Filing Date (Closing) | E49: =E19/E$13 -> 0.27782433 | G49: =G19/G$13 -> 0.21442318 | I49: =I19/I$13 -> 0.2438581 | K49: =K19/K$13 -> 0.62633215
A50: Justified Trailing ratio | C50: =C35*C65*C67*C69 -> 0.18780209 | E50: =E35*E65*E67*E69 -> 0.21746631 | G50: =G35*G65*G67*G69 -> 0.2062216 | I50: =I35*I65*I67*I69 -> 0.17508348 | K50: =K35*K65*K67*K69 -> 0.32543796
A51: Justified Leading ratio | C51: =C36*C65*C67*C69 -> 0.17473943 | E51: =E36*E65*E67*E69 -> 0.20073815 | G51: =G36*G65*G67*G69 -> 0.18434538 | I51: =I36*I65*I67*I69 -> 0.16127534 | K51: =K36*K65*K67*K69 -> 0.29970726
A53: DDM
A54: Constant Growth DDM | C54: =C14/(C23-C25) -> 71.604794 | E54: =E14/(E23-E25) -> 112.53524 | G54: =G14/(G23-G25) -> 89.398131 | I54: =I14/(I23-I25) -> 47.497083 | K54: =K14/(K23-K25) -> 52.861711
A56: Residual Income
A57: Net Income | C57: =C9 -> 49883121 | E57: =E9 -> 57804659 | G57: =G9 -> 57757416 | I57: =I9 -> 34398330 | K57: =K9 -> 35506873
A58: Equity Charge | C58: =C23*E4 -> 93552044 | E58: =E23*G4 -> 83354769 | G58: =G23*I4 -> 64908707 | I58: =I23*K4 -> 64604454 | K58: =K23*SOFP!N25 -> 60461875
A59: Residual Income | C59: =C57-C58 -> -43668923 | E59: =E57-E58 -> -25550110 | G59: =G57-G58 -> -7151291.1 | I59: =I57-I58 -> -30206124 | K59: =K57-K58 -> -24955002
A61: DuPont Analysis
A62: Net Income/ Total Equity | C62: =C9/C4 -> 0.1104935 | E62: =E9/E4 -> 0.14071307 | G62: =G9/G4 -> 0.15779824 | I62: =I9/I4 -> 0.12068666 | K62: =K9/K4 -> 0.12516267
A63: ROE | C63: =C65*C67*C69*C71*C73 -> 0.1104935 | E63: =E65*E67*E69*E71*E73 -> 0.14071307 | G63: =G65*G67*G69*G71*G73 -> 0.15779824 | I63: =I65*I67*I69*I71*I73 -> 0.12068666 | K63: =K65*K67*K69*K71*K73 -> 0.12516267
A64: Tax Burden
A65: Net Income/EBT | C65: =C9/C8 -> 0.46 | E65: =E9/E8 -> 0.48036695 | G65: =G9/G8 -> 0.50864737 | I65: =I9/I8 -> 0.44655793 | K65: =K9/K8 -> 0.5724338
A66: Interest Burden
A67: EBT/EBIT | C67: =C8/C7 -> 0.85246838 | E67: =E8/E7 -> 0.8189457 | G67: =G8/G7 -> 0.89539413 | I67: =I8/I7 -> 0.90081169 | K67: =K8/K7 -> 0.88465944
A68: Operating Margin
A69: EBIT/Revenue | C69: =C7/C5 -> 0.21075771 | E69: =E7/E5 -> 0.18069306 | G69: =G7/G5 -> 0.17802717 | I69: =I7/I5 -> 0.19608231 | K69: =K7/K5 -> 0.26735541
A70: Asset Turnover
A71: Revenue/Assets | C71: =C5/C3 -> 0.088267288 | E71: =E5/E3 -> 0.13429842 | G71: =G5/G3 -> 0.12871345 | I71: =I5/I3 -> 0.094011482 | K71: =K5/K3 -> 0.060742535
A72: Equity Multiplier
A73: Assets/Equity | C73: =C3/C4 -> 15.146678 | E73: =E3/E4 -> 14.739876 | G73: =G3/G4 -> 15.120317 | I73: =I3/I4 -> 16.275267 | K73: =K3/K4 -> 15.21919
A75: Basil III Disclosures
A76: CET1 Ratio | D76: 0.085 | E76: 0.1348 | F76: 0.09 | G76: 0.1155 | H76: 0.09 | I76: 0.1079 | J76: 0.095 | K76: 0.1153
A77: Tier 1 Ratio | D77: 0.1 | E77: 0.1427 | F77: 0.105 | G77: 0.1244 | H77: 0.105 | I77: 0.1181 | J77: 0.11 | K77: 0.1228
A78: Total Capital Ratio | D78: 0.125 | E78: 0.177 | F78: 0.13 | G78: 0.1601 | H78: 0.13 | I78: 0.1483 | J78: 0.135 | K78: 0.1563
A79: Leverage Ratio (%) | D79: 0.03 | E79: ='Capital Adequacy and Liquidity'!C91 -> 0.0466 | F79: 0.03 | G79: ='Capital Adequacy and Liquidity'!E91 -> 0.0433 | H79: 0.03 | I79: ='Capital Adequacy and Liquidity'!G91 -> 0.042 | J79: 0.03 | K79: ='Capital Adequacy and Liquidity'!I91 -> 0.0438
A80: Liquidity Coverage Ratio | E80: ='Capital Adequacy and Liquidity'!C96 -> 2.6697 | G80: ='Capital Adequacy and Liquidity'!E96 -> 2.7081 | I80: ='Capital Adequacy and Liquidity'!G96 -> 2.5443 | K80: ='Capital Adequacy and Liquidity'!I96 -> 2.3147
A81: Net Stable Funding Ratio | E81: ='Capital Adequacy and Liquidity'!C100 -> 1.5208 | G81: ='Capital Adequacy and Liquidity'!E100 -> 1.5985 | I81: ='Capital Adequacy and Liquidity'!G100 -> 1.4852 | K81: ='Capital Adequacy and Liquidity'!I100 -> 1.5509

Sheet SOFP
A1: HABIB BANK LIMITED | D1: PKR | F1: PKR | H1: PKR | J1: PKR | L1: PKR | N1: PKR | P1: PKR
A2: CONSOLIDATED STATEMENT OF FINANCIAL POSITION | D2: 25 Forecast | F2: 24 | H2: 23 | J2: 22 | L2: 21 | N2: 20 | P2: 19
A3: ASSETS
A4: Cash and balances with treasury banks | D4: =D$19*D82 -> 4.2133749e+08 | F4: 460194916 | H4: 547528581 | J4: 296015386 | L4: 441252246 | N4: 375280120 | P4: 367593717
A5: Balances with other banks | D5: =D$19*D81 -> 72808358 | F5: 51324612 | H5: 56603548 | J5: 41513022 | L5: 64438075 | N5: 56533829 | P5: 41248554
A6: Lendings to financial institutions | D6: =D$19*D80 -> 1.5880951e+08 | F6: 84293922 | H6: 88598160 | J6: 254593287 | L6: 93742432 | N6: 30154193 | P6: 45303199
A7: Investments | D7: =D$19*D78 -> 2.8076679e+09 | F7: 2528200439 | H7: 2562299087 | J7: 1948801042 | L7: 1948955978 | N7: 1948576822 | P7: 1379607379
A8: Advances | D8: ='National Advances'!C25 -> 2.7902661e+09 | F8: 2435434872 | H8: 1861344592 | J8: 1782497923 | L8: 1507047097 | N8: 1223510222 | P8: 1166956994
A9: Property and equipment | C9: =AVERAGE(E9,G9,I9,K9,M9) -> 0.16000242 | D9: =F9*(1+C9) -> 1.5175752e+08 | E9: =F9/H9-1 -> 0.11587756 | F9: 130825175 | G9: =H9/J9-1 -> 0.40950059 | H9: 117239722 | I9: =J9/L9-1 -> 0.17068008 | J9: =105996430-J10 -> 83178200 | K9: =L9/N9-1 -> -0.017739496 | L9: =90872737-L10 -> 71051179 | M9: =N9/P9-1 -> 0.12169335 | N9: =89190210-N10 -> 72334354 | P9: =80462410-P10 -> 64486746
A10: Right-of-use assets | C10: =AVERAGE(E10,G10,I10,K10,M10) -> 0.11487619 | D10: =F10*(1+C10) -> 30556549 | E10: =F10/H10-1 -> 0.11167323 | F10: 27408020 | G10: =H10/J10-1 -> 0.080484551 | H10: 24654745 | I10: =J10/L10-1 -> 0.15118247 | J10: 22818230 | K10: =L10/N10-1 -> 0.17594491 | L10: 19821558 | M10: =N10/P10-1 -> 0.055095801 | N10: 16855856 | P10: 15975664
A11: Intangible assets | C11: =AVERAGE(E11,G11,I11,K11,M11) -> 0.22882223 | D11: =F11*(1+C11) -> 30534309 | E11: =F11/H11-1 -> 0.09365498 | F11: 24848435 | G11: =H11/J11-1 -> 0.23332409 | H11: 22720543 | I11: =J11/L11-1 -> 0.45855164 | J11: 18422200 | K11: =L11/N11-1 -> 0.21296654 | L11: 12630475 | M11: =N11/P11-1 -> 0.1456139 | N11: 10412880 | P11: 9089345
A12: Deferred tax assets | D12: =F12 -> 0 | F12: 0 | H12: 480873 | J12: 5797045 | N12: 0 | P12: 0
A13: Other assets | C13: =AVERAGE(E13,G13,I13,K13,M13) -> 0.19758332 | D13: =F13*(1+C13) -> 3.7434357e+08 | E13: =F13/H13-1 -> 0.23609776 | F13: 312582486 | G13: =H13/J13-1 -> 0.42631825 | H13: 252878451 | I13: =J13/L13-1 -> 0.17627441 | J13: 177294549 | K13: =L13/N13-1 -> 0.30606211 | L13: 150725500 | M13: =N13/P13-1 -> -0.15683592 | N13: 115404542 | P13: 136870799
A14: Total Assets | D14: =SUM(D4:D13) -> 6.8380813e+09 | F14: 6055112877 | H14: 5,534,348,303 | J14: 4638806111 | L14: 4317468145 | N14: 3849062818 | P14: 3227132397
A16: LIABILITIES
A17: Bills payable | C17: =AVERAGE(E17,G17,I17,K17,M17) -> 0.085733639 | D17: =(D$24-SUM(D$19:D$23))*C17 -> 82201034 | E17: =F17/(F$18+F$17) -> 0.10412291 | F17: 96104151 | G17: =H17/(H$18+H$17) -> 0.07213295 | H17: 51700823 | I17: =J17/(J$18+J$17) -> 0.081792682 | J17: 52001577 | K17: =L17/(L$18+L$17) -> 0.091989853 | L17: 44196984 | M17: =N17/(N$18+N$17) -> 0.078629796 | N17: 46434199 | O17: =P17/(P$18+P$17) -> 0.072061216 | P17: 29681108
A18: Borrowings | C18: =AVERAGE(E18,G18,I18,K18,M18) -> 0.91426636 | D18: =(D$24-SUM(D$19:D$23))*C18 -> 8.7659455e+08 | E18: =F18/(F$18+F$17) -> 0.89587709 | F18: 826883400 | G18: =H18/(H$18+H$17) -> 0.92786705 | H18: 665042679 | I18: =J18/(J$18+J$17) -> 0.91820732 | J18: 583771399 | K18: =L18/(L$18+L$17) -> 0.90801015 | L18: 436258005 | M18: =N18/(N$18+N$17) -> 0.9213702 | N18: 544107826 | O18: =P18/(P$18+P$17) -> 0.92793878 | P18: 382206306
A19: Deposits and other accounts | D19: ='National Deposits'!C50 -> 5.0136926e+09 | F19: 4370370642 | H19: 4142351836 | J19: 3469342252 | L19: 3381998398 | N19: 2830371390 | P19: 2437597169
A20: Lease liabilities | C20: =AVERAGE(E20,G20,I20) -> 0.17209923 | D20: =F20*(1+C20) -> 42042298 | E20: =F20/H20-1 -> 0.17642661 | F20: 35869231 | G20: =H20/J20-1 -> 0.12594434 | H20: 30489986 | I20: =J20/L20-1 -> 0.21392674 | J20: 27079479 | L20: 22307342
A21: Subordinated debt | C21: =AVERAGE(E21,G21,I21,K21,M21) -> 0.03131813 | D21: =F21*(1+C21) -> 21012076 | E21: =F21/H21-1 -> 0.034265699 | F21: 20374000 | G21: =H21/J21-1 -> 0.043710925 | H21: 19699000 | I21: =J21/L21-1 -> 0.52529497 | J21: 18874000 | K21: =L21/N21-1 -> -0.44650206 | L21: 12374000 | M21: =N21/P21-1 -> -0.00017889088 | N21: 22356000 | P21: 22360000
A22: Deferred tax liabilities | D22: =F22 -> 7995007 | F22: 7995007 | L22: 5082602 | N22: 10387859 | P22: 6189687
A23: Other liabilities | C23: =AVERAGE(E23,G23,I23,K23,M23) -> 0.19659674 | D23: =F23*(1+C23) -> 3.4308625e+08 | E23: =F23/H23-1 -> 0.10683551 | F23: 286718352 | G23: =H23/J23-1 -> 0.27786583 | H23: 259043326 | I23: =J23/L23-1 -> 0.54080167 | J23: =229795069-J20 -> 202715590 | K23: =L23/N23-1 -> 0.012737366 | L23: =153872354-L20 -> 131565012 | M23: =N23/P23-1 -> 0.044743333 | N23: 129910297 | P23: 124346615
A24: Total Liabiliatied | D24: =D14-D25 -> 6.3866238e+09 | F24: 5644314783 | H24: 5168327650 | J24: 4353784297 | L24: 4033782343 | N24: 3583567571 | P24: 3002380885
A25: NET ASSETS | C25: =AVERAGE(E25,G25,I25,K25,M25) -> 0.066021079 | D25: =D14*C25 -> 4.5145751e+08 | E25: =F25/F14 -> 0.067843177 | F25: 410798094 | G25: =H25/H14 -> 0.06613618 | H25: 366020653 | I25: =J25/J14 -> 0.061442925 | J25: 285021814 | K25: =L25/L14 -> 0.065706519 | L25: 283685802 | M25: =N25/N14 -> 0.068976595 | N25: 265495247 | O25: =P25/P14 -> 0.069644342 | P25: 224751512
A27: Shareholders' equity
A28: Share capital | D28: =F28 -> 14668525 | F28: 14668525 | H28: 14668525 | J28: 14668525 | L28: 14668525 | N28: 14668525 | P28: 14668525
A29: Reserves | C29: =AVERAGE(E29,G29,I29,K29,M29) -> 0.083814063 | D29: =F29*(1+C29) -> 1.065421e+08 | E29: =F29/H29-1 -> -0.024822361 | F29: 98302935 | G29: =H29/J29-1 -> 0.14849752 | H29: 100805157 | I29: =J29/L29-1 -> 0.078596279 | J29: 87771332 | K29: =L29/N29-1 -> 0.12924275 | L29: 81375519 | M29: =N29/P29-1 -> 0.087556131 | N29: 72062025 | P29: 66260511
A30: Surplus on revaluation of assets - net of tax | D30: =F30 -> 57370781 | F30: 57370781 | H30: 25857323 | J30: 1235369 | L30: 25159371 | N30: 36004914 | P30: 24875383
A31: Unappropriated profit | D31: =D34-SUM(D28:D30) -> 2.728761e+08 | F31: 238813471 | H31: 221883756 | J31: 178467639 | L31: 158441418 | N31: 138208223 | P31: 114550097
A32: Total equity attributable to the equity holders of the Bank | C32: =AVERAGE(E32,G32,I32,K32,M32,O32) -> 0.98788054 | D32: =D34*C32 -> 4.4598608e+08 | E32: =F32/F$34 -> 0.99600197 | F32: 409155712 | G32: =H32/H$34 -> 0.99233406 | H32: 363214761 | I32: =J32/J$34 -> 0.9898992 | J32: 282142865 | K32: =L32/L$34 -> 0.98575548 | L32: 279644833 | M32: =N32/N$34 -> 0.98285634 | N32: 260943687 | O32: =P32/P$34 -> 0.98043619 | P32: 220354516
A33: Non-controlling interest | C33: =AVERAGE(E33,G33,I33,K33,M33,O33) -> 0.01211946 | D33: =D34*C33 -> 5471421.3 | E33: =F33/F$34 -> 0.0039980273 | F33: 1642382 | G33: =H33/H$34 -> 0.007665939 | H33: 2805892 | I33: =J33/J$34 -> 0.010100802 | J33: 2878949 | K33: =L33/L$34 -> 0.014244523 | L33: 4040969 | M33: =N33/N$34 -> 0.017143659 | N33: 4551560 | O33: =P33/P$34 -> 0.019563811 | P33: 4396996
D34: =D25 -> 4.5145751e+08 | F34: 410798094 | H34: 366020653 | J34: 285,021,814 | L34: 283685802 | N34: 265495247 | P34: 224751512
Q36: Adjusted Revaluation Surplus
A37: 1
A38: Investments:
A39: Market Treasury Bills | C39: 0.215 | D39: =D$52*C39 -> 6.0364859e+08 | E39: =F39/F$52 -> 0.1766476 | F39: 446600531 | G39: =H39/H$52 -> 0.1653845 | H39: 423764549 | I39: =J39/J$52 -> 0.17308731 | J39: 337312735 | K39: =L39/L$52 -> 0.20097912 | L39: 391699451 | M39: =N39/N$52 -> 0.3245299 | N39: 632371432 | O39: =P39/P$52 -> 0.43886911 | P39: 605467062
A40: Pakistan Investment Bonds | C40: 0.52 | D40: =D$52*C40 -> 1.4599873e+09 | E40: =F40/F$52 -> 0.54084158 | F40: 1367355920 | G40: =H40/H$52 -> 0.60756457 | H40: 1556762138 | I40: =J40/J$52 -> 0.61129566 | J40: 1191293622 | K40: =L40/L$52 -> 0.60499795 | L40: 1179114373 | M40: =N40/N$52 -> 0.53254389 | N40: 1037702672 | O40: =P40/P$52 -> 0.451731 | P40: 623211426
A41: Ijarah Sukuk | C41: =E41 -> 0.13503515 | D41: =D$52*C41 -> 3.7913386e+08 | E41: =F41/F$52 -> 0.13503515 | F41: 341395936 | G41: =H41/H$52 -> 0.08635633 | H41: 221270745 | I41: =J41/J$52 -> 0.062904179 | J41: 122587729 | K41: =L41/L$52 -> 0.061099803 | L41: 119080826 | M41: =N41/N$52 -> 0.034566741 | N41: 67355950 | O41: =P41/P$52 -> 0.0033495566 | P41: 4621073
A42: Government of Pakistan US Dollar Bonds | C42: =(E42+G42+I42+K42+M42+O42)/6 -> 0.0065103977 | D42: =D$52*C42 -> 18279034 | E42: =F42/F$52 -> 0.0052037765 | F42: 13156190 | G42: =H42/H$52 -> 0.0090979765 | H42: 23311737 | I42: =J42/J$52 -> 0.0068489629 | J42: 13347266 | K42: =L42/L$52 -> 0.0084503094 | L42: 16469281 | M42: =N42/N$52 -> 0.0058492972 | N42: 11397805 | O42: =P42/P$52 -> 0.0036120639 | P42: 4983230
A43: Other Federal Government securities | C43: =D43/D44 -> 0.0031949759 | D43: =D44-SUM(D39:D42) -> 7888194.1 | E43: =F43/F$52 -> 0.0010207755 | F43: 2580725 | G43: =H43/H$52 -> 0.0021633532 | H43: 5543158 | I43: =J43/J$52 -> 0.0024045862 | J43: 4686060 | K43: =L43/L$52 -> 0.0060597161 | L43: 11810120 | M43: =N43/N$52 -> 0.005811697 | N43: 11324538 | O43: =P43/P$52 -> 0.0078239651 | P43: 10794000
A44: Federal Government securities | C44: =(E44+G44+I44+K44+M44+O44)/6 -> 0.87935507 | D44: =D$52*C44 -> 2.468937e+09 | E44: =F44/F$52 -> 0.85874888 | F44: =SUM(F39:F43) -> 2171089302 | G44: =H44/H$52 -> 0.87056673 | H44: =SUM(H39:H43) -> 2230652327 | I44: =J44/J$52 -> 0.8565407 | J44: =SUM(J39:J43) -> 1669227412 | K44: =L44/L$52 -> 0.8815869 | L44: =SUM(L39:L43) -> 1718174051 | M44: =N44/N$52 -> 0.90330152 | N44: =SUM(N39:N43) -> 1760152397 | O44: =P44/P$52 -> 0.9053857 | P44: =SUM(P39:P43) -> 1249076791
A45: Shares | C45: =(E45+G45+I45+K45+M45+O45)/6 -> 0.0072580247 | D45: =D$52*C45 -> 20378123 | E45: =F45/F$52 -> 0.010242686 | F45: 25895564 | G45: =H45/H$52 -> 0.0084921839 | H45: 21759515 | I45: =J45/J$52 -> 0.0047421213 | J45: 9241451 | K45: =L45/L$52 -> 0.0062731715 | L45: 12226135 | M45: =N45/N$52 -> 0.0055410733 | N45: 10797207 | O45: =P45/P$52 -> 0.0082569122 | P45: 11391297
A46: Non-Government debt securities | C46: =(E46+G46+I46+K46+M46+O46)/6 -> 0.032395791 | D46: =D$52*C46 -> 90956620 | E46: =F46/F$52 -> 0.029718042 | F46: 75133167 | G46: =H46/H$52 -> 0.030116486 | H46: 77167444 | I46: =J46/J$52 -> 0.036631295 | J46: 71387105 | K46: =L46/L$52 -> 0.04038176 | L46: 78702272 | M46: =N46/N$52 -> 0.036330867 | N46: 70793485 | O46: =P46/P$52 -> 0.021196295 | P46: 29242565
A47: Foreign securities | C47: =(E47+G47+I47+K47+M47+O47)/6 -> 0.06217434 | D47: =D$52*C47 -> 1.745649e+08 | E47: =F47/F$52 -> 0.082864271 | F47: 209497487 | G47: =H47/H$52 -> 0.07570422 | H47: 193976853 | I47: =J47/J$52 -> 0.080175457 | J47: 156246015 | K47: =L47/L$52 -> 0.053262415 | L47: 103806102 | M47: =N47/N$52 -> 0.037994771 | N47: 74035731 | O47: =P47/P$52 -> 0.043044905 | P47: 59385069
A48: National Investment Unit Trust units | C48: =(E48+G48+I48+K48+M48+O48)/6 -> 2.5936562e-05 | D48: =D$52*C48 -> 72821.252 | E48: =F48/F$52 -> 3.7332483e-05 | F48: 94384 | G48: =H48/H$52 -> 1.980448e-05 | H48: 50745 | I48: =J48/J$52 -> 1.9586402e-05 | J48: 38170 | K48: =L48/L$52 -> 2.3832247e-05 | L48: 46448 | M48: =N48/N$52 -> 2.4037543e-05 | N48: 46839 | O48: =P48/P$52 -> 3.1026219e-05 | P48: 42804
A49: Real Estate Investment Trust units | C49: =(E49+G49+I49+K49+M49+O49)/6 -> 0.00049399447 | D49: =D$52*C49 -> 1386972.4 | E49: =F49/F$52 -> 0.0013756255 | F49: 3477857 | G49: =H49/H$52 -> 0.0006414942 | H49: 1643700 | I49: =J49/J$52 -> 0.0008431851 | J49: 1643200 | K49: =L49/L$52 -> 3.1196189e-05 | L49: 60800 | M49: =N49/N$52 -> 2.7199338e-05 | N49: 53000 | O49: =P49/P$52 -> 4.5266502e-05 | P49: 62450
A50: Preference shares | C50: =(E50+G50+I50+K50+M50+O50)/6 -> 0.00035665976 | D50: =D$52*C50 -> 1001382.2 | E50: =F50/F$52 -> 0.00034565297 | F50: 873880 | G50: =H50/H$52 -> 0.00035744461 | H50: 915880 | I50: =J50/J$52 -> 0.00050584538 | J50: 985792 | K50: =L50/L$52 -> 0.00043705964 | L50: 851810 | M50: =N50/N$52 -> 0.00046177292 | N50: 899800 | O50: =P50/P$52 -> 3.2183069e-05 | P50: 44400
A51: Investments in associates | C51: =(E51+G51+I51+K51+M51+O51)/6 -> 0.017940184 | D51: =D$52*C51 -> 50370077 | E51: =F51/F$52 -> 0.016667507 | F51: 42138798 | G51: =H51/H$52 -> 0.014101641 | H51: 36132623 | I51: =J51/J$52 -> 0.020541808 | J51: 40031897 | K51: =L51/L$52 -> 0.01800367 | L51: 35088360 | M51: =N51/N$52 -> 0.016318763 | N51: 31798363 | O51: =P51/P$52 -> 0.022007713 | P51: 30362003
A52: Total | C52: =(E52+G52+I52+K52+M52+O52)/6 -> 1 | D52: =D7 -> 2.8076679e+09 | E52: 1 | F52: =SUM(F44:F51) -> 2528200439 | G52: 1 | H52: =SUM(H44:H51) -> 2562299087 | I52: 1 | J52: =SUM(J44:J51) -> 1948801042 | K52: 1 | L52: =SUM(L44:L51) -> 1948955978 | M52: 1 | N52: =SUM(N44:N51) -> 1948576822 | O52: 1 | P52: =SUM(P44:P51) -> 1379607379
F54: =F52-F7 -> 0 | H54: =H52-H7 -> 0 | J54: =J52-J7 -> 0 | L54: =L52-L7 -> 0 | N54: =N52-N7 -> 0 | P54: =P52-P7 -> 0
A56: Advances:
A57: Gross Performing Loans | D57: =D59-D58 -> 2.7964866e+09 | F57: 2461353794 | H57: 1862757724 | J57: 1783772956 | L57: 1510012130 | N57: 1223304893 | P57: 1161417102
A58: Gross Non-performaing Loan | D58: =D66/(1-C62) -> 1.5348542e+08 | F58: 111567323 | H58: 101899160 | J58: 90895949 | L58: 80888461 | N58: 82104376 | P58: 81905850
A59: Total | D59: =D67/(1-C63) -> 2.949972e+09 | F59: =SUM(F57:F58) -> 2572921117 | H59: =SUM(H57:H58) -> 1964656884 | J59: =SUM(J57:J58) -> 1874668905 | L59: =SUM(L57:L58) -> 1590900591 | N59: =SUM(N57:N58) -> 1305409269 | P59: =SUM(P57:P58) -> 1243322952
A61: Credit Allowance/Provision (Performing) | C61: =((2*E61)+(2*G61)+(2*I61)+K61+M61+O61)/9 -> 0.0095575944 | D61: =D57*C61 -> 26727685 | E61: =-F61/F57 -> 0.01556339 | F61: -38307009 | G61: =-H61/H57 -> 0.0098736506 | H61: -18392219 | I61: =-J61/J57 -> 0.0077989214 | J61: -13911505 | K61: =-L61/L57 -> 0.0072902116 | L61: -11008308 | M61: =-N61/N57 -> 0.0090437667 | N61: -11063284 | O61: =-P61/P57 -> 0.0032124471 | P61: -3730991
A62: Credit Allowance/Provision (Non-performing) | C62: =((2*E62)+(2*G62)+(2*I62)+K62+M62+O62)/9 -> 0.8685286 | D62: =D58*C62 -> 1.3330648e+08 | E62: =-F62/F58 -> 0.88896312 | F62: -99179236 | G62: =-H62/H58 -> 0.83337363 | H62: -84920073 | I62: =-J62/J58 -> 0.86097871 | J62: -78259477 | K62: =-L62/L58 -> 0.90056338 | L62: -72845186 | M62: =-N62/N58 -> 0.86275259 | N62: -70835763 | O62: =-P62/P58 -> 0.88681049 | P62: -72634967
A63: Total | C63: =((2*E63)+(2*G63)+(2*I63)+K63+M63+O63)/9 -> 0.054138098 | D63: =D59*C63 -> 1.5970587e+08 | E63: =-F63/F59 -> 0.053435857 | F63: =SUM(F61:F62) -> -137486245 | G63: =-H63/H59 -> 0.052585412 | H63: =SUM(H61:H62) -> -103312292 | I63: =-J63/J59 -> 0.049166539 | J63: =SUM(J61:J62) -> -92170982 | K63: =-L63/L59 -> 0.052708192 | L63: =SUM(L61:L62) -> -83853494 | M63: =-N63/N59 -> 0.062738215 | N63: =SUM(N61:N62) -> -81899047 | O63: =-P63/P59 -> 0.061420854 | P63: =SUM(P61:P62) -> -76365958
A65: Net Performing Loans | C65: =((2*E65)+(2*G65)+(2*I65)+K65+M65+O65)/9 -> 0.99276809 | D65: =C65*D$67 -> 2.7700872e+09 | E65: =F65/F$67 -> 0.9949134 | F65: =F57+F61 -> 2423046785 | G65: =H65/H$67 -> 0.99087805 | H65: =H57+H61 -> 1844365505 | I65: =J65/J$67 -> 0.99291081 | J65: =J57+J61 -> 1769861451 | K65: =L65/L$67 -> 0.99466289 | L65: =L57+L61 -> 1499003822 | M65: =N65/N$67 -> 0.99078993 | N65: =N57+N61 -> 1212241609 | O65: =P65/P$67 -> 0.99205551 | P65: =P57+P61 -> 1157686111
A66: Net Non-performing Loans | C66: =((2*E66)+(2*G66)+(2*I66)+K66+M66+O66)/9 -> 0.0072319062 | D66: =C66*D$67 -> 20178943 | E66: =F66/F$67 -> 0.0050866016 | F66: =F58+F62 -> 12388087 | G66: =H66/H$67 -> 0.0091219472 | H66: =H58+H62 -> 16979087 | I66: =J66/J$67 -> 0.0070891931 | J66: =J58+J62 -> 12636472 | K66: =L66/L$67 -> 0.0053371092 | L66: =L58+L62 -> 8043275 | M66: =N66/N$67 -> 0.0092100685 | N66: =N58+N62 -> 11268613 | O66: =P66/P$67 -> 0.0079444941 | P66: =P58+P62 -> 9270883
A67: Net Advances | D67: =D8 -> 2.7902661e+09 | F67: =F59+F63 -> 2435434872 | H67: =H59+H63 -> 1861344592 | J67: =J59+J63 -> 1782497923 | L67: =L59+L63 -> 1507047097 | N67: =N59+N63 -> 1223510222 | P67: =P59+P63 -> 1166956994
F69: =F67-F8 -> 0 | H69: =H67-H8 -> 0 | J69: =J67-J8 -> 0 | L69: =L67-L8 -> 0 | N69: =N67-N8 -> 0 | P69: =P67-P8 -> 0
A72: Loans, cash credits, running finances, etc. | F72: 2171007396 | H72: 1575536894
A73: Islamic financing and related assets | F73: 209656409 | H73: 219714285
A74: Bills discounted and purchased | F74: 192257312 | H74: 169405705
A75: Gross Advances | F75: =SUM(F72:F74) -> 2572921117 | H75: =SUM(H72:H74) -> 1964656884
A78: Investment to Deposit ratio | D78: 0.56 | F78: =F7/F$19 -> 0.57848651 | H78: =H7/H$19 -> 0.61856143 | J78: =J7/J$19 -> 0.56172061 | L78: =L7/L$19 -> 0.57627348 | N78: =N7/N$19 -> 0.6884527 | P78: =P7/P$19 -> 0.56597021
A79: Advance to Deposit ratio | D79: =D8/D$19 -> 0.55652916 | F79: =F8/F$19 -> 0.55726049 | H79: =H8/H$19 -> 0.44934488 | J79: =J8/J$19 -> 0.51378555 | L79: =L8/L$19 -> 0.44560846 | N79: =N8/N$19 -> 0.43227904 | P79: =P8/P$19 -> 0.4787325
A80: Lendings to financial institutions to Deposit ratio | D80: =((2*F80)+(2*H80)+(2*J80)+L80+N80+P80)/9 -> 0.031675159 | F80: =F6/F$19 -> 0.019287591 | H80: =H6/H$19 -> 0.021388372 | J80: =J6/J$19 -> 0.073383733 | L80: =L6/L$19 -> 0.027718059 | N80: =N6/N$19 -> 0.010653794 | P80: =P6/P$19 -> 0.018585187
A81: Balances with other banks to Deposit ratio | D81: =((2*F81)+(2*H81)+(2*J81)+L81+N81+P81)/9 -> 0.014521903 | F81: =F5/F$19 -> 0.011743766 | H81: =H5/H$19 -> 0.013664592 | J81: =J5/J$19 -> 0.011965675 | L81: =L5/L$19 -> 0.019053254 | N81: =N5/N$19 -> 0.019973997 | P81: =P5/P$19 -> 0.016921809
A82: Cash and balances with treasury banks | D82: =D83-SUM(D78:D81) -> 0.08403736 | F82: =F4/F$19 -> 0.10529883 | H82: =H4/H$19 -> 0.13217819 | J82: =J4/J$19 -> 0.085323201 | L82: =L4/L$19 -> 0.13047086 | N82: =N4/N$19 -> 0.13259042 | P82: =P4/P$19 -> 0.15080167
A83: *SUM to Deposit rato | D83: =((2*F83)+(2*H83)+(2*J83)+L83+N83+P83)/9 -> 1.2467636 | F83: =SUM(F78:F82) -> 1.2720772 | H83: =SUM(H78:H82) -> 1.2351375 | J83: =SUM(J78:J82) -> 1.2461788 | L83: =SUM(L78:L82) -> 1.1991241 | N83: =SUM(N78:N82) -> 1.2839499 | P83: =SUM(P78:P82) -> 1.2310114
A84: Policy Rate | D84: 0.115 | F84: ='Policy Rate'!D103 -> 0.18032787 | H84: ='Policy Rate'!D112 -> 0.21386301 | J84: ='Policy Rate'!D121 -> 0.14582877 | L84: ='Policy Rate'!D129 -> 0.077787671 | N84: ='Policy Rate'!D141 -> 0.084439891 | P84: ='Policy Rate'!D150 -> 0.1245411
A87: Market Treasury Bills
A88: Fair Value through OCI/Available for Sale | C88: =((2*E88)+(2*G88)+(2*I88)+K88+M88+O88)/9 -> 0.64083918 | D88: =C88*D$91 -> 3.616144e+08 | E88: =F88/F$91 -> 0.63467472 | F88: 283446069 | G88: =H88/H$91 -> 0.52667347 | H88: 223185544 | I88: =J88/J$91 -> 0.65923 | J88: 222366674 | K88: =L88/L$91 -> 0.71417393 | L88: 279741535 | M88: =N88/N$91 -> 0.832618 | N88: 526523839 | O88: =P88/P$91 -> 0.57960432 | P88: 350931325
A89: Fair Value through Profit and Loss/Held for Tradng | C89: =((2*E89)+(2*G89)+(2*I89)+K89+M89+O89)/9 -> 0.1825997 | D89: =C89*D$91 -> 1.0303784e+08 | E89: =F89/F$91 -> 0.15861347 | F89: 70836862 | G89: =H89/H$91 -> 0.20982298 | H89: 88915542 | I89: =J89/J$91 -> 0.017425123 | J89: 5877716 | K89: =L89/L$91 -> 0.28481209 | L89: 111560738 | M89: =N89/N$91 -> 0.16691974 | N89: 105555277 | O89: =P89/P$91 -> 0.41994235 | P89: 254261260
A90: Amortized Cost/Held to Maturity | C90: =((2*E90)+(2*G90)+(2*I90)+K90+M90+O90)/9 -> 0.17656111 | D90: =C90*D$91 -> 99630365 | E90: =F90/F$91 -> 0.2067118 | F90: 92317600 | G90: =H90/H$91 -> 0.26350355 | H90: 111663463 | I90: =J90/J$91 -> 0.32334488 | J90: 109068345 | K90: =L90/L$91 -> 0.0010139866 | L90: 397178 | M90: =N90/N$91 -> 0.00046225365 | N90: 292316 | O90: =P90/P$91 -> 0.00045333102 | P90: 274477
D91: 5.6428261e+08 | F91: =SUM(F88:F90) -> 446600531 | H91: =SUM(H88:H90) -> 423764549 | J91: =SUM(J88:J90) -> 337312735 | L91: =SUM(L88:L90) -> 391699451 | N91: =SUM(N88:N90) -> 632371432 | P91: =SUM(P88:P90) -> 605467062
D92: =D39-D91 -> 39365983 | F92: =F39-F91 -> 0 | H92: =H39-H91 -> 0 | J92: =J39-J91 -> 0 | L92: =L39-L91 -> 0 | N92: =N39-N91 -> 0 | P92: =P39-P91 -> 0
A94: Pakistan Investment Bonds
A95: Fair Value through OCI/Available for Sale | C95: =((2*E95)+(2*G95)+(2*I95)+K95+M95+O95)/9 -> 0.74310274 | D95: =C95*D$98 -> 1.2622591e+09 | E95: =F95/F$98 -> 0.78050316 | F95: 1067225618 | G95: =H95/H$98 -> 0.7155819 | H95: 1113990814 | I95: =J95/J$98 -> 0.76113672 | J95: 906737321 | K95: =L95/L$98 -> 0.67942227 | L95: 801116563 | M95: =N95/N$98 -> 0.76629245 | N95: 795183721 | O95: =P95/P$98 -> 0.72776639 | P95: 453552332
A96: Fair Value through Profit and Loss/Held for Tradng | C96: =((2*E96)+(2*G96)+(2*I96)+K96+M96+O96)/9 -> 0.051326057 | D96: =C96*D$98 -> 87184150 | E96: =F96/F$98 -> 0.034810237 | F96: 47597984 | G96: =H96/H$98 -> 0.090534688 | H96: 140940974 | I96: =J96/J$98 -> 0.043974207 | J96: 52386192 | K96: =L96/L$98 -> 0.078289398 | L96: 92312154 | M96: =N96/N$98 -> 0.024741574 | N96: 25674397 | O96: =P96/P$98 -> 0.02026528 | P96: 12629554
A97: Amortized Cost/Held to Maturity | C97: =((2*E97)+(2*G97)+(2*I97)+K97+M97+O97)/9 -> 0.2055712 | D97: =C97*D$98 -> 3.4919009e+08 | E97: =F97/F$98 -> 0.1846866 | F97: 252532318 | G97: =H97/H$98 -> 0.19388341 | H97: 301830350 | I97: =J97/J$98 -> 0.19488907 | J97: 232170109 | K97: =L97/L$98 -> 0.24228833 | L97: 285685656 | M97: =N97/N$98 -> 0.20896598 | N97: 216844554 | O97: =P97/P$98 -> 0.25196833 | P97: 157029540
D98: 1.6986333e+09 | F98: =SUM(F95:F97) -> 1367355920 | H98: =SUM(H95:H97) -> 1556762138 | J98: =SUM(J95:J97) -> 1191293622 | L98: =SUM(L95:L97) -> 1179114373 | N98: =SUM(N95:N97) -> 1037702672 | P98: =SUM(P95:P97) -> 623211426
D99: =D40-D98 -> -2.3864601e+08 | F99: =F40-F98 -> 0 | H99: =H40-H98 -> 0 | J99: =J40-J98 -> 0 | L99: =L40-L98 -> 0 | N99: =N40-N98 -> 0 | P99: =P40-P98 -> 0
A101: Ijarah Sukuk
A102: Fair Value through OCI/Available for Sale | C102: =E102 -> 0.87934813 | D102: =C102*D$105 -> 1.5085037e+08 | E102: =F102/F$105 -> 0.87934813 | F102: 300205879 | H102: 213476351 | J102: 122587729 | L102: 119080826 | N102: 67355950 | P102: 4621073
A103: Fair Value through Profit and Loss/Held for Tradng | C103: =E103 -> 0.037830439 | D103: =C103*D$105 -> 6489734.3 | E103: =F103/F$105 -> 0.037830439 | F103: 12915158 | H103: 7794394
A104: Amortized Cost/Held to Maturity | C104: =E104 -> 0.082821428 | D104: =C104*D$105 -> 14207846 | E104: =F104/F$105 -> 0.082821428 | F104: 28274899
D105: 1.7154795e+08 | F105: =SUM(F102:F104) -> 341395936 | H105: =SUM(H102:H104) -> 221270745 | J105: =SUM(J102:J104) -> 122587729 | L105: =SUM(L102:L104) -> 119080826 | N105: =SUM(N102:N104) -> 67355950 | P105: =SUM(P102:P104) -> 4621073
D106: =D41-D105 -> 2.0758591e+08 | F106: =F41-F105 -> 0 | H106: =H41-H105 -> 0 | J106: =J41-J105 -> 0 | L106: =L41-L105 -> 0 | N106: =N41-N105 -> 0 | P106: =P41-P105 -> 0
A107: Foreign Securities
A108: Fair Value through OCI/Available for Sale | C108: =((2*E108)+(2*G108)+(2*I108)+K108+M108+O108)/9 -> 0.87504803 | D108: =C108*D$111 -> 1.5275267e+08 | E108: =F108/F$111 -> 0.90236845 | F108: =177985040+11052424+6459 -> 189043923 | G108: =H108/H$111 -> 0.90870811 | H108: =170658260+5600618+9462 -> 176268340 | I108: =J108/J$111 -> 0.88411683 | J108: =124562876+8107344+5461947+7565 -> 138139732 | K108: =L108/L$111 -> 0.84704359 | L108: =75344603+12577528+6162 -> 87928293 | M108: =N108/N$111 -> 0.79418031 | N108: =45041706+13750422+5592 -> 58797720 | O108: =P108/P$111 -> 0.8438216 | P108: =15699559+34055549+5912+349384 -> 50110404
A109: Fair Value through Profit and Loss/Held for Tradng | C109: =((2*E109)+(2*G109)+(2*I109)+K109+M109+O109)/9 -> 0.01333226 | D109: =C109*D$111 -> 2327344.6 | E109: =F109/F$111 -> 0.020713905 | F109: 4339511 | G109: =H109/H$111 -> 0.014874697 | H109: 2885347 | I109: =J109/J$111 -> 0.021039871 | J109: 3287396 | K109: =L109/L$111 -> 0.0031740523 | L109: 329486 | M109: =N109/N$111 -> 0.0017081212 | N109: 126462 | O109: =P109/P$111 -> 0.0018512229 | P109: 109935
A110: Amortized Cost/Held to Maturity | C110: =((2*E110)+(2*G110)+(2*I110)+K110+M110+O110)/9 -> 0.11161971 | D110: =C110*D$111 -> 19484882 | E110: =F110/F$111 -> 0.076917643 | F110: 16114053 | G110: =H110/H$111 -> 0.07641719 | H110: =14663737+159429 -> 14823166 | I110: =J110/J$111 -> 0.094843296 | J110: =14365073+145714+308100 -> 14818887 | K110: =L110/L$111 -> 0.14978236 | L110: =14672889+260893+614541 -> 15548323 | M110: =N110/N$111 -> 0.20411157 | N110: =13617532+1182691+311326 -> 15111549 | O110: =P110/P$111 -> 0.15432718 | P110: =7371115+1280682+512933 -> 9164730
D111: =D47 -> 1.745649e+08 | F111: =SUM(F108:F110) -> 209497487 | H111: =SUM(H108:H110) -> 193976853 | J111: =SUM(J108:J110) -> 156246015 | L111: =SUM(L108:L110) -> 103806102 | N111: =SUM(N108:N110) -> 74035731 | P111: =SUM(P108:P110) -> 59385069
D112: =D111-D47 -> 0 | F112: =F111-F47 -> 0 | H112: =H111-H47 -> 0 | J112: =J111-J47 -> 0 | L112: =L111-L47 -> 0 | N112: =N111-N47 -> 0 | P112: =P111-P47 -> 0
A113: Non-Government debt securities
A114: Fair Value through OCI/Available for Sale | C114: =E114 -> 0.6409412 | D114: =C114*D$117 -> 58297845 | E114: =F114/F$117 -> 0.6409412 | F114: =47551020+604922 -> 48155942 | G114: =H114/H$117 -> 0.67190113 | H114: =49614767+2234126 -> 51848893 | I114: =J114/J$117 -> 0.71934101 | J114: =49084350+2267322 -> 51351672 | K114: =L114/L$117 -> 0.67958667 | L114: =52060015+1425000 -> 53485015 | M114: =N114/N$117 -> 0.6877597 | N114: =47265405+1423501 -> 48688906 | O114: =P114/P$117 -> 0.12782757 | P114: =1722749+2015257 -> 3738006
A115: Fair Value through Profit and Loss/Held for Tradng | C115: =E115 -> 0.046477729 | D115: =C115*D$117 -> 4227457.2 | E115: =F115/F$117 -> 0.046477729 | F115: =2691019+801000 -> 3492019 | G115: =H115/H$117 -> 0 | I115: =J115/J$117 -> 0 | K115: =L115/L$117 -> 0 | M115: =N115/N$117 -> 0 | O115: =P115/P$117 -> 0
A116: Amortized Cost/Held to Maturity | C116: =E116 -> 0.31258107 | D116: =C116*D$117 -> 28431318 | E116: =F116/F$117 -> 0.31258107 | F116: =899081+22586125 -> 23485206 | G116: =H116/H$117 -> 0.32809887 | H116: =1899450+23419101 -> 25318551 | I116: =J116/J$117 -> 0.28065899 | J116: =1733442+18301991 -> 20035433 | K116: =L116/L$117 -> 0.32041333 | L116: =2365422+22851835 -> 25217257 | M116: =N116/N$117 -> 0.3122403 | N116: =4277922+17826657 -> 22104579 | O116: =P116/P$117 -> 0.87217243 | P116: =5799373+19705186 -> 25504559
...

Sheet P&L
A1: HABIB BANK LIMITED | D1: PKR | F1: PKR | H1: PKR | J1: PKR | L1: PKR | N1: PKR | P1: PKR
A2: CONSOLIDATED STATEMENT OF PROFIT AND LOSS ACCOUNT | D2: 25 Forecast | F2: 24 | H2: 23 | J2: 22 | L2: 21 | N2: 20 | P2: 19
A3: Mark-up / return / profit / interest earned | D3: =D45 -> 6.0357889e+08 | F3: 813192081 | H3: 712345078 | J3: 436101037 | L3: 262253962 | N3: 271237258 | P3: 258113896
A4: Mark-up / return / profit / interest expensed | D4: ='National Deposits'!C95 -> 3.3507174e+08 | F4: 567569845 | H4: 470212037 | J4: 270538340 | L4: 130834913 | N4: 141132940 | P4: 156790596
A5: Net mark-up / return / profit / interest income | D5: =D3-D4 -> 2.6850716e+08 | F5: 245622236 | H5: 242133041 | J5: 165562697 | L5: 131419049 | N5: 130104318 | P5: 101323300
A7: Non mark-up / interest income
A8: Fee and commission income | C8: {=AVERAGE( _xlfn._xlws.FILTER( CHOOSE({1,2,3,4,5}, E8, G8, I8, K8, M8), ISNUMBER(CHOOSE({1,2,3,4,5}, E8, G8, I8, K8, M8)) ) )} -> 0.20485125 | D8: =F8*(1+C8) -> 59667705 | E8: =F8/H8-1 -> 0.17213412 | F8: 49522881 | G8: =H8/J8-1 -> 0.3408439 | H8: 42250183 | I8: =J8/L8-1 -> 0.23892986 | J8: 31510143 | K8: =L8/N8-1 -> 0.35314472 | L8: 25433355 | M8: =N8/P8-1 -> -0.080796363 | N8: 18795739 | P8: 20447851
A9: Dividend income | C9: {=AVERAGE( _xlfn._xlws.FILTER( CHOOSE({1,2,3,4,5}, E9, G9, I9, K9, M9), ISNUMBER(CHOOSE({1,2,3,4,5}, E9, G9, I9, K9, M9)) ) )} -> 0.44355945 | D9: =F9*(1+C9) -> 4449656.5 | E9: =F9/H9-1 -> 0.33961822 | F9: 3082420 | G9: =H9/J9-1 -> 0.52519118 | H9: 2300969 | I9: =J9/L9-1 -> 0.65101136 | J9: 1508643 | K9: =L9/N9-1 -> 0.8674911 | L9: 913769 | M9: =N9/P9-1 -> -0.16551463 | N9: 489303 | P9: 586353
A10: Share of profit of associates and joint venture | C10: {=AVERAGE( _xlfn._xlws.FILTER( CHOOSE({1,2,3,4,5}, E10, G10, I10, K10, M10), ISNUMBER(CHOOSE({1,2,3,4,5}, E10, G10, I10, K10, M10)) ) )} -> 0.086358077 | D10: =F10*(1+C10) -> 5174323.5 | E10: =F10/H10-1 -> 0.076945166 | F10: 4763000 | G10: =H10/J10-1 -> 0.46038093 | H10: 4422695 | I10: =J10/L10-1 -> 0.17127895 | J10: 3028453 | K10: =L10/N10-1 -> -0.1273991 | L10: 2585595 | M10: =N10/P10-1 -> -0.14941556 | N10: 2963090 | P10: 3483593
A11: Foreign exchange income | C11: {=AVERAGE( _xlfn._xlws.FILTER( CHOOSE({1,2,3,4,5}, E11, G11, I11, K11, M11), ISNUMBER(CHOOSE({1,2,3,4,5}, E11, G11, I11, K11, M11)) ) )} -> -0.58980423 | D11: =F11*(1+C11) -> 3239123.2 | E11: =F11/H11-1 -> 0.71504793 | F11: 7896530 | G11: =H11/J11-1 -> -0.97672113 | H11: 4604262 | I11: =J11/L11-1 -> #DIV/0! | J11: =F50+F51+F52 -> 1.9778719e+08 | K11: =L11/N11-1 -> -1 | L11: =G50+G51+G52 -> 0 | M11: =N11/P11-1 -> -1.0975437 | N11: -161688 | P11: 1657595
A12: Income / (loss) from derivatives | C12: {=AVERAGE( _xlfn._xlws.FILTER( CHOOSE({1,2,3,4,5}, E12, G12, I12, K12, M12), ISNUMBER(CHOOSE({1,2,3,4,5}, E12, G12, I12, K12, M12)) ) )} -> 0.052947187 | D12: =F12*(1+C12) -> 6076944.6 | E12: =F12/H12-1 -> -4.7344177 | F12: 5771367 | G12: =H12/J12-1 -> -0.40970076 | H12: -1545453 | I12: =J12/L12-1 -> 13.377335 | J12: -2618084 | K12: =L12/N12-1 -> -1.1689307 | L12: -182098 | M12: =N12/P12-1 -> -6.7995502 | N12: 1077945 | P12: -185867
A13: Gain on securities - net | D13: {=AVERAGE( _xlfn._xlws.FILTER( CHOOSE({1,2,3,4,5}, F13, H13, J13, L13, N13), ISNUMBER(CHOOSE({1,2,3,4,5}, F13, H13, J13, L13, N13)) ) )} -> 4070829.8 | F13: 10462735 | H13: 945981 | J13: 866175 | L13: 1024384 | N13: 7054874 | P13: -2657256
A14: Other income | D14: {=AVERAGE( _xlfn._xlws.FILTER( CHOOSE({1,2,3,4,5}, F14, H14, J14, L14, N14), ISNUMBER(CHOOSE({1,2,3,4,5}, F14, H14, J14, L14, N14)) ) )} -> 4301203.8 | F14: 15013202 | H14: 4472468 | J14: 488991 | L14: 1155761 | N14: 375597 | P14: 829310
A15: Total non mark-up / interest income | D15: =SUM(D8:D14) -> 86979786 | F15: 96512135 | H15: 57451105 | J15: 46731737 | L15: 36311360 | N15: 30594860 | P15: 24161579
A16: Total income | D16: =D5+D15 -> 3.5548694e+08 | F16: 342134371 | H16: 299584146 | J16: 212294434 | L16: 167730409 | N16: 160699178 | P16: 125484879
A18: Non mark-up / interest expenses
A19: Operating expenses | C19: {=AVERAGE( _xlfn._xlws.FILTER( CHOOSE({1,2,3,4,5}, E19, G19, I19, K19, M19), ISNUMBER(CHOOSE({1,2,3,4,5}, E19, G19, I19, K19, M19)) ) )} -> 0.16711678 | D19: =F19*(1+C19) -> 2.2464016e+08 | E19: =F19/H19-1 -> 0.13133686 | F19: 192474447 | G19: =H19/J19-1 -> 0.36314049 | H19: 170130095 | I19: =J19/L19-1 -> 0.30299625 | J19: 124807455 | K19: =L19/N19-1 -> 0.018789555 | L19: 95784969 | M19: =N19/P19-1 -> 0.019320771 | N19: 94018405 | P19: 92236328
A20: Workers' Welfare Fund | C20: {=AVERAGE( _xlfn._xlws.FILTER( CHOOSE({1,2,3,4,5}, E20, G20, I20, K20, M20), ISNUMBER(CHOOSE({1,2,3,4,5}, E20, G20, I20, K20, M20)) ) )} -> 0.36367536 | D20: =F20*(1+C20) -> 3224542.7 | E20: =F20/H20-1 -> 0.03604836 | F20: 2364597 | G20: =H20/J20-1 -> 0.5228756 | H20: 2282323 | I20: =J20/L20-1 -> 0.17708325 | J20: 1498693 | K20: =L20/N20-1 -> 0.14732953 | L20: 1273226 | M20: =N20/P20-1 -> 0.93504007 | N20: 1109730 | P20: 573492
A21: Other charges | D21: {=AVERAGE( _xlfn._xlws.FILTER( CHOOSE({1,2,3,4,5}, F21, H21, J21, L21, N21), ISNUMBER(CHOOSE({1,2,3,4,5}, F21, H21, J21, L21, N21)) ) )} -> 413338.2 | F21: 357160 | H21: 354953 | J21: 476587 | L21: 557198 | N21: 320793 | P21: 480056
A22: Total non mark-up / interest expenses | D22: =SUM(D19:D21) -> 2.2827804e+08 | F22: 195196204 | H22: 172767371 | J22: 126782735 | L22: 97615393 | N22: 95448928 | P22: 93289876
A24: Profit before credit loss allowance and taxation | D24: =D16-D22 -> 1.272089e+08 | F24: 146938167 | H24: 126816775 | J24: 85511699 | L24: 70115016 | N24: 65250250 | P24: 32195003
A25: Credit loss allowance and write offs - net | D25: ='Credit Loss Allowance'!D15 -> 18767336 | F25: 26603787 | H25: 13265779 | J25: 8481761 | L25: 8087105 | N25: 12219614 | P25: 3314081
A26: Profit before taxation | D26: =D24-D25 -> 1.0844157e+08 | F26: 120334380 | H26: 113550996 | J26: 77029938 | L26: 62027911 | N26: 53030636 | P26: 28880922
A27: Taxation | C27: 0.54 | D27: =D26*C27 -> 58558446 | E27: =F27/F26 -> 0.51963305 | F27: 62529721 | G27: =H27/H26 -> 0.49135263 | H27: 55793580 | I27: =J27/J26 -> 0.55344207 | J27: 42631608 | K27: =L27/L26 -> 0.4275662 | L27: 26521038 | M27: =N27/N26 -> 0.41706622 | N27: 22117287 | P27: 13381127
A28: Profit after taxation | D28: =D26-D27 -> 49883121 | F28: 57804659 | H28: 57757416 | J28: 34398330 | L28: 35506873 | N28: 30913349 | P28: 15499795
A30: Attributable to:
A31: Equity holders of the Bank | C31: =AVERAGE(E31,G31,I31,K31,M31,O31) -> 0.99587183 | D31: =D$28*C31 -> 49677195 | E31: =F31/F$33 -> 1.0112986 | F31: 58457771 | G31: =H31/H$33 -> 0.99859107 | H31: 57676040 | I31: =J31/J$33 -> 0.99045759 | J31: 34070087 | K31: =L31/L$33 -> 0.98634011 | L31: 35021853 | M31: =N31/N$33 -> 0.99931816 | N31: 30892271 | O31: =P31/P$33 -> 0.98922547 | P31: 15332792
A32: Non-controlling interest | C32: =AVERAGE(E32,G32,I32,K32,M32,O32) -> 0.0041281658 | D32: =D$28*C32 -> 205925.79 | E32: =F32/F$33 -> -0.011298605 | F32: -653112 | G32: =H32/H$33 -> 0.0014089273 | H32: 81376 | I32: =J32/J$33 -> 0.0095424109 | J32: 328243 | K32: =L32/L$33 -> 0.013659891 | L32: 485020 | M32: =N32/N$33 -> 0.00068184136 | N32: 21078 | O32: =P32/P$33 -> 0.01077453 | P32: 167003
A33: Profit after taxation | D33: =SUM(D31:D32) -> 49883121 | F33: 57804659 | H33: 57757416 | J33: 34398330 | L33: 35506873 | N33: 30913349 | P33: 15499795
A35: Share Outstanding | D35: =F35 -> 1466852 | F35: 1466852 | H35: 1466852 | J35: 1466852 | L35: 1466852 | N35: 1466852 | P35: 1466852
A36: Basic and diluted earnings per share | D36: =D31/D35 -> 33.866535 | F36: 39.85 | H36: 39.32 | J36: 23.23 | L36: 23.88 | N36: 21.06 | P36: 10.45
A37: Cash Dividend per share | D37: =D36*D38 -> 10.953909 | F37: 16.25 | H37: 9.75 | J37: 6.75 | L37: 7.5 | N37: 4.25 | P37: 5
A38: Dividend/Earning | D38: =AVERAGE(F38,H38,J38,L38,N38,P38) -> 0.32344346 | F38: =F37/F36 -> 0.40777917 | H38: =H37/H36 -> 0.24796541 | J38: =J37/J36 -> 0.29057254 | L38: =L37/L36 -> 0.31407035 | N38: =N37/N36 -> 0.20180437 | P38: =P37/P36 -> 0.4784689
A39: Profit Retained | D39: =D33*(1-D38) -> 33748752 | F39: =F33*(1-F38) -> 34233123 | H39: =H33*(1-H38) -> 43435575 | J39: =J33*(1-J38) -> 24403120 | L39: =L33*(1-L38) -> 24355217 | N39: =N33*(1-N38) -> 24674900 | P39: =P33*(1-P38) -> 8083625.1
A41: Loans and advances | D41: =D58 -> 2.6124776e+08 | F41: 312318372 | H41: 300113714 | J41: 192939922 | L41: 111742121 | N41: 116793732 | P41: 132394180
A42: Investments | D42: =D103 -> 3.1030041e+08 | F42: 472523900 | H42: 370788429 | J42: 226000345 | L42: 143232732 | N42: 148742484 | P42: 110142418
A43: Lendings to financial institutions | D43: =D74 -> 17469046 | F43: 15222196 | H43: 30364394 | J43: 15354518 | L43: 6849788 | N43: 5027219 | P43: 14180501
A44: Balances with banks | D44: =D78 -> 14561672 | F44: 13127613 | H44: 11078541 | J44: 1806252 | L44: 429321 | N44: 673823 | P44: 1396797
A45: Gross Interest Income | D45: =SUM(D41:D44) -> 6.0357889e+08 | F45: =SUM(F41:F44) -> 813192081 | H45: =SUM(H41:H44) -> 712345078 | J45: 436101037 | L45: 262253962 | N45: 271237258 | P45: 258113896
C50: Estimated Spread
A51: Corporate and Commercial | C51: 0.02 | D51: =(D$62+$C51)*D64 -> 1.244682e+08 | F51: =(F$62+$C51)*F64 -> 1.5405038e+08 | H51: =(H$62+$C51)*H64 -> 1.3922393e+08 | J51: =(J$62+$C51)*J64 -> 1.0719246e+08 | L51: =(L$62+$C51)*L64 -> 59936290 | N51: =(N$62+$C51)*N64 -> 67139539 | P51: =(P$62+$C51)*P64 -> 86852785
A52: Consumer and Retail | C52: 0.05 | D52: =(D$62+$C52)*D65 -> 41101816 | F52: =(F$62+$C52)*F65 -> 43736819 | H52: =(H$62+$C52)*H65 -> 45446216 | J52: =(J$62+$C52)*J65 -> 31677228 | L52: =(L$62+$C52)*L65 -> 20324988 | N52: =(N$62+$C52)*N65 -> 19946489 | P52: =(P$62+$C52)*P65 -> 24521797
A53: Agriculture | C53: 0 | D53: =(D$62+$C53)*D66 -> 5678046.9 | F53: =(F$62+$C53)*F66 -> 7658093.9 | H53: =(H$62+$C53)*H66 -> 7536668.5 | J53: =(J$62+$C53)*J66 -> 4418169.8 | L53: =(L$62+$C53)*L66 -> 1926498.2 | N53: =(N$62+$C53)*N66 -> 2331657.7 | P53: =(P$62+$C53)*P66 -> 3453586
A54: SME | C54: 0.04 | D54: =(D$62+$C54)*D67 -> 13572185 | F54: =(F$62+$C54)*F67 -> 16653710 | H54: =(H$62+$C54)*H67 -> 18021722 | J54: =(J$62+$C54)*J67 -> 0 | L54: =(L$62+$C54)*L67 -> 0 | N54: =(N$62+$C54)*N67 -> 0 | P54: =(P$62+$C54)*P67 -> 0
A55: International | C55: 0.02 | D55: =(D$62+$C55)*D68 -> 40958642 | F55: =(F$62+$C55)*F68 -> 48636559 | H55: =(H$62+$C55)*H68 -> 54805343 | J55: =(J$62+$C55)*J68 -> 29267565 | L55: =(L$62+$C55)*L68 -> 18971139 | N55: =(N$62+$C55)*N68 -> 18175775 | P55: =(P$62+$C55)*P68 -> 23358243
A56: Microfinance | C56: 0.08 | D56: =(D$62+$C56)*D69 -> 13324717 | F56: =(F$62+$C56)*F69 -> 13503138 | H56: =(H$62+$C56)*H69 -> 20006493 | J56: =(J$62+$C56)*J69 -> 14493608 | L56: =(L$62+$C56)*L69 -> 7397074.4 | N56: =(N$62+$C56)*N69 -> 6264109.3 | P56: =(P$62+$C56)*P69 -> 5736034.8
A57: Financial Institution | C57: 0 | D57: =(D$62+$C57)*D70 -> 22144157 | F57: =(F$62+$C57)*F70 -> 28079678 | H57: =(H$62+$C57)*H70 -> 15073337 | J57: =(J$62+$C57)*J70 -> 5890893 | L57: =(L$62+$C57)*L70 -> 3186131.6 | N57: =(N$62+$C57)*N70 -> 2936161.5 | P57: =(P$62+$C57)*P70 -> 4049031.9
A58: Income from Advances | D58: =SUM(D51:D57) -> 2.6124776e+08 | F58: =F41 -> 312318372 | H58: =H41 -> 300113714 | J58: =J41 -> 192939922 | L58: =L41 -> 111742121 | N58: =N41 -> 116793732 | P58: =P41+P43+P44 -> 147971478
A59: Advances | D59: =D71 -> 2.7902661e+09 | F59: =F71 -> 2435434872 | H59: =H71 -> 1861344592 | J59: =J71 -> 1.7824979e+09 | L59: =L71 -> 1.5070471e+09 | N59: =N71 -> 1223510222 | P59: =P71 -> 1.1692909e+09
A60: Yield on Advances | D60: =D58/D59 -> 0.09362826 | E60: =SUM(F51:F57)/F59 -> 0.12823926 | F60: =F58/F59 -> 0.12823926 | H60: =H58/H59 -> 0.1612349 | J60: =J58/J59 -> 0.10824132 | L60: =L58/L59 -> 0.074146403 | N60: =N58/N59 -> 0.095457913 | P60: =P58/P59 -> 0.12654804
A61: Weighted Policy Rate | D61: 0.115 | F61: ='Policy Rate'!D103 -> 0.18032787 | H61: ='Policy Rate'!D112 -> 0.21386301 | J61: ='Policy Rate'!D121 -> 0.14582877 | L61: ='Policy Rate'!D129 -> 0.077787671 | N61: ='Policy Rate'!D141 -> 0.084439891 | P61: ='Policy Rate'!D150 -> 0.1245411
A62: Base rates on top of which the estimated spread is added based on loan category | D62: 0.07 | F62: =(F58-(F64*$C51)-(F65*$C52)-(F67*$C54)-(F68*$C55)-(F69*$C56))/(F64+F65+F66+F67+F68+F69+F70) -> 0.10481487 | H62: =(H58-(H64*$C51)-(H65*$C52)-(H67*$C54)-(H68*$C55)-(H69*$C56))/(H64+H65+H66+H67+H68+H69+H70) -> 0.13496818 | J62: =(J58-(J64*$C51)-(J65*$C52)-(J67*$C54)-(J68*$C55)-(J69*$C56))/(J64+J65+J66+J67+J68+J69+J70) -> 0.082621317 | L62: =(L58-(L64*$C51)-(L65*$C52)-(L67*$C54)-(L68*$C55)-(L69*$C56))/(L64+L65+L66+L67+L68+L69+L70) -> 0.049166403 | N62: =(N58-(N64*$C51)-(N65*$C52)-(N67*$C54)-(N68*$C55)-(N69*$C56))/(N64+N65+N66+N67+N68+N69+N70) -> 0.070581913 | P62: =(P58-(P64*$C51)-(P65*$C52)-(P67*$C54)-(P68*$C55)-(P69*$C56))/(P64+P65+P66+P67+P68+P69+P70) -> 0.10205104
A64: Corporate and Commercial | D64: ='National Advances'!C18 -> 1.38298e+09 | E64: =F64/F$71 -> 0.50678051 | F64: ='National Advances'!F18 -> 1.2342309e+09 | G64: =H64/H$71 -> 0.48266366 | H64: ='National Advances'!I18 -> 8.9840339e+08 | J64: ='National Advances'!L18 -> 1.0445438e+09 | L64: ='National Advances'!O18 -> 8.6655208e+08 | N64: ='National Advances'!R18 -> 7.4120249e+08 | P64: ='National Advances'!U18 -> 7.1161037e+08
A65: Consumer and Retail | D65: ='National Advances'!C19 -> 3.4251513e+08 | E65: =F65/F$71 -> 0.116 | F65: ='National Advances'!F19 -> 2.8251045e+08 | G65: =H65/H$71 -> 0.132 | H65: ='National Advances'!I19 -> 2.4569749e+08 | J65: ='National Advances'!L19 -> 2.3885472e+08 | L65: ='National Advances'!O19 -> 2.0495841e+08 | N65: ='National Advances'!R19 -> 1.6541858e+08 | P65: ='National Advances'!U19 -> 1.6127346e+08
A66: Agriculture | D66: ='National Advances'!C20 -> 81114956 | E66: =F66/F$71 -> 0.03 | F66: ='National Advances'!F20 -> 73063046 | G66: =H66/H$71 -> 0.03 | H66: ='National Advances'!I20 -> 55840338 | J66: ='National Advances'!L20 -> 53474938 | L66: ='National Advances'!O20 -> 39183225 | N66: ='National Advances'!R20 -> 33034776 | P66: ='National Advances'!U20 -> 33841753
A67: SME | D67: ='National Advances'!C21 -> 1.233835e+08 | E67: =F67/F$71 -> 0.047219493 | F67: ='National Advances'!F21 -> 115000000 | G67: =H67/H$71 -> 0.055336342 | H67: ='National Advances'!I21 -> 103000000 | J67: ='National Advances'!L21 -> 0 | L67: ='National Advances'!O21 -> 0 | N67: ='National Advances'!R21 -> 0 | P67: ='National Advances'!U21 -> 0
A68: International | D68: ='National Advances'!C22 -> 4.5509602e+08 | E68: =F68/F$71 -> 0.16 | F68: ='National Advances'!F22 -> 3.8966958e+08 | G68: =H68/H$71 -> 0.19 | H68: ='National Advances'!I22 -> 3.5365547e+08 | J68: ='National Advances'!L22 -> 2.8519967e+08 | L68: ='National Advances'!O22 -> 2.7428257e+08 | N68: ='National Advances'!R22 -> 2.0065568e+08 | P68: ='National Advances'!U22 -> 1.9138095e+08
A69: Microfinance | D69: ='National Advances'!C23 -> 88831447 | E69: =F69/F$71 -> 0.03 | F69: ='National Advances'!F23 -> 73063046 | G69: =H69/H$71 -> 0.05 | H69: ='National Advances'!I23 -> 93067230 | J69: ='National Advances'!L23 -> 89124896 | L69: ='National Advances'!O23 -> 57267790 | N69: ='National Advances'!R23 -> 41599348 | P69: ='National Advances'!U23 -> 31507839
A70: Financial Institution | D70: ='National Advances'!C24 -> 3.163451e+08 | E70: =F70/F$71 -> 0.11 | F70: ='National Advances'!F24 -> 2.6789784e+08 | G70: =H70/H$71 -> 0.06 | H70: ='National Advances'!I24 -> 1.1168068e+08 | J70: ='National Advances'!L24 -> 71299917 | L70: ='National Advances'!O24 -> 64803025 | N70: ='National Advances'!R24 -> 41599348 | P70: ='National Advances'!U24 -> 39676538
A71: Gross Advances | D71: ='National Advances'!C25 -> 2.7902661e+09 | F71: ='National Advances'!F25 -> 2435434872 | H71: ='National Advances'!I25 -> 1861344592 | J71: ='National Advances'!L25 -> 1.7824979e+09 | L71: ='National Advances'!O25 -> 1.5070471e+09 | N71: ='National Advances'!R25 -> 1223510222 | P71: ='National Advances'!U25 -> 1.1692909e+09
A73: Lendings to financial institutions | D73: =SOFP!D6 -> 1.5880951e+08 | F73: =SOFP!F6 -> 84293922 | H73: =SOFP!H6 -> 88598160 | J73: =SOFP!J6 -> 254593287 | L73: =SOFP!L6 -> 93742432 | N73: =SOFP!N6 -> 30154193 | P73: =SOFP!P6 -> 45303199
A74: Income from Lendings to financial institutions | D74: =D75*D73 -> 17469046 | F74: =F43 -> 15222196 | H74: =H43 -> 30364394 | J74: =J43 -> 15354518 | L74: =L43 -> 6849788 | N74: =N43 -> 5027219 | P74: =P43 -> 14180501
A75: Yield % | D75: 0.11 | F75: =F74/F73 -> 0.18058474 | H75: =H74/H73 -> 0.34272037 | J75: =J74/J73 -> 0.060309988 | L75: =L74/L73 -> 0.073070304 | N75: =N74/N73 -> 0.16671708 | P75: =P74/P73 -> 0.31301324
A77: Balances with other banks | D77: =SOFP!D5 -> 72808358 | F77: =SOFP!F5 -> 51324612 | H77: =SOFP!H5 -> 56603548 | J77: =SOFP!J5 -> 41513022 | L77: =SOFP!L5 -> 64438075 | N77: =SOFP!N5 -> 56533829 | P77: =SOFP!P5 -> 41248554
A78: Income from Balances with other banks | D78: =D79*D77 -> 14561672 | F78: =F44 -> 13127613 | H78: =H44 -> 11078541 | J78: =J44 -> 1806252 | L78: =L44 -> 429321 | N78: =N44 -> 673823 | P78: =P44 -> 1396797
A79: Yield % | D79: 0.2 | F79: =F78/F77 -> 0.25577618 | H79: =H78/H77 -> 0.19572167 | J79: =J78/J77 -> 0.043510492 | L79: =L78/L77 -> 0.0066625361 | N79: =N78/N77 -> 0.011918934 | P79: =P78/P77 -> 0.033862933
A81: Surplus/deficit from FVOCI (Not Added)/AFS | D81: =((2*F81)+(2*H81)+(2*J81)+L81+N81+P81)/9 -> 1681638.8 | F81: 7011503 | H81: 133734 | J81: -396299 | L81: 108423 | N81: 1445950 | P81: 82500
A82: Surplus/deficit from FVPL/HFT | D82: =((2*F82)+(2*H82)+(2*J82)+L82+N82+P82)/9 -> 5701 | F82: 154602 | H82: -34842 | J82: -7865 | L82: -31517 | N82: -13658 | P82: -127306
A83: Imputed Interest | D83: =(D112*C84)-D82-D81 -> 62640877 | F83: =(F112*E84)-F82-F81 -> 73101619 | H83: =(H112*G84)-H82-H81 -> 90118400 | J83: =(J112*I84)-J82-J81 -> 49064942 | L83: =(L112*K84)-L82-L81 -> 32023702 | N83: =(N112*M84)-N82-N81 -> 53373033 | P83: =(P112*O84)-P82-P81 -> 78715063
A84: Market Treasury Bills | C84: 0.114 | D84: =D83+D82 -> 62646578 | E84: ='Market Treasury Bills'!E707 -> 0.17973047 | F84: =F83+F82 -> 73256221 | G84: ='Market Treasury Bills'!E679 -> 0.21289485 | H84: =H83+H82 -> 90083558 | I84: ='Market Treasury Bills'!E651 -> 0.14426013 | J84: =J83+J82 -> 49057077 | K84: ='Market Treasury Bills'!E623 -> 0.08195214 | L84: =L83+L82 -> 31992185 | M84: ='Market Treasury Bills'!E595 -> 0.086666352 | N84: =N83+N82 -> 53359375 | O84: ='Market Treasury Bills'!E567 -> 0.12993317 | P84: =P83+P82 -> 78587757
A85: Surplus/deficit from FVOCI (Not Added)/AFS | D85: =((2*F85)+(2*H85)+(2*J85)+L85+N85+P85)/9 -> -10149101 | F85: 7739668 | H85: -28598476 | J85: -29604154 | L85: -4943247 | N85: 10689727 | P85: 3837538
A86: Surplus/deficit from FVPL/HFT | D86: =((2*F86)+(2*H86)+(2*J86)+L86+N86+P86)/9 -> 56307.333 | F86: 156510 | H86: 100654 | J86: -85104 | L86: 110414 | N86: 19066 | P86: 33166
A87: Coupon Income | C87: =((2*E87)+(2*G87)+(2*I87)+K87+M87+O87)/9 -> 0.096555556 | D87: =D116*C87 -> 1.6401248e+08 | E87: ='Pakistan Investment Bonds'!J499 -> 0.126 | F87: =F116*E87 -> 1.7228685e+08 | G87: ='Pakistan Investment Bonds'!J431 -> 0.10916667 | H87: =H116*G87 -> 1.6994653e+08 | I87: ='Pakistan Investment Bonds'!J345 -> 0.095833333 | J87: =J116*I87 -> 1.1416564e+08 | K87: ='Pakistan Investment Bonds'!$J260-0.015 -> 0.076666667 | L87: =L116*K87 -> 90398769 | M87: ='Pakistan Investment Bonds'!$J174-0.0175 -> 0.0795 | N87: =N116*M87 -> 82497362 | O87: ='Pakistan Investment Bonds'!$J100-0.04 -> 0.050833333 | P87: =P116*O87 -> 31679914
A88: Pakistan Investment Bonds | D88: =D86+D87 -> 1.6406879e+08 | E88: =F88/F116 -> 0.12611446 | F88: =F86+F87 -> 1.7244336e+08 | G88: =H88/H116 -> 0.10923132 | H88: =H86+H87 -> 1.7004719e+08 | I88: =J88/J116 -> 0.095761895 | J88: =J86+J87 -> 1.1408053e+08 | K88: =L88/L116 -> 0.076760308 | L88: =L86+L87 -> 90509183 | M88: =N88/N116 -> 0.079518373 | N88: =N86+N87 -> 82516428 | O88: =P88/P116 -> 0.050886551 | P88: =P86+P87 -> 31713080
A89: Surplus/deficit from FVOCI (Not Added)/AFS | D89: =((2*F89)+(2*H89)+(2*J89)+L89+N89+P89)/9 -> 1851665.1 | F89: 12551056 | H89: -992900 | J89: -2772531 | L89: -537141 | N89: -322645 | P89: -46478
A90: Surplus/deficit from FVPL/HFT | D90: =(F90+H90)/2 -> 200481 | F90: 104464 | H90: 296498
A91: Coupon Income | C91: 0.105 | D91: =D120*C91 -> 18012535 | E91: =('Ijara Sukuk VRR'!T14+'Ijara Sukuk FRR'!T14)/2 -> 0.16925 | F91: =F120*E91 -> 57781262 | G91: =('Ijara Sukuk VRR'!T13+'Ijara Sukuk FRR'!T13)/2 -> 0.1985492 | H91: =H120*G91 -> 43933129 | I91: =('Ijara Sukuk VRR'!T12+'Ijara Sukuk FRR'!T12)/2 -> 0.134133 | J91: =J120*I91 -> 16443060 | K91: =('Ijara Sukuk VRR'!T11+'Ijara Sukuk FRR'!T11)/2 -> 0.092288667 | L91: =L120*K91 -> 10989811 | M91: =('Ijara Sukuk VRR'!T10+'Ijara Sukuk FRR'!T10)/2 -> 0.0768595 | N91: =N120*M91 -> 5176944.6 | O91: =('Ijara Sukuk VRR'!T9+'Ijara Sukuk FRR'!T9)/2 -> 0.122 | P91: =P120*O91 -> 563770.91
A92: Ijarah Sukuk | D92: =D90+D91 -> 18213016 | E92: =F92/F120 -> 0.16955599 | F92: =F90+F91 -> 57885726 | G92: =H92/H120 -> 0.19988918 | H92: =H90+H91 -> 44229627 | I92: =J92/J120 -> 0.134133 | J92: =J90+J91 -> 16443060 | K92: =L92/L120 -> 0.092288667 | L92: =L90+L91 -> 10989811 | M92: =N92/N120 -> 0.0768595 | N92: =N90+N91 -> 5176944.6 | O92: =P92/P120 -> 0.122 | P92: =P90+P91 -> 563770.91
A93: Government of Pakistan US Dollar Bonds | C93: =D61 -> 0.115 | D93: =D121*C93 -> 2728451.1 | E93: =F61 -> 0.18032787 | F93: =F121*E93 -> 2372427.7 | G93: =H61 -> 0.21386301 | H93: =H121*G93 -> 4985518.3 | I93: =J61 -> 0.14582877 | J93: =J121*I93 -> 1946415.3 | K93: =L61-0.01 -> 0.067787671 | L93: =L121*K93 -> 1116414.2 | M93: =N61-0.015 -> 0.069439891 | N93: =N121*M93 -> 791462.33 | O93: =P61-0.04 -> 0.084541096 | P93: =P121*O93 -> 421287.73
A94: Other Federal Government securities | C94: =D61 -> 0.115 | D94: =D122*C94 -> 1235956.1 | E94: =F61 -> 0.18032787 | F94: =F122*E94 -> 465376.64 | G94: =H61 -> 0.21386301 | H94: =H122*G94 -> 1185476.5 | I94: =J61 -> 0.14582877 | J94: =J122*I94 -> 683362.35 | K94: =L61-0.01 -> 0.067787671 | L94: =L122*K94 -> 800580.53 | M94: =N61-0.015 -> 0.069439891 | N94: =N122*M94 -> 786374.68 | O94: =P61-0.04 -> 0.084541096 | P94: =P122*O94 -> 912536.59
A95: Federal Government securities | C95: =D95/D103 -> 0.80210268 | D95: =D94+D93+D92+D88+D84 -> 2.4889279e+08 | E95: =F95/F103 -> 0.64848171 | F95: =F94+F93+F92+F88+F84 -> 3.0642311e+08 | G95: =H95/H103 -> 0.83748937 | H95: =H94+H93+H92+H88+H84 -> 3.1053137e+08 | I95: =J95/J103 -> 0.8062397 | J95: =J94+J93+J92+J88+J84 -> 1.8221045e+08 | K95: =L95/L103 -> 0.94537171 | L95: =L94+L93+L92+L88+L84 -> 1.3540817e+08 | M95: =N95/N103 -> 0.95890953 | N95: =N94+N93+N92+N88+N84 -> 1.4263059e+08 | O95: =P95/P103 -> 1.0186669 | P95: =P94+P93+P92+P88+P84 -> 1.1219843e+08
A96: Shares | D96: =((2*F96)+(2*H96)+(2*J96)+L96+N96+P96)/9 -> 4251769.8 | F96: =(F$103-F$95-F$97)*(E124/(E$131-E$123-E$125)) -> 14009694 | H96: =(H$103-H$95-H$97)*(G124/(G$131-G$123-G$125)) -> 3741213.5 | J96: =(J$103-J$95-J$97)*(I124/(I$131-I$123-I$125)) -> 1481728.7 | L96: =(L$103-L$95-L$97)*(K124/(K$131-K$123-K$125)) -> 200139.49 | N96: =(N$103-N$95-N$97)*(M124/(M$131-M$123-M$125)) -> 109780.07 | P96: =(P$103-P$95-P$97)*(O124/(O$131-O$123-O$125)) -> -509262.71
A97: Non-Government debt securities | C97: =D61 -> 0.115 | D97: =D125*C97 -> 10460011 | E97: =F61 -> 0.18032787 | F97: =F125*E97 -> 13548604 | G97: =H61 -> 0.21386301 | H97: =H125*G97 -> 16503262 | I97: =J61 -> 0.14582877 | J97: =J125*I97 -> 10410294 | K97: =L61-0.01 -> 0.067787671 | L97: =L125*K97 -> 5335043.7 | M97: =N61-0.015 -> 0.069439891 | N97: =N125*M97 -> 4915891.9 | O97: =P61-0.04 -> 0.084541096 | P97: =P125*O97 -> 2472198.5
A98: Foreign securities | D98: =((2*F98)+(2*H98)+(2*J98)+L98+N98+P98)/9 -> 38142518 | F98: =(F$103-F$95-F$97)*(E126/(E$131-E$123-E$125)) -> 1.1333971e+08 | H98: =(H$103-H$95-H$97)*(G126/(G$131-G$123-G$125)) -> 33351332 | J98: =(J$103-J$95-J$97)*(I126/(I$131-I$123-I$125)) -> 25051716 | L98: =(L$103-L$95-L$97)*(K126/(K$131-K$123-K$125)) -> 1699286.1 | N98: =(N$103-N$95-N$97)*(M126/(M$131-M$123-M$125)) -> 752754.61 | P98: =(P$103-P$95-P$97)*(O126/(O$131-O$123-O$125)) -> -2654886.6
A99: National Investment Unit Trust units | D99: =((2*F99)+(2*H99)+(2*J99)+L99+N99+P99)/9 -> 14570.832 | F99: =(F$103-F$95-F$97)*(E127/(E$131-E$123-E$125)) -> 51062.449 | H99: =(H$103-H$95-H$97)*(G127/(G$131-G$123-G$125)) -> 8724.8212 | J99: =(J$103-J$95-J$97)*(I127/(I$131-I$123-I$125)) -> 6119.9898 | L99: =(L$103-L$95-L$97)*(K127/(K$131-K$123-K$125)) -> 760.34489 | N99: =(N$103-N$95-N$97)*(M127/(M$131-M$123-M$125)) -> 476.2332 | P99: =(P$103-P$95-P$97)*(O127/(O$131-O$123-O$125)) -> -1913.6084
A100: Real Estate Investment Trust units | D100: =((2*F100)+(2*H100)+(2*J100)+L100+N100+P100)/9 -> 539330.94 | F100: =(F$103-F$95-F$97)*(E128/(E$131-E$123-E$125)) -> 1881546.6 | H100: =(H$103-H$95-H$97)*(G128/(G$131-G$123-G$125)) -> 282608.9 | J100: =(J$103-J$95-J$97)*(I128/(I$131-I$123-I$125)) -> 263462.59 | L100: =(L$103-L$95-L$97)*(K128/(K$131-K$123-K$125)) -> 995.28439 | N100: =(N$103-N$95-N$97)*(M128/(M$131-M$123-M$125)) -> 538.87486 | P100: =(P$103-P$95-P$97)*(O128/(O$131-O$123-O$125)) -> -2791.9083
A101: Preference shares | D101: =((2*F101)+(2*H101)+(2*J101)+L101+N101+P101)/9 -> 177523.99 | F101: =(F$103-F$95-F$97)*(E129/(E$131-E$123-E$125)) -> 472775.61 | H101: =(H$103-H$95-H$97)*(G129/(G$131-G$123-G$125)) -> 157471.46 | J101: =(J$103-J$95-J$97)*(I129/(I$131-I$123-I$125)) -> 158057.03 | L101: =(L$103-L$95-L$97)*(K129/(K$131-K$123-K$125)) -> 13943.967 | N101: =(N$103-N$95-N$97)*(M129/(M$131-M$123-M$125)) -> 9148.6718 | P101: =(P$103-P$95-P$97)*(O129/(O$131-O$123-O$125)) -> -1984.9596
A102: Investments in associates | D102: =((2*F102)+(2*H102)+(2*J102)+L102+N102+P102)/9 -> 7821896.1 | F102: =(F$103-F$95-F$97)*(E130/(E$131-E$123-E$125)) -> 22797405 | H102: =(H$103-H$95-H$97)*(G130/(G$131-G$123-G$125)) -> 6212448 | J102: =(J$103-J$95-J$97)*(I130/(I$131-I$123-I$125)) -> 6418517.2 | L102: =(L$103-L$95-L$97)*(K130/(K$131-K$123-K$125)) -> 574389.75 | N102: =(N$103-N$95-N$97)*(M130/(M$131-M$123-M$125)) -> 323308.27 | P102: =(P$103-P$95-P$97)*(O130/(O$131-O$123-O$125)) -> -1357372.7
A103: Income from Investments | D103: =D102+D101+D100+D99+D98+D97+D96+D95 -> 3.1030041e+08 | F103: =F42 -> 472523900 | H103: =H42 -> 370788429 | J103: =J42 -> 226000345 | L103: =L42 -> 143232732 | N103: =N42 -> 148742484 | P103: =P42 -> 110142418
A104: Investments | D104: =SOFP!D7 -> 2.8076679e+09 | F104: =SOFP!F7 -> 2528200439 | H104: =SOFP!H7 -> 2562299087 | J104: =SOFP!J7 -> 1948801042 | L104: =SOFP!L7 -> 1948955978 | N104: =SOFP!N7 -> 1948576822 | P104: =SOFP!P7 -> 1379607379
A105: Yield on Investment | D105: =D103/D104 -> 0.11051892 | F105: =F103/F104 -> 0.18690128 | H105: =H103/H104 -> 0.14470927 | J105: =J103/J104 -> 0.11596892 | L105: =L103/L104 -> 0.07349203 | N105: =N103/N104 -> 0.076333908 | P105: =P103/P104 -> 0.07983606
F107: =F103-SUM(F84:F102) -> -5.5704291e+08
A109: Fair Value through OCI/Available for Sale | C109: =SOFP!C88 -> 0.64083918 | D109: =SOFP!D88 -> 3.616144e+08 | E109: =SOFP!E88 -> 0.63467472 | F109: =SOFP!F88 -> 283446069 | G109: =SOFP!G88 -> 0.52667347 | H109: =SOFP!H88 -> 223185544 | I109: =SOFP!I88 -> 0.65923 | J109: =SOFP!J88 -> 222366674 | ... P109: =SOFP!P88 -> 350931325
A110: Fair Value through Profit and Loss/Held for Tradng | C110: =SOFP!C89 -> 0.1825997 | D110: =SOFP!D89 -> 1.0303784e+08 | E110: =SOFP!E89 -> 0.15861347 | F110: =SOFP!F89 -> 70836862 | G110: =SOFP!G89 -> 0.20982298 | H110: =SOFP!H89 -> 88915542 | I110: =SOFP!I89 -> 0.017425123 | J110: =SOFP!J89 -> 5877716 | ... P110: =SOFP!P89 -> 254261260
A111: Amortized Cost/Held to Maturity | C111: =SOFP!C90 -> 0.17656111 | D111: =SOFP!D90 -> 99630365 | E111: =SOFP!E90 -> 0.2067118 | F111: =SOFP!F90 -> 92317600 | G111: =SOFP!G90 -> 0.26350355 | H111: =SOFP!H90 -> 111663463 | I111: =SOFP!I90 -> 0.32334488 | J111: =SOFP!J90 -> 109068345 | ... P111: =SOFP!P90 -> 274477
A112: Market Treasury Bills | C112: =D112/D$131 -> 0.20097912 | D112: 5.6428261e+08 | E112: =F112/F$131 -> 0.1766476 | F112: 446600531 | G112: =H112/H$131 -> 0.1653845 | H112: 423764549 | I112: =J112/J$131 -> 0.17308731 | J112: 337312735 | K112: =L112/L$131 -> 0.20097912 | L112: 391699451 | M112: =N112/N$131 -> 0.3245299 | N112: 632371432 | O112: =P112/P$131 -> 0.43886911 | P112: 605467062
A113: Fair Value through OCI/Available for Sale | C113: =SOFP!C95 -> 0.74310274 | D113: =SOFP!D95 -> 1.2622591e+09 | E113: =SOFP!E95 -> 0.78050316 | F113: =SOFP!F95 -> 1067225618 | G113: =SOFP!G95 -> 0.7155819 | H113: =SOFP!H95 -> 1113990814 | I113: =SOFP!I95 -> 0.76113672 | J113: =SOFP!J95 -> 906737321 | ... P113: =SOFP!P95 -> 453552332
A114: Fair Value through Profit and Loss/Held for Tradng | C114: =SOFP!C96 -> 0.051326057 | D114: =SOFP!D96 -> 87184150 | E114: =SOFP!E96 -> 0.034810237 | F114: =SOFP!F96 -> 47597984 | G114: =SOFP!G96 -> 0.090534688 | H114: =SOFP!H96 -> 140940974 | I114: =SOFP!I96 -> 0.043974207 | J114: =SOFP!J96 -> 52386192 | ... P114: =SOFP!P96 -> 12629554
A115: Amortized Cost/Held to Maturity | C115: =SOFP!C97 -> 0.2055712 | D115: =SOFP!D97 -> 3.4919009e+08 | E115: =SOFP!E97 -> 0.1846866 | F115: =SOFP!F97 -> 252532318 | G115: =SOFP!G97 -> 0.19388341 | H115: =SOFP!H97 -> 301830350 | I115: =SOFP!I97 -> 0.19488907 | J115: =SOFP!J97 -> 232170109 | ... P115: =SOFP!P97 -> 157029540
A116: Pakistan Investment Bonds | C116: =D116/D$131 -> 0.60499795 | D116: 1.6986333e+09 | E116: =F116/F$131 -> 0.54084158 | F116: 1367355920 | G116: =H116/H$131 -> 0.60756457 | H116: 1556762138 | I116: =J116/J$131 -> 0.61129566 | J116: 1191293622 | K116: =L116/L$131 -> 0.60499795 | L116: 1179114373 | M116: =N116/N$131 -> 0.53254389 | N116: 1037702672 | O116: =P116/P$131 -> 0.451731 | P116: 623211426
...

Sheet CF
A1: HABIB BANK LIMITED | K1: PKR | M1: PKR | O1: PKR | Q1: PKR | S1: PKR
A2: CONSOLIDATED CASH FLOW STATEMENT | K2: 25 Forecast | M2: 24 | O2: 23 | Q2: 22 | S2: 21
A3: Profit before taxation | K3: ='P&L'!D26 -> 1.0844157e+08 | M3: 120334380 | O3: 113550996 | Q3: 77029938 | S3: 62027911
A4: Dividend income | K4: =-'P&L'!D9 -> -4449656.5 | M4: -3082420 | O4: -2300969 | Q4: -1508643 | S4: -913769
A5: Share of profit of associates and joint venture | C5: USD | E5: USD | G5: USD | I5: USD | K5: =-'P&L'!D10 -> -5174323.5 | M5: -4763000 | O5: -4422695 | Q5: -3028453 | S5: -2585595
A6: Mark-up expensed on subordinated debt | C6: 24 | E6: 23 | G6: 22 | I6: 21 | K6: ='P&L'!D138 -> 3587276.5 | M6: 4096181 | O6: 4281784 | Q6: 1891880 | S6: 1239075
C7: 432003 | E7: 407650 | K7: =SUM(K4:K6) -> -6036703.6 | M7: -3749239 | O7: -2441880 | Q7: -2645216 | S7: -2260289
C8: -11066 | E8: -8261 | K8: =K3-K7 -> 1.1447827e+08 | M8: 116585141 | O8: 111109116 | Q8: 74384722 | S8: 59767622
C9: -17099 | E9: -15878
A10: Non-Cash Expenses | C10: 14705 | E10: 15372
A11: Depreciation | C11: -13460 | E11: -8767 | K11: ='P&L'!D144 -> 11775229 | M11: 10957614 | O11: 9680335 | Q11: 7782494 | S11: 6969192
A12: Amortisation | C12: 418543 | E12: 398883 | K12: ='P&L'!D154 -> 1948774.3 | M12: 2738087 | O12: 2246980 | Q12: 1852350 | S12: 1061035
A13: Depreciation on right-of-use assets | K13: ='P&L'!D148 -> 5522854.6 | M13: 4525300 | O13: 4426688 | Q13: 3978154 | S13: 3384774
A14: Provision for / (reversal of) diminution in value of investments | K14: 0 | Q14: 3851708 | S14: -1258723
A15: Mark-up expensed on lease liability against right-of-use assets | C15: 39338 | E15: 34753 | K15: ='National Deposits'!C94 -> 3985416 | M15: 3551598 | O15: 3345591 | Q15: 3145165 | S15: 3252794
A16: Reversal of credit loss allowance against investments | C16: 9830 | E16: 8067 | K16: 0 | M16: -1730634 | O16: -184104
A17: Provisions / credit loss allowance against loans and advances | C17: 16246 | E17: 15892 | K17: ='Credit Loss Allowance'!D38 -> 16595894 | M17: 20568188 | O17: 13469201 | Q17: 5943661 | S17: 7645044
A18: Reversal of credit loss allowance against lendings to financial institutions | K18: ='Credit Loss Allowance'!D6 -> -170.71612 | M18: -1210 | O18: -
A19: Provision / credit loss allowance against other assets | C19: 12750 | E19: 12011 | K19: ='Credit Loss Allowance'!D7 -> 1219618.4 | M19: 2340528 | O19: 1140717 | Q19: 624244 | S19: 190136
A20: Charge / (reversal) of credit loss allowance against off-balance sheet obligations | C20: -6213 | E20: -661 | K20: ='Credit Loss Allowance'!D8 -> 867247.06 | M20: 4606306 | O20: -93890 | Q20: -1331585 | S20: 1540508
A21: Unrealised gain on securities designated at fair value through profit and loss (FVTPL) | C21: 73840 | E21: 48355 | K21: 0 | M21: -1263203 | O21: -
A22: Unrealised gain on held-for-trading securities | C22: -4 | E22: - | K22: 0 | M22: - | O22: -280323 | Q22: 84390 | S22: -67246
A23: Gain on derecognition of joint venture | C23: 8403 | E23: 4095 | K23: 0 | M23: - | O23: -3731399 | Q23: 0 | S23: 0
A24: Exchange loss / (gain) on goodwill | C24: 16537 | E24: -337 | K24: 0 | M24: 109740 | O24: -1055507 | Q24: -429394 | S24: -244750
A25: Exchange gain realised on partial repatriation of branch capital - net of tax | C25: -4535 | E25: - | K25: 0 | S25: -246489
A26: Exchange gain realised on liquidation of subsidiary - net of tax | C26: - | E26: -1006 | K26: 0 | S26: -1369
A27: Gain on sale of property and equipment - net | C27: - | E27: -13396 | K27: 0 | M27: -156538 | O27: -48681 | Q27: -42024 | S27: -79639
A28: Gain realised on closure / sale of the Bank's branches | C28: 394 | E28: -3789 | K28: 0 | M28: -14254667 | O28: - | Q28: 0 | S28: -16000
A29: Workers' Welfare Fund | K29: ='P&L'!D20 -> 3224542.7 | M29: 2364597 | O29: 2282323 | Q29: 1498693 | S29: 1273226
A30: Non-Cash Expenses | K30: =SUM(K11:K29) -> 45139406 | M30: 34355706 | O30: 31197931 | Q30: 26957856 | S30: 23402493
A31: Profit before taxation adjusted for non-cash expenses | C31: -562 | E31: -175 | K31: =K30+K8 -> 1.5961768e+08 | M31: 150940847 | O31: 142307047 | Q31: 101342578 | S31: 83170115
C32: -51175 | E32: -
A33: (Increase) / decrease in operating assets | C33: 8489 | E33: 8194
A34: Lendings to financial institutions | C34: 123338 | E34: 112003 | K34: =SOFP!F6-SOFP!D6 -> -74515589 | M34: 4296525 | O34: 165995127 | Q34: -160850855 | S34: -63588239
A35: Net investment in securities carried at FVTPL | C35: 541881 | E35: 510886 | K35: =SOFP!F135-SOFP!D135 -> -1.0111302e+08 | M35: 91405547 | O35: - | Q35: 0 | S35: 0
A36: Net investment in held-for-trading securities | K36: 0 | M36: - | O36: -178812226 | Q36: 142875183 | S36: -72978890
A37: Advances | K37: =SOFP!F8-SOFP!D8 -> -3.5483128e+08 | M37: -651100311 | O37: -92315870 | Q37: -281394487 | S37: -291181919
A38: Other assets (excluding advance taxation) | C38: 15425 | E38: 595926 | K38: =SOFP!F13-SOFP!D13 -> -61761087 | M38: 7476467 | O38: -83795260 | Q38: -31429797 | S38: -34306119
A39: (Increase) / decrease in operating assets | C39: 328148 | E39: - | K39: =SUM(K34:K38) -> -5.9222097e+08 | M39: -547921772 | O39: -188928229 | Q39: -330799956 | S39: -462055167
C40: - | E40: -641939
A41: Increase / (decrease) in operating liabilities | C41: -2337463 | E41: -331416
A42: Bills payable | C42: 26841 | E42: -300827 | K42: =SOFP!D17-SOFP!F17 -> -13903117 | M42: 44403328 | O42: -300754 | Q42: 7804593 | S42: -2237215
A43: Borrowings from financial institutions | C43: -1967049 | E43: -678256 | K43: =SOFP!D18-SOFP!F18 -> 49711146 | M43: 168195241 | O43: 81271280 | Q43: 147513394 | S43: -107849821
A44: Deposits and other accounts | K44: =SOFP!D19-SOFP!F19 -> 6.4332195e+08 | M44: 228018806 | O44: 673009584 | Q44: 87343854 | S44: 551627008
A45: Other liabilities | K45: =SOFP!D23-SOFP!F23 -> 56367894 | M45: 39478873 | O45: 55522237 | Q45: 67997391 | S45: 16006633
A46: Increase / (decrease) in operating liabilities | C46: 159409 | E46: -1080 | K46: =SUM(K42:K45) -> 7.3549787e+08 | M46: 480096248 | O46: 809502347 | Q46: 310659232 | S46: 457546605
A47: Increase / (decrease) in operating net assets | C47: 603824 | E47: 291765 | K47: =K46+K39+K31 -> 3.0289458e+08 | M47: 83115323 | O47: 762881165 | Q47: 81201854 | S47: 78661553
C48: 818592 | E48: 2416118
A49: Income tax paid | C49: 141730 | E49: 199326 | K49: =-'P&L'!D27 -> -58558446 | M49: -95275207 | O49: -51150860 | Q49: -32102961 | S49: -26199570
A50: Net cash flows (used in) / generated from operating activities | C50: 1723555 | E50: 2906129 | K50: =K47+K49 -> 2.4433614e+08 | M50: -12159884 | O50: 711730305 | Q50: 49098893 | S50: 52461983
C51: 298387 | E51: 2738759
A52: CASH FLOWS FROM INVESTING ACTIVITIES
A53: Net investment in securities carried at FVOCI | C53: -342040 | E53: -183633 | K53: =SOFP!F135-SOFP!D135 -> -1.0111302e+08 | M53: -60053423 | O53: -
A54: Net investment in securities carried at Amortised Cost | C54: -43653 | E54: 2555126 | K54: =SOFP!F140-SOFP!D140 -> -1.0549865e+08 | M54: 45408402 | O54: -
A55: Net investment in available-for-sale securities | K55: 0 | M55: - | O55: -334968861 | Q55: -138904867 | S55: 132180606
A56: Net investment in held-to-maturity securities | K56: 0 | M56: - | O56: -78711656 | Q56: -43705242 | S56: -72505857
A57: Net investment in associates | C57: -215593 | E57: - | K57: =SOFP!F142-SOFP!D142 -> -8231278.9 | M57: -1973419 | O57: -450925 | Q57: -2819460 | S57: -857866
A58: Dividend received | C58: 163017 | E58: - | K58: ='P&L'!D9 -> 4449656.5 | M58: 3086558 | O58: 2295759 | Q58: 1689973 | S58: 743582
A59: Investment in property and equipment | C59: - | E59: -1202545 | K59: =SOFP!F9-SOFP!D9-K11 -> -32707573 | M59: -24998434 | O59: -17222863 | Q59: -19464322 | S59: -13571964
A60: Investment in intangible assets | C60: - | E60: -282576 | K60: =SOFP!F11-SOFP!D11-CF!K12 -> -7634648.6 | M60: -5251776 | O60: -5376002 | Q60: -7644075 | S60: -3001342
A61: Proceeds from sale of property and equipment | C61: -7085 | E61: -1619 | K61: 0 | M61: 550830 | O61: 281697 | Q61: 65071 | S61: 128881
A62: Effect of translation of net investment in foreign branches, subsidiaries, joint venture and associates - net of tax | C62: 11081 | E62: 8242 | K62: 0 | M62: -2750167 | O62: 10529694 | Q62: 2258212 | S62: 5465689
A63: Net cash flows used in investing activities | C63: -89745 | E63: -61830 | K63: =SUM(K53:K62) -> -2.5073551e+08 | M63: -45981429 | O63: -423623157 | Q63: -208524710 | S63: 48797729
C64: -18854 | E64: -19300
A65: CASH FLOWS FROM FINANCING ACTIVITIES | C65: 1977 | E65: 1011
A66: Effect of translation of net investment by non-controlling interest in subsidiary | C66: -9873 | E66: 37802 | K66: 0 | Q66: 44140 | S66: 85115
A67: Proceeds from issuance of subordinated debt | C67: -165075 | E67: -1520815 | K67: =SOFP!D21-SOFP!F21 -> 638075.58 | M67: 675000 | O67: 825000 | Q67: 6500000
A68: Repayment of subordinated debt | K68: 0 | M68: 0 | O68: 0 | Q68: -9982000
A69: Payment of mark-up on subordinated debt | K69: =-'National Deposits'!C92 -> -3576900.4 | M69: -4121360 | O69: -4287065 | Q69: -1847577 | S69: -1517481
A70: Payment of lease liability against right-of-use assets | K70: ='P&L'!D150 -> -7093427.7 | M70: -5759500 | O70: -5683153 | Q70: -4939145 | S70: -5113819
A71: Dividend paid | C71: 2423 | E71: 2962 | K71: =-('P&L'!D33-'P&L'!D39) -> -16134369 | M71: -25265428 | O71: -12358209 | Q71: -8493514 | S71: -10855155
A72: Net cash flows used in financing activities | K72: =SUM(K66:K71) -> -26166622 | M72: -34471288 | O72: -21503427 | Q72: -8736096 | S72: -27383340
C73: -14796 | E73: -15391
A74: (Decrease) / increase in cash and cash equivalents during the year | C74: -20677 | E74: -20403 | K74: =K72+K63+K50 -> -32565994 | M74: -92612601 | O74: 266603721 | Q74: -168161913 | S74: 73876372
A75: Cash and cash equivalents at the beginning of the year (W/O Exchange rate Effect) | C75: -90703 | E75: -44366 | K75: =M78 -> 511519528 | M75: 624857321 | O75: 330872995 | Q75: 482746454 | S75: 422601823
A76: Effect of exchange rate changes on cash and cash equivalents | C76: -123753 | E76: -77198 | K76: 0 | M76: -20725192 | O76: 6655413 | Q76: 22943867 | S76: 9212126
A77: Cash and cash equivalents at the beginning of the year | K77: =M78 -> 511519528 | M77: 604132129 | O77: 337528408 | Q77: 505690321 | S77: 431813949
A78: Cash and cash equivalents at the end of the year | C78: -332481 | E78: 957113 | K78: =K74+K77 -> 4.7895353e+08 | M78: 511519528 | O78: 604132129 | Q78: 337528408 | S78: 505690321
C79: 2243250 | E79: 1187841
C80: -74404 | E80: 23894
C81: 2168846 | E81: 1211735
C82: 1836365 | E82: 2168848

Sheet Capital Adequacy and Liquidity
A1: HABIB BANK LIMITED
A2: CAPITAL ADEQUACY AND LIQUIDITY DISCLOSURE | C2: PKR | E2: PKR | G2: PKR | I2: PKR
A3: On-balance sheet | C3: 24 | E3: 23 | G3: 22 | I3: 21
A4: Sovereigns | C4: 188007983 | E4: 220694114 | G4: 169188045 | I4: 134646975
A5: Public Sector Entities | C5: 40515867 | E5: 34860385 | G5: 34618570 | I5: 34638689
A6: Multilateral Development Banks | C6: 0 | E6: 0 | G6: 379658 | I6: 623184
A7: Banks | C7: 142832495 | E7: 88249491 | G7: 71698824 | I7: 99803166
A8: Corporates | C8: 584863243 | E8: 596497395 | G8: 603109959 | I8: 517129917
A9: Retail | C9: 307316054 | E9: 283150039 | G9: 261121134 | I9: 217681533
A10: Residential mortgages | C10: 17690609 | E10: 13106314 | G10: 8715744 | I10: 6979380
A11: Low Cost Housing | C11: 1781213 | E11: 1922030 | G11: 2025188 | I11: 518924
A12: Past due loans | C12: 8196097 | E12: 16220289 | G12: 12675228 | I12: 6979726
A13: Listed equity investments | C13: 5864302 | E13: 8571270 | G13: 6777298 | I13: 3750255
A14: Unlisted equity investments | C14: 581993 | E14: 7117404 | G14: 7141103 | I14: 7181663
... A18: On-balance sheet Assets | C18: 1581427836 | E18: 1516674571 | G18: 1401128779 | I18: 1196735096
A20: Off-balance sheet
A21: Non-market related | C21: 139947639 | E21: 121315175 | G21: 107895419 | I21: 125698401
A22: Market related | C22: 4449114 | E22: 3029974 | G22: 2816544 | I22: 6357655
A23: Off-balance sheet Assets | C23: 144396753 | E23: 124345149 | G23: 110711963 | I23: 132056056
A25: Market Risk
A26: Interest Rate Risk | C26: 73698487 | E26: 69778337 | G26: 32110088 | I26: 30729675
A27: Equity Position Risk | C27: 37264900 | E27: 17256000 | G27: 7623075 | I27: 16238275
A28: Foreign Exchange Risk | C28: 120495038 | E28: 110076688 | G28: 65484575 | I28: 69711838
A29: Market Risk | C29: 231458425 | E29: 197111025 | G29: 105217738 | I29: 116679788
A30: Operational Risk | C30: 388610901 | E30: 303760456 | G30: 266263405 | I30: 224085265
A31: Total Risk Weighted Assets | C31: 2345893915 | E31: 2141891201 | G31: 1883321885 | I31: 1669556205
A33: Capital Adequacy Ratio
A34: Total eligible regulatory capital held | C34: 415322248 | E34: 342825915 | G34: 279322811 | I34: 260917929
A35: Total risk weighted assets | C35: 2345893915 | E35: 2141891201 | G35: 1883321885 | I35: 1669556205
A36: Capital adequacy ratio | C36: 0.177 | E36: 0.1601 | G36: 0.1483 | I36: 0.1563
A38: Common Equity Tier I
A39: Fully Paid-up Capital | C39: 14668525 | E39: 14668525 | G39: 14668525 | I39: 14668525
A40: Balance in Share Premium Account - - | C40: 0 | E40: 0 | G40: 0 | I40: 0
A41: Reserve for issue of Bonus Shares - - | C41: 0 | E41: 0 | G41: 0 | I41: 0
A42: Discount on Issue of shares - - | C42: 0 | E42: 0 | G42: 0 | I42: 0
A43: General and Capital Reserves | C43: 98302935 | E43: 50500007 | G43: 46044309 | I43: 42549449
A44: Gain/(Losses) on derivatives held as Cash Flow Hedge - - | C44: 0 | E44: 0 | G44: 0 | I44: 0
A45: Unappropriated profit | C45: 246508577 | E45: 221883756 | G45: 178467639 | I45: 158441418
A46: Non-controlling interest arising from CET1 capital instruments issued to third parties | C46: 0 | E46: 0 | G46: 0 | I46: 0
A47: by consolidated banking subsidiaries (amount allowed in CET1 capital of the - - | C47: 0 | E47: 0 | G47: 0 | I47: 0
A48: consolidation group) | C48: 1008476 | E48: 1937061 | G48: 1969443 | I48: 2699363
A49: CET before Regulatory Adjustments | C49: 360488513 | E49: 288989349 | G49: 241149916 | I49: 218358755
A50: Total regulatory adjustments applied to CET1 1.3.1 | C50: -44250062 | E50: -41598622 | G50: -37898154 | I50: -25893674
A51: Common Equity Tier | C51: 316238451 | E51: 247390727 | G51: 203251762 | I51: 192465081
A53: Additional Tier 1 (AT 1) Capital
A54: Qualifying Additional Tier-1 instruments plus any related share premium | C54: 18874000 | E54: 18874000 | G54: 18874000 | I54: 12374000
A55: of which: Classified as equity - - | C55: 0 | E55: 0 | G55: 0 | I55: 0
A56: of which: Classified as liabilities | C56: 18874000 | E56: 18874000 | G56: 18874000 | I56: 12374000
A57: Additional Tier-1 capital instruments issued by consolidated subsidiaries and held by third parties (amount allowed in group AT 1) | C57: 177966 | E57: 341834 | G57: 328650 | I57: 413111
A58: of which: instrument issued by subsidiaries subject to phase out - - | C58: 0 | E58: 0 | G58: 0 | I58: 0
A59: AT1 before regulatory adjustments | C59: 19051966 | E59: 19215834 | G59: 19202650 | I59: 12787111
A60: Total of Regulatory Adjustment applied to AT1 capital 1.3.2 | C60: -430613 | E60: -86476 | G60: -109225 | I60: -180351
A61: Additional Tier capital after regulatory adjustments - - | C61: 0 | E61: 0 | G61: 0 | I61: 0
A62: Additional Tier capital recognized for capital adequacy | C62: 18621353 | E62: 19129359 | G62: 19093425 | I62: 12606759
A63: Tier 1 Capital (CET1 + admissible AT1) | C63: 334859804 | E63: 266520086 | G63: 222345187 | I63: 205071840
A65: Tier 2 Capital
A66: Qualifying Tier capital instruments under Basel III plus any related share premium | C66: 1500000 | E66: 825000 | G66: 0 | I66: 0
A67: Tier 2 capital instruments subject to phase out arrangement issued under pre-Basel 3 rules | C67: 0 | E67: 0 | G67: 0 | I67: 0
A68: Tier capital instruments issued to third parties by consolidated banking subsidiaries (amount allowed in tier 2) | C68: 296611 | E68: 569723 | G68: 517266 | I68: 506005
A69: of which: instruments issued by subsidiaries subject to phase out | C69: 0 | E69: 0 | G69: 0 | I69: 0
A70: General Provisions or general reserves for loan losses-up to maximum of of Credit Risk Weighted Assets | C70: 21572807 | E70: 18392219 | G70: 13911505 | I70: 11008308
A71: Revaluation Reserves (net of taxes) | C71: 57159757 | E71: 25665732 | G71: 1028565 | I71: 24913722
A72: of which: Revaluation reserves on fixed assets | C72: 42525073 | E72: 42947693 | G72: 27140972 | I72: 27213335
A73: of which: Unrealized gains/losses on FVOCI | B73: ? | C73: 14634684 | E73: -17281961 | G73: -26112407 | I73: -2299613
A74: Foreign Exchange Translation Reserves - | C74: 50305150 | G74: 41727023 | I74: 38826070
A75: Tier 2 before regulatory adjustments | C75: 80529175 | E75: 95757824 | G75: 57184359 | I75: 75254105
A76: Total regulatory adjustment applied to T2 capital 1.3.3 | C76: -66731 | E76: -46808 | G76: -206735 | I76: -380625
A77: Tier 2 after regulatory adjustments | C77: 80462444 | E77: 95711016 | G77: 56977624 | I77: 74873480
A78: Tier 2 capital not recognized for capital adequacy | C78: 0 | E78: 19405187 | G78: 0 | I78: -19027391
A79: Tier capital recognized for capital adequacy | C79: 80462444 | E79: 76305829 | G79: 56977624 | I79: 55846089
A80: Portion of Additional Tier 1 capital recognized in Tier capital 2 | C80: 0 | E80: 0 | G80: 0 | I80: 0
A81: Total Tier 2 capital admissible for capital adequacy | C81: 80462444 | E81: 76305829 | G81: 56977624 | I81: 55846089
A82: TOTAL CAPITAL (Tier 1 + admissible Tier 2) | C82: 415322248 | E82: 342825915 | G82: 279322811 | I82: 260917929
A83: Total Risk Weighted Assets | C83: 2345893915 | E83: 2141891201 | G83: 1883321885 | I83: 1669556205
A85: CET1 Ratio | C85: 0.1348 | D85: 0.09 | E85: 0.1155 | F85: 0.09 | G85: 0.1079 | H85: 0.095 | I85: 0.1153
A86: Tier 1 Ratio | C86: 0.1427 | D86: 0.105 | E86: 0.1244 | F86: 0.105 | G86: 0.1181 | H86: 0.11 | I86: 0.1228
A87: Total Capital Ratio | B87: 0.085 | C87: 0.177 | D87: 0.13 | E87: 0.1601 | F87: 0.13 | G87: 0.1483 | H87: 0.135 | I87: 0.1563
B88: 0.1
A89: Eligible Tier-1 Capital | B89: 0.125 | C89: 334859804 | E89: 266520086 | G89: 222345187 | I89: 205071840
A90: Total Exposures | C90: 7184144791 | E90: 6158603788 | G90: 5292442000 | I90: 4687343787
A91: Leverage Ratio (%) | C91: 0.0466 | E91: 0.0433 | G91: 0.042 | I91: 0.0438
A92: Minimum Requirement (%) | C92: 0.03 | E92: 0.03 | G92: 0.03 | I92: 0.03
A94: AVERAGE HIGH QUALITY LIQUID ASSETS | C94: 2320570154 | E94: 1879073951 | G94: 1609446790 | I94: 1477650149
A95: AVERAGE NET CASH OUTFLOWS | C95: 869235371 | E95: 693860676 | G95: 632560916 | I95: 638366023
A96: LIQUIDITY COVERAGE RATIO | C96: 2.6697 | E96: 2.7081 | G96: 2.5443 | I96: 2.3147
A98: Total Available Stable Funding | C98: 4156125272 | E98: 4156125272 | G98: 3225111950 | I98: 3046911457
A99: Required Available Stable Funding | C99: 2732852018 | E99: 2384738674 | G99: 2171559048 | I99: 1964571726
A100: Net Stable Funding Ratio | C100: 1.5208 | E100: 1.5985 | G100: 1.4852 | I100: 1.5509

Sheet Credit Loss Allowance
A1: HABIB BANK LIMITED | D1: PKR | G1: PKR | J1: PKR | M1: PKR | P1: PKR | S1: PKR | V1: PKR
A2: CREDIT LOSS ALLOWANCE | D2: 25 Forecast | G2: 24 | J2: 23 | M2: 22 | P2: 21 | S2: 20 | V2: 19
A3: Reversal of credit loss allowance against investments | C3: {=AVERAGE( _xlfn._xlws.FILTER( CHOOSE({1,2,3,4,5}, F3, I3, L3, O3, R3), ISNUMBER(CHOOSE({1,2,3,4,5}, F3, I3, L3, O3, R3)) ) )} -> 0.038845386 | D3: =C3*D$15 -> 729024.41 | F3: =G3/G$15 -> -0.065052167 | G3: -1730634 | I3: =J3/J$15 -> -0.013878115 | J3: -184104 | L3: =M3/M$15 -> 0.45411654 | M3: 3851708 | O3: =P3/P$15 -> -0.15564569 | P3: -1258723 | R3: =S3/S$15 -> -0.025313647 | S3: -309323 | U3: =V3/V$15 -> 0.1668897 | V3: 553086
A4: Credit loss allowance against loans and advances | C4: {=AVERAGE( _xlfn._xlws.FILTER( CHOOSE({1,2,3,4,5}, F4, I4, L4, O4, R4), ISNUMBER(CHOOSE({1,2,3,4,5}, F4, I4, L4, O4, R4)) ) )} -> 0.88429675 | D4: =D38 -> 16595894 | F4: =G4/G$15 -> 0.77313008 | G4: 20568188 | I4: =J4/J$15 -> 1.0153343 | J4: 13469201 | L4: =M4/M$15 -> 0.7007579 | M4: 5943661 | O4: =P4/P$15 -> 0.94533755 | P4: 7645044 | R4: =S4/S$15 -> 0.98692389 | S4: 12059829 | U4: =V4/V$15 -> 1.0187135 | V4: 3376099
A5: Credit loss allowance against cash and cash equivalent | C5: {=AVERAGE( _xlfn._xlws.FILTER( CHOOSE({1,2,3,4,5}, F5, I5, L5, O5, R5), ISNUMBER(CHOOSE({1,2,3,4,5}, F5, I5, L5, O5, R5)) ) )} -> 5.7427914e-05 | D5: =C5*D$15 -> 1077.769 | F5: =G5/G$15 -> 0.00028713957 | G5: 7639 | I5: =J5/J$15 -> 0 | J5: 0 | L5: =M5/M$15 -> 0 | M5: 0 | O5: =P5/P$15 -> 0 | P5: 0 | R5: =S5/S$15 -> 0 | S5: 0 | U5: =V5/V$15 -> 0 | V5: 0
A6: Reversal of credit loss allowance against lendings to financial institutions | C6: {=AVERAGE( _xlfn._xlws.FILTER( CHOOSE({1,2,3,4,5}, F6, I6, L6, O6, R6), ISNUMBER(CHOOSE({1,2,3,4,5}, F6, I6, L6, O6, R6)) ) )} -> -9.0964493e-06 | D6: =C6*D$15 -> -170.71612 | F6: =G6/G$15 -> -4.5482247e-05 | G6: -1210 | I6: =J6/J$15 -> 0 | J6: 0 | L6: =M6/M$15 -> 0 | M6: 0 | O6: =P6/P$15 -> 0 | P6: 0 | R6: =S6/S$15 -> 0 | S6: 0 | U6: =V6/V$15 -> 0 | V6: 0
A7: Provision / credit loss allowance against other assets | C7: {=AVERAGE( _xlfn._xlws.FILTER( CHOOSE({1,2,3,4,5}, F7, I7, L7, O7, R7), ISNUMBER(CHOOSE({1,2,3,4,5}, F7, I7, L7, O7, R7)) ) )} -> 0.064986231 | D7: =C7*D$15 -> 1219618.4 | F7: =G7/G$15 -> 0.087977249 | G7: 2340528 | I7: =J7/J$15 -> 0.085989447 | J7: 1140717 | L7: =M7/M$15 -> 0.073598395 | M7: 624244 | O7: =P7/P$15 -> 0.023511009 | P7: 190136 | R7: =S7/S$15 -> 0.053855056 | S7: 658088 | U7: =V7/V$15 -> 0.027222931 | V7: 90219
A8: Charge / (reversal) of credit loss allowance against off-balance sheet obligations | C8: {=AVERAGE( _xlfn._xlws.FILTER( CHOOSE({1,2,3,4,5}, F8, I8, L8, O8, R8), ISNUMBER(CHOOSE({1,2,3,4,5}, F8, I8, L8, O8, R8)) ) )} -> 0.046210451 | D8: =C8*D$15 -> 867247.06 | F8: =G8/G$15 -> 0.17314475 | G8: 4606306 | I8: =J8/J$15 -> -0.0070776092 | J8: -93890 | L8: =M8/M$15 -> -0.15699393 | M8: -1331585 | O8: =P8/P$15 -> 0.19048943 | P8: 1540508 | R8: =S8/S$15 -> 0.03148962 | S8: 384791 | U8: =V8/V$15 -> -0.014855702 | V8: -49233
A9: Recoveries against written off / charged off bad debts | C9: {=AVERAGE( _xlfn._xlws.FILTER( CHOOSE({1,2,3,4,5}, F9, I9, L9, O9, R9), ISNUMBER(CHOOSE({1,2,3,4,5}, F9, I9, L9, O9, R9)) ) )} -> -0.075528923 | D9: =C9*D$15 -> -1417476.7 | F9: =G9/G$15 -> -0.029496515 | G9: -784719 | I9: =J9/J$15 -> -0.087233852 | J9: -1157225 | L9: =M9/M$15 -> -0.10681343 | M9: -905966 | O9: =P9/P$15 -> -0.10421356 | P9: -842786 | R9: =S9/S$15 -> -0.049887255 | S9: -609603 | U9: =V9/V$15 -> -0.18505703 | V9: -613294
A10: Recoveries against other assets written off | C10: {=AVERAGE( _xlfn._xlws.FILTER( CHOOSE({1,2,3,4,5}, F10, I10, L10, O10, R10), ISNUMBER(CHOOSE({1,2,3,4,5}, F10, I10, L10, O10, R10)) ) )} -> -0.0015889517 | D10: =C10*D$15 -> -29820.391 | F10: =G10/G$15 -> -6.6644647e-05 | G10: -1773 | I10: =J10/J$15 -> -0.0011323873 | J10: -15022 | L10: =M10/M$15 -> -0.00021328118 | M10: -1809 | O10: =P10/P$15 -> -0.0013260617 | P10: -10724 | R10: =S10/S$15 -> -0.0052063838 | S10: -63620 | U10: =V10/V$15 -> -0.012913384 | V10: -42796
A11: Write off of fixed assets | C11: {=AVERAGE( _xlfn._xlws.FILTER( CHOOSE({1,2,3,4,5}, F11, I11, L11, O11, R11), ISNUMBER(CHOOSE({1,2,3,4,5}, F11, I11, L11, O11, R11)) ) )} -> 0.0033102328 | D11: =C11*D$15 -> 62124.251 | F11: =G11/G$15 -> 0 | I11: =J11/J$15 -> 0 | L11: =M11/M$15 -> 0 | O11: =P11/P$15 -> 0.016551164 | P11: 133851 | R11: =S11/S$15 -> 0 | S11: 0 | U11: =V11/V$15 -> 0 | V11: 0
A12: Software written off | C12: {=AVERAGE( _xlfn._xlws.FILTER( CHOOSE({1,2,3,4,5}, F12, I12, L12, O12, R12), ISNUMBER(CHOOSE({1,2,3,4,5}, F12, I12, L12, O12, R12)) ) )} -> 0.0054918347 | D12: =C12*D$15 -> 103067.11 | F12: =G12/G$15 -> 0.027459173 | G12: 730518 | I12: =J12/J$15 -> 0 | J12: 0 | L12: =M12/M$15 -> 0 | O12: =P12/P$15 -> 0 | R12: =S12/S$15 -> 0 | S12: 0 | U12: =V12/V$15 -> 0 | V12: 0
A13: Other write offs and operational losses | C13: {=AVERAGE( _xlfn._xlws.FILTER( CHOOSE({1,2,3,4,5}, F13, I13, L13, O13, R13), ISNUMBER(CHOOSE({1,2,3,4,5}, F13, I13, L13, O13, R13)) ) )} -> 0.030296016 | D13: =C13*D$15 -> 568575.51 | F13: =G13/G$15 -> 0.032662418 | G13: 868944 | I13: =J13/J$15 -> 0.0079981733 | J13: 106102 | L13: =M13/M$15 -> 0.035547807 | M13: 301508 | O13: =P13/P$15 -> 0.075271683 | P13: 608730 | R13: =S13/S$15 -> 0 | S13: 0 | U13: =V13/V$15 -> 0 | V13: 0
A14: Bad debts written off directly | C14: {=AVERAGE( _xlfn._xlws.FILTER( CHOOSE({1,2,3,4,5}, F14, I14, L14, O14, R14), ISNUMBER(CHOOSE({1,2,3,4,5}, F14, I14, L14, O14, R14)) ) )} -> 0.0036326392 | D14: =C14*D$15 -> 68174.96 | F14: =G14/G$15 -> 0 | G14: 0 | I14: =J14/J$15 -> 0 | J14: 0 | L14: =M14/M$15 -> 0 | O14: =P14/P$15 -> 0.010024477 | P14: 81069 | R14: =S14/S$15 -> 0.0081387186 | S14: 99452 | U14: =V14/V$15 -> 0 | V14: 0
A15: Total | D15: =D4/C4 -> 18767336 | G15: 26603787 | J15: 13265779 | M15: 8481761 | P15: 8087105 | S15: 12219614 | V15: 3314081
B18: Specific | C18: General | D18: Total | E18: Specific | F18: General | G18: Total | H18: Specific | I18: General | J18: Total | K18: Specific | L18: General | M18: Total | N18: Specific | O18: General | P18: Total | Q18: Specific | R18: General | S18: Total | T18: Specific | U18: General | V18: Total
A19: Opening balance | H19: 78259477 | I19: 13911505 | J19: 92170982 | K19: 72845186 | L19: 11008308 | M19: 83853494 | N19: 70835763 | O19: 11063284 | P19: 81899047 | Q19: 72634967 | R19: 3730991 | S19: 76365958 | T19: 68465249 | U19: 3528347 | V19: 71993596
A20: Exchange adjustment | H20: 8019828 | I20: 831237 | J20: 8851065 | K20: 7453225 | L20: 691606 | M20: 8144831 | N20: 2670248 | O20: 222274 | P20: 2892522 | Q20: 974252 | R20: 47701 | S20: 1021953 | T20: 3108243 | U20: 183081 | V20: 3291324
A21: Charge for the year | H21: 16462892 | I21: 4857453 | J21: 21320345 | K21: 10153742 | L21: 3341192 | M21: 13494934 | N21: 12415018 | O21: 1613469 | P21: 14028487 | Q21: 9301182 | R21: 7636845 | S21: 16938027 | T21: 7524537 | U21: 528694 | V21: 8053231
A22: Reversal for the year | H22: -6643168 | I22: -1207976 | J22: -7851144 | K22: -6421672 | L22: -1129601 | M22: -7551273 | N22: -4492724 | O22: -1890719 | P22: -6383443 | Q22: -4525945 | R22: -352253 | S22: -4878198 | T22: -4256484 | U22: -420648 | V22: -4677132
A23: Net charge / (reversal) against advances | H23: 9819724 | I23: 3649477 | J23: 13469201 | K23: 3732070 | L23: 2211591 | M23: 5943661 | N23: 7922294 | O23: -277250 | P23: 7645044 | Q23: 4775237 | R23: 7284592 | S23: 12059829 | T23: 3268053 | U23: 108046 | V23: 3376099
A24: Charged off during the year agriculture financing | H24: -503799 | J24: -503799 | K24: -582438 | M24: -582438 | N24: -532280 | P24: -532280 | Q24: -750824 | S24: -750824 | T24: -604496 | V24: -604496
A25: Written off during the year | H25: -10675157 | J25: -10675157 | K25: -5333549 | M25: -5333549 | N25: -8050839 | P25: -8050839 | Q25: -6797869 | S25: -6797869 | T25: -1602082 | V25: -1602082
A26: Transferred out | K26: -67880 | M26: -67880
A27: Other movement | K27: 212863 | M27: 212863 | T27: -88483 | V27: -88483
A28: Closing balance | H28: 84920073 | I28: 18392219 | J28: 103312292 | K28: 78259477 | L28: 13911505 | M28: 92170982 | N28: 72845186 | O28: 11008308 | P28: 83853494 | Q28: 70835763 | R28: 11063284 | S28: 81899047 | T28: 72634967 | U28: 3730991 | V28: 76365958
B30: Stage 3, & Non-Performing | C30: Stage 1, 2, & Performing | D30: Total | E30: Stage 3, & Non-Performing | F30: Stage 1, 2, & Performing | G30: Total
A31: Opening balance - as restated | B31: =E42 -> 99179236 | C31: =F42 -> 38307009 | D31: =G42 -> 137486245 | E31: =F49+G49 -> 91132797 | F31: =D49+E49+H49 -> 38269669 | G31: =I49 -> 129402466
A32: Transfer to stage 1 | E32: =F50+G50 -> -13318 | F32: =D50+E50+H50 -> 13318 | G32: =I50 -> 0
A33: Transfer to stage 2 | E33: =F51+G51 -> -588849 | F33: =D51+E51+H51 -> 588849 | G33: =I51 -> 0
A34: Transfer to stage 3 | E34: =F52+G52 -> 3733133 | F34: =D52+E52+H52 -> -3733133 | G34: =I52 -> 0
A35: Exchange adjustment | E35: =F53+G53 -> -658411 | F35: =D53+E53+H53 -> -85245 | G35: =I53 -> -743656
A36: Charge for the year | E36: =F54+G54 -> 26780977 | F36: =D54+E54+H54 -> 37796996 | G36: =I54 -> 64577973
A37: Reversal for the year | E37: =F55+G55 -> -9466340 | F37: =D55+E55+H55 -> -34543445 | G37: =I55 -> -44009785
A38: Net charge / (reversal) against advances | B38: =B31*B44 -> 11455469 | C38: =C31*C44 -> 10779641 | D38: =D31*D44 -> 16595894 | E38: =F56+G56 -> 17314637 | F38: =D56+E56+H56 -> 3253551 | G38: =I56 -> 20568188
A39: Charged off during the year agriculture financing | E39: =F58+G58 -> -274326 | F39: =D58+E58+H58 -> 0 | G39: =I58 -> -274326
A40: Charged off during the year corporate, commercial and SME advances | E40: =F60+G60 -> -3534146 | F40: =D60+E60+H60 -> 0 | G40: =I60 -> -3534146
A41: Written off during the year | E41: =F61+G61 -> -7932281 | F41: =D61+E61+H61 -> 0 | G41: =I61 -> -7932281
A42: Closing balance | E42: =F62+G62 -> 99179236 | F42: =D62+E62+H62 -> 38307009 | G42: =I62 -> 137486245
A44: Net Charge/Opening Balance of Loss Allowance | B44: =(3*(E44+H44)+(2*(K44+N44))+(Q44+T44))/12 -> 0.11550269 | C44: =(3*(F44+I44)+(2*(L44+O44))+(R44+U44))/12 -> 0.28140128 | D44: =(3*(G44+J44)+(2*(M44+P44))+(S44+V44))/12 -> 0.12070949 | E44: =E38/E31 -> 0.18999348 | F44: =F38/F31 -> 0.08501644 | G44: =G38/G31 -> 0.15894742 | H44: =H23/H19 -> 0.12547648 | I44: =I23/I19 -> 0.26233517 | J44: =J23/J19 -> 0.14613277 | K44: =K23/K19 -> 0.051232898 | L44: =L23/L19 -> 0.20090199 | M44: =M23/M19 -> 0.070881495 | N44: =N23/N19 -> 0.11184031 | O44: =O23/O19 -> -0.025060371 | ... V44: =V23/V19 -> 0.046894435
D46: Stage 1 | E46: Stage 2 | F46: Stage 3 | G46: Specific | H46: General | I46: Total
A47: Opening balance - as reported | G47: 84920073 | H47: 18392219 | I47: 103312292
A48: Impact of adoption of IFRS | D48: 13256248 | E48: 17241118 | F48: 86791214 | G48: -80578490 | H48: -10619916 | I48: 26090174
A49: Opening balance - as restated | D49: 13256248 | E49: 17241118 | F49: 86791214 | G49: 4341583 | H49: 7772303 | I49: 129402466
A50: Transfer to stage 1 | D50: 461482 | E50: -448164 | F50: -13318
A51: Transfer to stage 2 | D51: -1420532 | E51: 2009381 | F51: -588849
A52: Transfer to stage 3 | D52: -554289 | E52: -3178844 | F52: 3733133
A53: Exchange adjustment | D53: -44796 | E53: -24324 | F53: -605460 | G53: -52951 | H53: -16125 | I53: -743656
A54: Charge for the year | D54: 9927206 | E54: 24240602 | F54: 26686494 | G54: 94483 | H54: 3629188 | I54: 64577973
A55: Reversal for the year | D55: -8321201 | E55: -26205360 | F55: -9412105 | G55: -54235 | H55: -16884 | I55: -44009785
A56: Net charge / (reversal) against advances | D56: 1606005 | E56: -1964758 | F56: 17274389 | G56: 40248 | H56: 3612304 | I56: 20568188
A57: Charged off during the year
A58: agriculture financing | F58: -274326 | I58: -274326
A59: Charged off during the year
A60: corporate, commercial and SME advances | F60: -3534146 | I60: -3534146
A61: Written off during the year | F61: -7932281 | I61: -7932281
A62: Closing balance | D62: 13304118 | E62: 13634409 | F62: 94850356 | G62: 4328880 | H62: 11368482 | I62: 137486245

Sheet Policy Rate
A1: Observation Date | B1: Series name | C1: Observation Value | D1: Unit | E1: Observation Status | F1: Sequence No.
A2: 45783 | B2: State Bank of Pakistan's Reverse Repo Rate | C2: 12 | D2: Percent | E2: Normal | F2: 10
A3: 45783 | B3: State Bank of Pakistan's Repo Rate | C3: 10 | D3: Percent | E3: Normal | F3: 20
A4: 45783 | B4: State Bank of Pakistan's Policy (Target) Rate | C4: 11 | D4: Percent | E4: Normal | F4: 30
A5: 45685 | B5: State Bank of Pakistan's Reverse Repo Rate | C5: 13 | D5: Percent | E5: Normal | F5: 10
A6: 45685 | B6: State Bank of Pakistan's Repo Rate | C6: 11 | D6: Percent | E6: Normal | F6: 20
A7: 45685 | B7: State Bank of Pakistan's Policy (Target) Rate | C7: 12 | D7: Percent | E7: Normal | F7: 30
A8: 45643 | B8: State Bank of Pakistan's Reverse Repo Rate | C8: 14 | D8: Percent | E8: Normal | F8: 10
A9: 45643 | B9: State Bank of Pakistan's Repo Rate | C9: 12 | D9: Percent | E9: Normal | F9: 20
A10: 45643 | B10: State Bank of Pakistan's Policy (Target) Rate | C10: 13 | D10: Percent | E10: Normal | F10: 30
A11: 45601 | B11: State Bank of Pakistan's Reverse Repo Rate | C11: 16 | D11: Percent | E11: Normal | F11: 10
A12: 45601 | B12: State Bank of Pakistan's Repo Rate | C12: 14 | D12: Percent | E12: Normal | F12: 20
A13: 45601 | B13: State Bank of Pakistan's Policy (Target) Rate | C13: 15 | D13: Percent | E13: Normal | F13: 30
... A91: 43437 | B91: State Bank of Pakistan's Policy (Target) Rate | C91: 10 | D91: Percent | E91: Normal | F91: 30
A95: Date | B95: Rate | C95: Days in Effect | D95: Weighted Rate
A96: 45657 | B96: 0.13 | C96: =A96-A97+1 -> 15 | D96: =(B96*C96) -> 1.95
A97: 45643 | B97: 0.13 | C97: =A97-A98 -> 42 | D97: =(B97*C97) -> 5.46
A98: 45601 | B98: 0.15 | C98: =A98-A99 -> 53 | D98: =(B98*C98) -> 7.95
A99: 45548 | B99: 0.175 | C99: =A99-A100 -> 45 | D99: =(B99*C99) -> 7.875
A100: 45503 | B100: 0.195 | C100: =A100-A101 -> 49 | D100: =(B100*C100) -> 9.555
A101: 45454 | B101: 0.205 | C101: =A101-A102 -> 162 | D101: =(B101*C101) -> 33.21
A102: 45292 | B102: 0.22
C103: =SUM(C96:C102) -> 366 | D103: =SUM(D96:D102)/C103 -> 0.18032787
A105: Date | B105: Rate | C105: Days in Effect | D105: Weighted Rate
A106: 45291 | B106: 0.22 | C106: =A106-A107+1 -> 188 | D106: =(B106*C106) -> 41.36
A107: 45104 | B107: 0.22 | C107: =A107-A108 -> 83 | D107: =(B107*C107) -> 18.26
A108: 45021 | B108: 0.21 | C108: =A108-A109 -> 33 | D108: =(B108*C108) -> 6.93
A109: 44988 | B109: 0.2 | C109: =A109-A110 -> 38 | D109: =(B109*C109) -> 7.6
A110: 44950 | B110: 0.17 | C110: =A110-A111 -> 23 | D110: =(B110*C110) -> 3.91
A111: 44927 | B111: 0.16
C112: =SUM(C106:C111) -> 365 | D112: =SUM(D106:D111)/C112 -> 0.21386301
A114: Date | B114: Rate | C114: Days in Effect | D114: Weighted Rate
A115: 44926 | B115: 0.16 | C115: =A115-A116+1 -> 34 | D115: =(B115*C115) -> 5.44
A116: 44893 | B116: 0.16 | C116: =A116-A117 -> 138 | D116: =(B116*C116) -> 22.08
A117: 44755 | B117: 0.15 | C117: =A117-A118 -> 50 | D117: =(B117*C117) -> 7.5
A118: 44705 | B118: 0.1375 | C118: =A118-A119 -> 46 | D118: =(B118*C118) -> 6.325
A119: 44659 | B119: 0.1225 | C119: =A119-A120 -> 97 | D119: =(B119*C119) -> 11.8825
A120: 44562 | B120: 0.0975
C121: =SUM(C115:C120) -> 365 | D121: =SUM(D115:D120)/C121 -> 0.14582877
A123: Date | B123: Rate | C123: Days in Effect | D123: Weighted Rate
A124: 44561 | B124: 0.0975 | C124: =A124-A125+1 -> 17 | D124: =(B124*C124) -> 1.6575
A125: 44545 | B125: 0.0975 | C125: =A125-A126 -> 23 | D125: =(B125*C125) -> 2.2425
A126: 44522 | B126: 0.0875 | C126: =A126-A127 -> 62 | D126: =(B126*C126) -> 5.425
A127: 44460 | B127: 0.0725 | C127: =A127-A128 -> 263 | D127: =(B127*C127) -> 19.0675
A128: 44197 | B128: 0.07
C129: =SUM(C124:C128) -> 365 | D129: =SUM(D124:D128)/C129 -> 0.077787671
A131: Date | B131: Rate | C131: Days in Effect | D131: Weighted Rate
A132: 44196 | B132: 0.07 | C132: =A132-A133+1 -> 189 | D132: =(B132*C132) -> 13.23
A133: 44008 | B133: 0.07 | C133: =A133-A134 -> 39 | D133: =(B133*C133) -> 2.73
A134: 43969 | B134: 0.08 | C134: =A134-A135 -> 2 | D134: =(B134*C134) -> 0.16
A135: 43967 | B135: 0.08 | C135: =A135-A136 -> 29 | D135: =(B135*C135) -> 2.32
A136: 43938 | B136: 0.09 | C136: =A136-A137 -> 1 | D136: =(B136*C136) -> 0.09
A137: 43937 | B137: 0.09 | C137: =A137-A138 -> 22 | D137: =(B137*C137) -> 1.98
A138: 43915 | B138: 0.11 | C138: =A138-A139 -> 7 | D138: =(B138*C138) -> 0.77
A139: 43908 | B139: 0.125 | C139: =A139-A140 -> 77 | D139: =(B139*C139) -> 9.625
A140: 43831 | B140: 0.1325
C141: =SUM(C132:C140) -> 366 | D141: =SUM(D132:D140)/C141 -> 0.084439891
A143: Date | B143: Rate | C143: Days in Effect | D143: Weighted Rate
A144: 43830 | B144: 0.1325 | C144: =A144-A145+1 -> 168 | D144: =(B144*C144) -> 22.26
A145: 43663 | B145: 0.1325 | C145: =A145-A146 -> 57 | D145: =(B145*C145) -> 7.5525
A146: 43606 | B146: 0.1225 | C146: =A146-A147 -> 50 | D146: =(B146*C146) -> 6.125
A147: 43556 | B147: 0.1075 | C147: =A147-A148 -> 59 | D147: =(B147*C147) -> 6.3425
A148: 43497 | B148: 0.1025 | C148: =A148-A149 -> 31 | D148: =(B148*C148) -> 3.1775
A149: 43466 | B149: 0.1
C150: =SUM(C144:C149) -> 365 | D150: =SUM(D144:D149)/C150 -> 0.1245411

Sheet National Advances
A1: Macroeconomic Data | C1: The figures for these categories are taken from Quarterly Compendium: Statistics of the Banking System, issued by the State Bank of Pakistan
C2: PKR | D2: Forecasted Growth | F2: PKR | G2: YoY Growth | I2: PKR | J2: YoY Growth | L2: PKR | M2: YoY Growth | O2: PKR | P2: YoY Growth | R2: PKR | S2: YoY Growth | U2: PKR
A3: National Total | C3: 25 Forecast | D3: CAGR | F3: 24 | I3: 23 | L3: 22 | O3: 21 | R3: 20 | U3: 19
A4: Corporate Sector | C4: =(1+D4)*F4 -> 9.3759508e+09 | D4: =(PRODUCT(1+G4,1+J4,1+M4,1+P4,1+S4)^(1/5))-1 -> 0.10646433 | F4: =12304672000-2101528000-F11 -> 8473794000 | G4: =F4/I4-1 -> 0.29398183 | I4: =(8878428-1924342)*1000-I11 -> 6548619000 | J4: =I4/L4-1 -> -0.0079819006 | L4: =(9022077-1756988)*1000-L11 -> 6601310000 | M4: =L4/O4-1 -> 0.15011833 | O4: =(7731109-1653957)*1000-O11 -> 5739679000 | P4: =O4/R4-1 -> 0.15881803 | R4: =(6421776-1238574)*1000-R11 -> 4953046000 | S4: =R4/U4-1 -> -0.030647916 | U4: =(6356658-1247012)*1000 -> 5109646000
A5: SMEs Sector | C5: =(1+D5)*F5 -> 6.8317646e+08 | D5: =(PRODUCT(1+G5,1+J5,1+M5,1+P5,1+S5)^(1/5))-1 -> 0.077568799 | F5: =677718000-43720000 -> 633998000 | G5: =F5/I5-1 -> 0.25187931 | I5: =(537795-31358)*1000 -> 506437000 | J5: =I5/L5-1 -> 0.025834392 | L5: =(532580-38897)*1000 -> 493683000 | M5: =L5/O5-1 -> 0.037467374 | O5: =(518631-42777)*1000 -> 475854000 | P5: =O5/R5-1 -> 0.13344989 | R5: =(460690-40862)*1000 -> 419828000 | S5: =R5/U5-1 -> -0.037925835 | U5: =(480009-43631)*1000 -> 436378000
A6: Agriculture Sector | C6: =(1+D6)*F6 -> 6.4164735e+08 | D6: =(PRODUCT(1+G6,1+J6,1+M6,1+P6,1+S6)^(1/5))-1 -> 0.10916088 | F6: 578498000 | G6: =F6/I6-1 -> 0.15302958 | I6: 501720000 | J6: =I6/L6-1 -> 0.11859487 | L6: 448527000 | M6: =L6/O6-1 -> 0.10789261 | O6: 404847000 | P6: =O6/R6-1 -> 0.19764109 | R6: 338037000 | S6: =R6/U6-1 -> -0.019076582 | U6: 344611000
A7: Consumer sector | C7: =(1+D7)*F7 -> 9.7370978e+08 | D7: =(PRODUCT(1+G7,1+J7,1+M7,1+P7,1+S7)^(1/5))-1 -> 0.092532527 | F7: 891241000 | G7: =F7/I7-1 -> 0.093806263 | I7: 814807000 | J7: =I7/L7-1 -> -0.090523804 | L7: 895908000 | M7: =L7/O7-1 -> 0.091335659 | O7: 820928000 | P7: =O7/R7-1 -> 0.29233801 | R7: 635227000 | S7: =R7/U7-1 -> 0.10944472 | U7: 572563000
A8: Commodity financing | C8: =(1+D8)*F8 -> 1.5626276e+09 | D8: =(PRODUCT(1+G8,1+J8,1+M8,1+P8,1+S8)^(1/5))-1 -> 0.11825291 | F8: 1397383000 | G8: =F8/I8-1 -> -0.0068901653 | I8: 1407078000 | J8: =I8/L8-1 -> 0.11590581 | L8: 1260929000 | M8: =L8/O8-1 -> 0.27263341 | O8: 990803000 | P8: =O8/R8-1 -> 0.18887705 | R8: 833394000 | S8: =R8/U8-1 -> 0.042881848 | U8: 799126000
A9: Staff Loans | C9: =(1+D9)*F9 -> 4.3733388e+08 | D9: =(PRODUCT(1+G9,1+J9,1+M9,1+P9,1+S9)^(1/5))-1 -> 0.19383794 | F9: 366326000 | G9: =F9/I9-1 -> 0.20870151 | I9: 303074000 | J9: =I9/L9-1 -> 0.24490249 | L9: 243452000 | M9: =L9/O9-1 -> 0.22770779 | O9: 198298000 | P9: =O9/R9-1 -> 0.20916364 | R9: 163996000 | S9: =R9/U9-1 -> 0.085656408 | U9: 151057000
A10: Trade Finance | C10: =(1+D10)*F10 -> 2.3747166e+09 | D10: =(PRODUCT(1+G10,1+J10,1+M10,1+P10,1+S10)^(1/5))-1 -> 0.10696598 | F10: =2101528000+43720000 -> 2145248000 | G10: =F10/I10-1 -> 0.096920796 | I10: =(1924342+31358)*1000 -> 1955700000 | J10: =I10/L10-1 -> 0.088989551 | L10: =(1756988+38897)*1000 -> 1795885000 | M10: =L10/O10-1 -> 0.058436384 | O10: =(1653957+42777)*1000 -> 1696734000 | P10: =O10/R10-1 -> 0.32615778 | R10: =(1238574+40862)*1000 -> 1279436000 | S10: =R10/U10-1 -> -0.0086832687 | U10: =(1247012+43631)*1000 -> 1290643000
A11: Financial | C11: =(1+D11)*F11 -> 2.5419054e+09 | D11: =(PRODUCT(1+G11,1+J11,1+M11,1+P11,1+S11)^(1/5))-1 -> 0.46986173 | F11: 1729350000 | G11: =F11/I11-1 -> 3.265082 | I11: 405467000 | J11: =I11/L11-1 -> -0.38915362 | L11: 663779000 | M11: =L11/O11-1 -> 0.96690995 | O11: 337473000 | P11: =O11/R11-1 -> 0.46627939 | R11: 230156000 | S11: =R11/U11-1 -> -0.086892699 | U11: 252058000
A12: Others | C12: =(1+D12)*F12 -> 9.3257069e+08 | D12: =(PRODUCT(1+G12,1+J12,1+M12,1+P12,1+S12)^(1/5))-1 -> 0.33502451 | F12: 698542000 | G12: =F12/I12-1 -> 0.062109525 | I12: 657693000 | J12: =I12/L12-1 -> 1.7190543 | L12: 241883000 | M12: =L12/O12-1 -> 0.0046977803 | O12: 240752000 | P12: =O12/R12-1 -> 0.41105862 | R12: 170618000 | S12: =R12/U12-1 -> 0.035806217 | U12: 164720000
A13: Total | C13: =SUM(C4:C12) -> 1.9523639e+10 | D13: =(PRODUCT(1+G13,1+J13,1+M13,1+P13,1+S13)^(1/5))-1 -> 0.13147408 | F13: 16914380000 | G13: =F13/I13-1 -> 0.2911154 | I13: =SUM(I4:I12) -> 13100595000 | J13: =I13/L13-1 -> 0.036000489 | L13: =SUM(L4:L12) -> 12645356000 | M13: =L13/O13-1 -> 0.15955335 | O13: =SUM(O4:O12) -> 10905368000 | P13: =O13/R13-1 -> 0.20852002 | R13: =SUM(R4:R12) -> 9023738000 | S13: =R13/U13-1 -> -0.010642047 | U13: =SUM(U4:U12) -> 9120802000
C16: PKR | D16: Forecasted Proportion | F16: PKR | G16: Proportion of National Total | I16: PKR | J16: Proportion of National Total | L16: PKR | M16: Proportion of National Total | O16: PKR | P16: Proportion of National Total | R16: PKR | S16: Proportion of National Total | U16: PKR | V16: Proportion of National Total
A17: HBL | C17: 25 Forecast | D17: CAGR | F17: 24 | G17: 24 | I17: 23 | J17: 23 | L17: 22 | M17: 22 | O17: 21 | P17: 21 | R17: 20 | S17: 20 | U17: 19 | V17: 19
A18: Corporate and Commercial | C18: =(1+D18)*F18 -> 1.38298e+09 | D18: =(PRODUCT(1+G18,1+J18,1+M18,1+P18,1+S18)^(1/5))-1 -> 0.12051965 | F18: =F29+F30+(F34*0.8)-F21 -> 1.2342309e+09 | G18: =F18/(F4+F8) -> 0.12503382 | I18: =I29+I30+(I34*0.8)-I21 -> 8.9840339e+08 | J18: =I18/(I4+I8) -> 0.11292579 | L18: =L29+L30+(L34*0.8)-L21 -> 1.0445438e+09 | M18: =L18/(L4+L8+L5) -> 0.12500641 | O18: =O29+O30+(O34*0.8)-O21 -> 8.6655208e+08 | P18: =O18/(O4+O8+O5) -> 0.12024864 | R18: =R29+R30+(R34*0.8)-R21 -> 7.4120249e+08 | S18: =R18/(R4+R8+R5) -> 0.11942805 | U18: =U29+U30+(U34*0.8)-U21 -> 7.1161037e+08 | V18: =U18/(U4+U8+U5) -> 0.11215028
A19: Consumer and Retail | C19: =(1+D19)*F19 -> 3.4251513e+08 | D19: =(PRODUCT(1+G19,1+J19,1+M19,1+P19,1+S19)^(1/5))-1 -> 0.21239812 | F19: =F31+F32+(F34*0.2) -> 2.8251045e+08 | G19: =F19/(F7+F9) -> 0.22464842 | I19: =I31+I32+(I34*0.2) -> 2.4569749e+08 | J19: =I19/(I7+I9) -> 0.21978859 | L19: =L31+L32+(L34*0.2) -> 2.3885472e+08 | M19: =L19/(L7+L9) -> 0.20963938 | O19: =O31+O32+(O34*0.2) -> 2.0495841e+08 | P19: =O19/(O7+O9) -> 0.20109221 | R19: =R31+R32+(R34*0.2) -> 1.6541858e+08 | S19: =R19/(R7+R9) -> 0.20697425 | U19: =U31+U32+(U34*0.2) -> 1.6127346e+08 | V19: =U19/(U7+U9) -> 0.22287037
A20: Agriculture | C20: =(1+D20)*F20 -> 81114956 | D20: =(PRODUCT(1+G20,1+J20,1+M20,1+P20,1+S20)^(1/5))-1 -> 0.11020495 | F20: =F33 -> 73063046 | G20: =F20/F6 -> 0.12629784 | I20: =I33 -> 55840338 | J20: =I20/I6 -> 0.11129781 | L20: =L33 -> 53474938 | M20: =L20/L6 -> 0.11922345 | O20: =O33 -> 39183225 | P20: =O20/O6 -> 0.096785266 | R20: =R33 -> 33034776 | S20: =R20/R6 -> 0.097725326 | U20: =U33 -> 33841753 | V20: =U20/U6 -> 0.098202764
A21: SME | C21: =(1+D21)*F21 -> 1.233835e+08 | D21: =(PRODUCT(1+G21,1+J21,1+M21,1+P21,1+S21)^(1/5))-1 -> 0.072899967 | F21: 115000000 | G21: =F21/F5 -> 0.18138858 | I21: 103000000 | J21: =I21/I5 -> 0.20338166 | M21: =L21/L5 -> 0 | P21: =O21/O5 -> 0 | S21: =R21/R5 -> 0 | V21: =U21/U5 -> 0
A22: International | C22: =(1+D22)*F22 -> 4.5509602e+08 | D22: =(PRODUCT(1+G22,1+J22,1+M22,1+P22,1+S22)^(1/5))-1 -> 0.16790236 | F22: =F35 -> 3.8966958e+08 | G22: =F22/F10 -> 0.18164314 | I22: =I35 -> 3.5365547e+08 | J22: =I22/I10 -> 0.18083319 | L22: =L35 -> 2.8519967e+08 | M22: =L22/L10 -> 0.15880731 | O22: =O35 -> 2.7428257e+08 | P22: =O22/O10 -> 0.16165325 | R22: =R35 -> 2.0065568e+08 | S22: =R22/R10 -> 0.15683135 | U22: =U35 -> 1.9138095e+08 | V22: =U22/U10 -> 0.14828341
A23: Microfinance | C23: =(1+D23)*F23 -> 88831447 | D23: =(PRODUCT(1+G23,1+J23,1+M23,1+P23,1+S23)^(1/5))-1 -> 0.21581911 | F23: =F36 -> 73063046 | G23: =F23/F12 -> 0.10459363 | I23: =I36 -> 93067230 | J23: =I23/I12 -> 0.14150558 | L23: =L36 -> 89124896 | M23: =L23/L12 -> 0.36846284 | O23: =O36 -> 57267790 | P23: =O23/O12 -> 0.23787046 | R23: =R36 -> 41599348 | S23: =R23/R12 -> 0.2438157 | U23: =U36 -> 31507839 | V23: =U23/U12 -> 0.1912812
A24: Financial Institution | C24: =(1+D24)*F24 -> 3.163451e+08 | D24: =(PRODUCT(1+G24,1+J24,1+M24,1+P24,1+S24)^(1/5))-1 -> 0.18084229 | F24: =F37 -> 2.6789784e+08 | G24: =F24/F11 -> 0.15491244 | I24: =I37 -> 1.1168068e+08 | J24: =I24/I11 -> 0.27543715 | L24: =L37 -> 71299917 | M24: =L24/L11 -> 0.10741514 | O24: =O37 -> 64803025 | P24: =O24/O11 -> 0.19202433 | R24: =R37 -> 41599348 | S24: =R24/R11 -> 0.18074414 | U24: =U37 -> 39676538 | V24: =U24/U11 -> 0.15741035
A25: Gross Advances | C25: =SUM(C18:C24) -> 2.7902661e+09 | D25: =(PRODUCT(1+G25,1+J25,1+M25,1+P25,1+S25)^(1/5))-1 -> 0.14015791 | F25: =SUM(F18:F24) -> 2435434872 | G25: =F25/F13 -> 0.14398606 | I25: =SUM(I18:I24) -> 1861344592 | J25: =I25/I13 -> 0.14208092 | L25: =SUM(L18:L24) -> 1.7824979e+09 | M25: =L25/L13 -> 0.14096068 | O25: =SUM(O18:O24) -> 1.5070471e+09 | P25: =O25/O13 -> 0.13819314 | R25: =SUM(R18:R24) -> 1223510222 | S25: =R25/R13 -> 0.13558796 | U25: =SUM(U18:U24) -> 1.1692909e+09 | V25: =U25/U13 -> 0.12820045
C27: The proportions for these categories are taken from HBL Investor Presentation issued quarterly
A29: Corporate | E29: 0.44 | F29: =F$38*E29 -> 1.0715913e+09 | H29: 0.39 | I29: =I$38*H29 -> 7.2592439e+08 | K29: 0.43 | L29: =L$38*K29 -> 7.6647411e+08 | N29: 0.43 | O29: =O$38*N29 -> 6.4803025e+08 | Q29: 0.446 | R29: =R$38*Q29 -> 5.4568556e+08 | T29: 0.446 | U29: =U$38*T29 -> 5.2046282e+08
A30: Commercial | E30: 0.05 | F30: =F$38*E30 -> 1.2177174e+08 | H30: 0.06 | I30: =I$38*H30 -> 1.1168068e+08 | K30: 0.06 | L30: =L$38*K30 -> 1.0694988e+08 | N30: 0.061 | O30: =O$38*N30 -> 91929873 | Q30: 0.059 | R30: =R$38*Q30 -> 72187103 | T30: 0.059 | U30: =U$38*T30 -> 68850463
A31: Consumer | E31: 0.05 | F31: =F$38*E31 -> 1.2177174e+08 | H31: 0.06 | I31: =I$38*H31 -> 1.1168068e+08 | K31: 0.06 | L31: =L$38*K31 -> 1.0694988e+08 | N31: 0.068 | O31: =O$38*N31 -> 1.024792e+08 | Q31: 0.061 | R31: =R$38*Q31 -> 74634124 | T31: 0.051 | U31: =U$38*T31 -> 59514807
A32: Retail Lending | E32: 0.05 | F32: =F$38*E32 -> 1.2177174e+08 | H32: 0.05 | I32: =I$38*H32 -> 93067230 | K32: 0.05 | L32: =L$38*K32 -> 89124896 | N32: 0.047 | O32: =O$38*N32 -> 70831214 | Q32: 0.049 | R32: =R$38*Q32 -> 59952001 | T32: 0.061 | U32: =U$38*T32 -> 71184377
A33: Agriculture | E33: 0.03 | F33: =F$38*E33 -> 73063046 | H33: 0.03 | I33: =I$38*H33 -> 55840338 | K33: 0.03 | L33: =L$38*K33 -> 53474938 | N33: 0.026 | O33: =O$38*N33 -> 39183225 | Q33: 0.027 | R33: =R$38*Q33 -> 33034776 | T33: 0.029 | U33: =U$38*T33 -> 33841753
A34: Islamic | E34: 0.08 | F34: =F$38*E34 -> 1.9483479e+08 | H34: 0.11 | I34: =I$38*H34 -> 2.0474791e+08 | K34: 0.12 | L34: =L$38*K34 -> 2.1389975e+08 | N34: 0.105 | O34: =O$38*N34 -> 1.5823995e+08 | Q34: 0.126 | R34: =R$38*Q34 -> 1.5416229e+08 | T34: 0.131 | U34: =U$38*T34 -> 1.5287137e+08
A35: International | E35: 0.16 | F35: =F$38*E35 -> 3.8966958e+08 | H35: 0.19 | I35: =I$38*H35 -> 3.5365547e+08 | K35: 0.16 | L35: =L$38*K35 -> 2.8519967e+08 | N35: 0.182 | O35: =O$38*N35 -> 2.7428257e+08 | Q35: 0.164 | R35: =R$38*Q35 -> 2.0065568e+08 | T35: 0.164 | U35: =U$38*T35 -> 1.9138095e+08
A36: Microfinance | E36: 0.03 | F36: =F$38*E36 -> 73063046 | H36: 0.05 | I36: =I$38*H36 -> 93067230 | K36: 0.05 | L36: =L$38*K36 -> 89124896 | N36: 0.038 | O36: =O$38*N36 -> 57267790 | Q36: 0.034 | R36: =R$38*Q36 -> 41599348 | T36: 0.027 | U36: =U$38*T36 -> 31507839
A37: Financial Institution | E37: 0.11 | F37: =F$38*E37 -> 2.6789784e+08 | H37: 0.06 | I37: =I$38*H37 -> 1.1168068e+08 | K37: 0.04 | L37: =L$38*K37 -> 71299917 | N37: 0.043 | O37: =O$38*N37 -> 64803025 | Q37: 0.034 | R37: =R$38*Q37 -> 41599348 | T37: 0.034 | U37: =U$38*T37 -> 39676538
A38: Gross Advances | E38: 1 | F38: 2435434872 | H38: 1 | I38: 1861344592 | L38: 1782497923 | O38: 1507047097 | R38: =SOFP!N8 -> 1223510222 | U38: =SOFP!P8 -> 1166956994

Sheet National Deposits
A1: Macroeconomic Data | C1: The figures for these categories are taken from Quarterly Compendium: Statistics of the Banking System, issued by the State Bank of Pakistan
C2: PKR | D2: Forecasted Growth | F2: PKR | G2: YoY Growth | I2: PKR | J2: YoY Growth | L2: PKR | M2: YoY Growth | O2: PKR | P2: YoY Growth | R2: PKR | S2: YoY Growth | U2: PKR
A3: National Total | C3: 25 Forecast | D3: CAGR | F3: 24 | I3: 23 | L3: 22 | O3: 21 | R3: 20 | U3: 19
A4: Current Accounts | C4: =(1+D4)*F4 -> 1.198773e+10 | D4: =(PRODUCT(1+G4,1+J4,1+M4,1+P4,1+S4)^(1/5))-1 -> 0.14321289 | F4: 10486000000 | G4: =F4/I4-1 -> -0.0028527957 | I4: 10516000000 | J4: =I4/L4-1 -> 0.18064444 | L4: 8907000000 | M4: =L4/O4-1 -> 0.13769319 | O4: 7829000000 | P4: =O4/R4-1 -> 0.21098221 | R4: 6465000000 | S4: =R4/U4-1 -> 0.20391061 | U4: 5370000000
A5: Saving Deposits | C5: =(1+D5)*F5 -> 1.5080665e+10 | D5: =(PRODUCT(1+G5,1+J5,1+M5,1+P5,1+S5)^(1/5))-1 -> 0.17780886 | F5: 12804000000 | G5: =F5/I5-1 -> 0.23543034 | I5: 10364000000 | J5: =I5/L5-1 -> 0.26267057 | L5: 8208000000 | M5: =L5/O5-1 -> 0.097472924 | O5: 7479000000 | P5: =O5/R5-1 -> 0.12145749 | R5: 6669000000 | S5: =R5/U5-1 -> 0.18056293 | U5: 5649000000
A6: Fixed Deposits | C6: =(1+D6)*F6 -> 4.6558488e+09 | D6: =(PRODUCT(1+G6,1+J6,1+M6,1+P6,1+S6)^(1/5))-1 -> 0.070310067 | F6: 4350000000 | G6: =F6/I6-1 -> -0.09261577 | I6: 4794000000 | J6: =I6/L6-1 -> 0.16784409 | L6: 4105000000 | M6: =L6/O6-1 -> 0.04373252 | O6: 3933000000 | P6: =O6/R6-1 -> 0.17684022 | R6: 3342000000 | S6: =R6/U6-1 -> 0.079108815 | U6: 3097000000
A7: Others | C7: =(1+D7)*F7 -> 2.0637581e+09 | D7: =(PRODUCT(1+G7,1+J7,1+M7,1+P7,1+S7)^(1/5))-1 -> 0.5753879 | F7: 1310000000 | G7: =F7/I7-1 -> 2.2914573 | I7: 398000000 | J7: =I7/L7-1 -> -0.067915691 | L7: 427000000 | M7: =L7/O7-1 -> 0.94090909 | O7: 220000000 | P7: =O7/R7-1 -> 0.25 | R7: 176000000 | S7: =R7/U7-1 -> 0.3037037 | U7: 135000000
A8: Customer | C8: =(1+D8)*F8 -> 3.3358707e+10 | D8: =(PRODUCT(1+G8,1+J8,1+M8,1+P8,1+S8)^(1/5))-1 -> 0.15228696 | F8: =(SUM(F4:F7)) -> 28950000000 | G8: =F8/I8-1 -> 0.11038662 | I8: =(SUM(I4:I7)) -> 26072000000 | J8: =I8/L8-1 -> 0.20441632 | L8: =(SUM(L4:L7)) -> 21647000000 | M8: =L8/O8-1 -> 0.11232722 | O8: =(SUM(O4:O7)) -> 19461000000 | P8: =O8/R8-1 -> 0.16868845 | R8: =(SUM(R4:R7)) -> 16652000000 | S8: =R8/U8-1 -> 0.1684794 | U8: =(SUM(U4:U7)) -> 14251000000
A9: Financial Institutions | C9: =(1+D9)*F9 -> 1.4059817e+09 | D9: =(PRODUCT(1+G9,1+J9,1+M9,1+P9,1+S9)^(1/5))-1 -> 0.052381541 | F9: 1336000000 | G9: =F9/I9-1 -> -0.25818989 | I9: 1801000000 | J9: =I9/L9-1 -> 1.1313609 | L9: 845000000 | M9: =L9/O9-1 -> -0.44002651 | O9: 1509000000 | P9: =O9/R9-1 -> 0.23587224 | R9: 1221000000 | S9: =R9/U9-1 -> 0.17971014 | U9: 1035000000
A10: DEPOSITS (Domestic) | C10: =(1+D10)*F10 -> 3.4725518e+10 | D10: =(PRODUCT(1+G10,1+J10,1+M10,1+P10,1+S10)^(1/5))-1 -> 0.14654863 | F10: 30287000000 | G10: =F10/I10-1 -> 0.086646096 | I10: 27872000000 | J10: =I10/L10-1 -> 0.23919616 | L10: 22492000000 | M10: =L10/O10-1 -> 0.07252873 | O10: 20971000000 | P10: =O10/R10-1 -> 0.17333408 | R10: 17873000000 | S10: =R10/U10-1 -> 0.16923983 | U10: 15286000000
A12: Current Accounts | C12: =(1+D12)*F12 -> 9.1650293e+08 | D12: =(PRODUCT(1+G12,1+J12,1+M12,1+P12,1+S12)^(1/5))-1 -> 0.23684606 | F12: =(F20-F4) -> 741000000 | G12: =F12/I12-1 -> 0.27758621 | I12: =(I70-I4) -> 580000000 | J12: =I12/L12-1 -> 0.35198135 | L12: =(L70-L4) -> 429000000 | M12: =L12/O12-1 -> 0.30792683 | O12: =(O70-O4) -> 328000000 | P12: =O12/R12-1 -> 0.30677291 | R12: =(R70-R4) -> 251000000 | S12: =R12/U12-1 -> -0.01953125 | U12: =(U70-U4) -> 256000000
A13: Saving Deposits | C13: =(1+D13)*F13 -> 2.0494131e+08 | D13: =(PRODUCT(1+G13,1+J13,1+M13,1+P13,1+S13)^(1/5))-1 -> 0.22719349 | F13: =(F21-F5) -> 167000000 | G13: =F13/I13-1 -> 0.59047619 | I13: =(I69-I5) -> 105000000 | J13: =I13/L13-1 -> 0.16666667 | L13: =(L69-L5) -> 90000000 | M13: =L13/O13-1 -> 0.084337349 | O13: =(O69-O5) -> 83000000 | P13: =O13/R13-1 -> 0.27692308 | R13: =(R69-R5) -> 65000000 | S13: =R13/U13-1 -> 0.083333333 | U13: =(U69-U5) -> 60000000
A14: Fixed Deposits | C14: =(1+D14)*F14 -> 5.8354456e+08 | D14: =(PRODUCT(1+G14,1+J14,1+M14,1+P14,1+S14)^(1/5))-1 -> 0.10940031 | F14: =(F22-F6) -> 526000000 | G14: =F14/I14-1 -> 0.019379845 | I14: =(I68-I6) -> 516000000 | J14: =I14/L14-1 -> 0.29648241 | L14: =(L68-L6) -> 398000000 | M14: =L14/O14-1 -> 0.3537415 | O14: =(O68-O6) -> 294000000 | P14: =O14/R14-1 -> 0.017301038 | R14: =(R68-R6) -> 289000000 | S14: =R14/U14-1 -> -0.076677316 | U14: =(U68-U6) -> 313000000
A15: Others | C15: =(1+D15)*F15 -> 21194627 | D15: =(PRODUCT(1+G15,1+J15,1+M15,1+P15,1+S15)^(1/5))-1 -> 0.1155067 | F15: =(F23-F7) -> 19000000 | G15: =F15/I15-1 -> 0.11764706 | I15: =(I73-I7) -> 17000000 | J15: =I15/L15-1 -> -0.15 | L15: =(L73-L7) -> 20000000 | M15: =L15/O15-1 -> 0.53846154 | O15: =(O73-O7) -> 13000000 | P15: =O15/R15-1 -> 0 | R15: =(R73-R7) -> 13000000 | S15: =R15/U15-1 -> 0.18181818 | U15: =(U73-U7) -> 11000000
A16: Customer | C16: =(1+D16)*F16 -> 1.7119171e+09 | D16: =(PRODUCT(1+G16,1+J16,1+M16,1+P16,1+S16)^(1/5))-1 -> 0.17819487 | F16: =(SUM(F12:F15)) -> 1453000000 | G16: =F16/I16-1 -> 0.19293924 | I16: =(SUM(I12:I15)) -> 1218000000 | J16: =I16/L16-1 -> 0.29989328 | L16: =(SUM(L12:L15)) -> 937000000 | M16: =L16/O16-1 -> 0.30501393 | O16: =(SUM(O12:O15)) -> 718000000 | P16: =O16/R16-1 -> 0.1618123 | R16: =(SUM(R12:R15)) -> 618000000 | S16: =R16/U16-1 -> -0.034375 | U16: =(SUM(U12:U15)) -> 640000000
A17: Financial Institutions | C17: =(1+D17)*F17 -> 60653839 | D17: =(PRODUCT(1+G17,1+J17,1+M17,1+P17,1+S17)^(1/5))-1 -> 0.14441205 | F17: =(F25-F9) -> 53000000 | G17: =F17/I17-1 -> 0.39473684 | I17: =(I74-I9) -> 38000000 | J17: =I17/L17-1 -> 0.15151515 | L17: =(L74-L9) -> 33000000 | M17: =L17/O17-1 -> 0.064516129 | O17: =(O74-O9) -> 31000000 | P17: =O17/R17-1 -> 0.14814815 | R17: =(R74-R9) -> 27000000 | S17: =R17/U17-1 -> 0 | U17: =(U74-U9) -> 27000000
A18: DEPOSITS (International) | C18: =(1+D18)*F18 -> 1.7710003e+09 | D18: =(PRODUCT(1+G18,1+J18,1+M18,1+P18,1+S18)^(1/5))-1 -> 0.17674438 | F18: =(F77-F10) -> 1505000000 | G18: =F18/I18-1 -> 0.19824841 | I18: =(I77-I10) -> 1256000000 | J18: =I18/L18-1 -> 0.29618163 | L18: =(L77-L10) -> 969000000 | M18: =L18/O18-1 -> 0.29372497 | O18: =(O77-O10) -> 749000000 | P18: =O18/R18-1 -> 0.15944272 | R18: =(R77-R10) -> 646000000 | S18: =R18/U18-1 -> -0.031484258 | U18: =(U77-U10) -> 667000000
A20: Current Accounts | C20: =(1+D20)*F20 -> 1.1703804e+10 | D20: =(PRODUCT(1+G20,1+J20,1+M20,1+P20,1+S20)^(1/5))-1 -> 0.042469365 | F20: 11227000000 | G20: =F20/I20-1 -> 0.011806056 | I20: 11096000000 | J20: =I20/L20-1 -> 0.18851757 | L20: 9336000000 | M20: =L20/O20-1 -> -0.20807532 | O20: =(O22+O21) -> 11789000000 | P20: =O20/R20-1 -> 0.13738543 | R20: =(R22+R21) -> 10365000000 | S20: =R20/U20-1 -> 0.13663779 | U20: =(U22+U21) -> 9119000000
A21: Saving Deposits | C21: =(1+D21)*F21 -> 1.5284673e+10 | D21: =(PRODUCT(1+G21,1+J21,1+M21,1+P21,1+S21)^(1/5))-1 -> 0.17837273 | F21: 12971000000 | G21: =F21/I21-1 -> 0.23899131 | I21: 10469000000 | J21: =I21/L21-1 -> 0.26162931 | L21: 8298000000 | M21: =L21/O21-1 -> 0.097328749 | O21: 7562000000 | P21: =O21/R21-1 -> 0.12295812 | R21: 6734000000 | S21: =R21/U21-1 -> 0.17954108 | U21: 5709000000
A22: Fixed Deposits | C22: =(1+D22)*F22 -> 5.2375184e+09 | D22: =(PRODUCT(1+G22,1+J22,1+M22,1+P22,1+S22)^(1/5))-1 -> 0.074142409 | F22: 4876000000 | G22: =F22/I22-1 -> -0.08173258 | I22: 5310000000 | J22: =I22/L22-1 -> 0.17921386 | L22: 4503000000 | M22: =L22/O22-1 -> 0.065294535 | O22: 4227000000 | P22: =O22/R22-1 -> 0.16414211 | R22: 3631000000 | S22: =R22/U22-1 -> 0.064809384 | U22: 3410000000
A23: Others | C23: =(1+D23)*F23 -> 2.0670901e+09 | D23: =(PRODUCT(1+G23,1+J23,1+M23,1+P23,1+S23)^(1/5))-1 -> 0.55537253 | F23: 1329000000 | G23: =F23/I23-1 -> 2.2024096 | I23: 415000000 | J23: =I23/L23-1 -> -0.071588367 | L23: 447000000 | M23: =L23/O23-1 -> 0.91845494 | O23: 233000000 | P23: =O23/R23-1 -> 0.23280423 | R23: 189000000 | S23: =R23/U23-1 -> 0.29452055 | U23: 146000000
A24: Customer | C24: =(1+D24)*F24 -> 3.3621085e+10 | D24: =(PRODUCT(1+G24,1+J24,1+M24,1+P24,1+S24)^(1/5))-1 -> 0.10584762 | F24: =(SUM(F20:F23)) -> 30403000000 | G24: =F24/I24-1 -> 0.11407109 | I24: =(SUM(I20:I23)) -> 27290000000 | J24: =I24/L24-1 -> 0.20837761 | L24: =(SUM(L20:L23)) -> 22584000000 | M24: =L24/O24-1 -> -0.051530805 | O24: =(SUM(O20:O23)) -> 23811000000 | P24: =O24/R24-1 -> 0.13824753 | R24: =(SUM(R20:R23)) -> 20919000000 | S24: =R24/U24-1 -> 0.13789164 | U24: =(SUM(U20:U23)) -> 18384000000
A25: Financial Institutions | C25: =(1+D25)*F25 -> 1.4656079e+09 | D25: =(PRODUCT(1+G25,1+J25,1+M25,1+P25,1+S25)^(1/5))-1 -> 0.055153262 | F25: 1389000000 | G25: =F25/I25-1 -> -0.24469821 | I25: 1839000000 | J25: =I25/L25-1 -> 1.094533 | L25: 878000000 | M25: =L25/O25-1 -> -0.42987013 | O25: 1540000000 | P25: =O25/R25-1 -> 0.23397436 | R25: 1248000000 | S25: =R25/U25-1 -> 0.17514124 | U25: 1062000000
A26: DEPOSITS (Total) | C26: =(1+D26)*F26 -> 3.6493284e+10 | D26: =(PRODUCT(1+G26,1+J26,1+M26,1+P26,1+S26)^(1/5))-1 -> 0.14787632 | F26: 31792000000 | G26: =F26/I26-1 -> 0.091458391 | I26: 29128000000 | J26: =I26/L26-1 -> 0.24154981 | L26: 23461000000 | M26: =L26/O26-1 -> 0.080156538 | O26: 21720000000 | P26: =O26/R26-1 -> 0.17284951 | R26: 18519000000 | S26: =R26/U26-1 -> 0.16084749 | U26: 15953000000
C29: PKR | D29: Forecasted Proportion | F29: PKR | G29: Proportion of National Total | I29: PKR | J29: Proportion of National Total | L29: PKR | M29: Proportion of National Total | O29: PKR | P29: Proportion of National Total | R29: PKR | S29: Proportion of National Total | U29: PKR | V29: Proportion of National Total
A30: HBL | C30: 25 Forecast | D30: CAGR | F30: 24 | G30: 24 | I30: 23 | J30: 23 | L30: 22 | M30: 22 | O30: 21 | P30: 21 | R30: 20 | S30: 20 | U30: 19 | V30: 19
A31: Current Accounts | C31: =(1+D31)*F31 -> 1.4151787e+09 | D31: =(PRODUCT(1+G31,1+J31,1+M31,1+P31,1+S31)^(1/5))-1 -> 0.12289867 | F31: =F45-F38 -> 1260290667 | G31: =F31/(F4+(F$7*(F4/F$8))) -> 0.11498482 | I31: =I45-I38 -> 1.1179706e+09 | J31: =I31/(I4+(I$7*(I4/I$8))) -> 0.1047129 | L31: =L45-L38 -> 1.1966596e+09 | M31: =L31/(L4+(L$7*(L4/L$8))) -> 0.13175159 | O31: =O45-O38 -> 1.0183543e+09 | P31: =O31/(O4+(O$7*(O4/O$8))) -> 0.12862062 | R31: =R45-R38 -> 8.8011308e+08 | S31: =R31/(R4+(R$7*(R4/R$8))) -> 0.13471124 | U31: =U45-U38 -> 7.6935686e+08 | V31: =U31/(U4+(U$7*(U4/U$8))) -> 0.14192498
A32: Saving Deposits | C32: =(1+D32)*F32 -> 2.1628169e+09 | D32: =(PRODUCT(1+G32,1+J32,1+M32,1+P32,1+S32)^(1/5))-1 -> 0.15380996 | F32: =F46-F39 -> 1874500149 | G32: =F32/(F5+(F$7*(F5/F$8))) -> 0.14006172 | I32: =I46-I39 -> 1.7007409e+09 | J32: =I32/(I5+(I$7*(I5/I$8))) -> 0.16163342 | L32: =L46-L39 -> 1.2859683e+09 | M32: =L32/(L5+(L$7*(L5/L$8))) -> 0.15364188 | O32: =O46-O39 -> 1.1795808e+09 | P32: =O32/(O5+(O$7*(O5/O$8))) -> 0.15595603 | R32: =R46-R39 -> 1.0639957e+09 | S32: =R32/(R5+(R$7*(R5/R$8))) -> 0.15787489 | U32: =U46-U39 -> 9.8251818e+08 | V32: =U32/(U5+(U$7*(U5/U$8))) -> 0.17229565
A33: Fixed Deposits | C33: =(1+D33)*F33 -> 6.5546415e+08 | D33: =(PRODUCT(1+G33,1+J33,1+M33,1+P33,1+S33)^(1/5))-1 -> 0.11838362 | F33: =F47-F40 -> 586081678 | G33: =F33/(F6+(F$7*(F6/F$8))) -> 0.1288987 | I33: =I47-I40 -> 5.9834402e+08 | J33: =I33/(I6+(I$7*(I6/I$8))) -> 0.12293437 | L33: =L47-L40 -> 4.5250714e+08 | M33: =L33/(L6+(L$7*(L6/L$8))) -> 0.10810081 | O33: =O47-O40 -> 5.2184457e+08 | P33: =O33/(O6+(O$7*(O6/O$8))) -> 0.13120042 | R33: =R47-R40 -> 3.4143913e+08 | S33: =R33/(R6+(R$7*(R6/R$8))) -> 0.10109758 | U33: =U47-U40 -> 2.9259623e+08 | V33: =U33/(U6+(U$7*(U6/U$8))) -> 0.093590723
A34: Customer | C34: =(1+D34)*F34 -> 4.2112869e+09 | D34: =(PRODUCT(1+G34,1+J34,1+M34,1+P34,1+S34)^(1/5))-1 -> 0.1341174 | F34: =F48-F41 -> 3713272494 | G34: =F34/F8 -> 0.12826503 | I34: =I48-I41 -> 3.4095435e+09 | J34: =I34/I8 -> 0.13077415 | L34: =L48-L41 -> 2.9263012e+09 | M34: =L34/L8 -> 0.13518276 | O34: =O48-O41 -> 2.7140347e+09 | P34: =O34/O8 -> 0.13946019 | R34: =R48-R41 -> 2.2803499e+09 | S34: =R34/R8 -> 0.1369415 | U34: =U48-U41 -> 2.0400779e+09 | V34: =U34/U8 -> 0.14315331
A35: Financial Institutions | C35: =(1+D35)*F35 -> 62635559 | D35: =(PRODUCT(1+G35,1+J35,1+M35,1+P35,1+S35)^(1/5))-1 -> 0.14511297 | F35: =F49-F42 -> 54698148 | G35: =F35/F9 -> 0.040941728 | I35: =I49-I42 -> 1.7780832e+08 | J35: =I35/I9 -> 0.098727553 | L35: =L49-L42 -> 1.1459933e+08 | M35: =L35/L9 -> 0.13562051 | O35: =O49-O42 -> 3.369637e+08 | P35: =O35/O9 -> 0.22330265 | R35: =R49-R42 -> 2.9212132e+08 | S35: =R35/R9 -> 0.2392476 | U35: =U49-U42 -> 1.3111931e+08 | V35: =U35/U9 -> 0.12668532
A36: DEPOSITS (Domestic) | C36: =(1+D36)*F36 -> 4.2790559e+09 | D36: =(PRODUCT(1+G36,1+J36,1+M36,1+P36,1+S36)^(1/5))-1 -> 0.13551886 | F36: =F50-F43 -> 3768370642 | G36: =F36/F10 -> 0.12442205 | I36: =I50-I43 -> 3587351836 | J36: =I36/I10 -> 0.12870809 | L36: =L50-L43 -> 3041342252 | M36: =L36/L10 -> 0.13521884 | O36: =O50-O43 -> 3050998398 | P36: =O36/O10 -> 0.14548655 | R36: =R50-R43 -> 2572071390 | S36: =R36/R10 -> 0.14390821 | U36: =U50-U43 -> 2171197169 | V36: =U36/U10 -> 0.14203828
A38: Current Accounts | C38: =(1+D38)*F38 -> 4.223461e+08 | D38: =(PRODUCT(1+G38,1+J38,1+M38,1+P38,1+S38)^(1/5))-1 -> 0.42491935 | F38: =G38*F12 -> 296400000 | G38: =G$43 -> 0.4 | I38: =J38*I12 -> 2.5628981e+08 | J38: =J$43 -> 0.44187898 | L38: =M38*L12 -> 1.8948607e+08 | M38: =M$43 -> 0.44169247 | O38: =P38*O12 -> 1.449506e+08 | P38: =P$43 -> 0.44192256 | R38: =S38*R12 -> 1.0036115e+08 | S38: =S$43 -> 0.3998452 | U38: =V38*U12 -> 1.0224648e+08 | V38: =V$43 -> 0.3994003
A39: Saving Deposits | C39: =(1+D39)*F39 -> 95184613 | D39: =(PRODUCT(1+G39,1+J39,1+M39,1+P39,1+S39)^(1/5))-1 -> 0.42491935 | F39: =G39*F13 -> 66800000 | G39: =G$43 -> 0.4 | I39: =J39*I13 -> 46397293 | J39: =J$43 -> 0.44187898 | L39: =M39*L13 -> 39752322 | M39: =M$43 -> 0.44169247 | O39: =P39*O13 -> 36679573 | P39: =P$43 -> 0.44192256 | R39: =S39*R13 -> 25989938 | S39: =S$43 -> 0.3998452 | U39: =V39*U13 -> 23964018 | V39: =V$43 -> 0.3994003
A40: Fixed Deposits | C40: =(1+D40)*F40 -> 2.9980303e+08 | D40: =(PRODUCT(1+G40,1+J40,1+M40,1+P40,1+S40)^(1/5))-1 -> 0.42491935 | F40: =G40*F14 -> 210400000 | G40: =G$43 -> 0.4 | I40: =J40*I14 -> 2.2800955e+08 | J40: =J$43 -> 0.44187898 | L40: =M40*L14 -> 1.757936e+08 | M40: =M$43 -> 0.44169247 | O40: =P40*O14 -> 1.2992523e+08 | P40: =P$43 -> 0.44192256 | R40: =S40*R14 -> 1.1555526e+08 | S40: =S$43 -> 0.3998452 | U40: =V40*U14 -> 1.2501229e+08 | V40: =V$43 -> 0.3994003
A41: Customer | C41: =(1+D41)*F41 -> 8.2816313e+08 | D41: =(PRODUCT(1+G41,1+J41,1+M41,1+P41,1+S41)^(1/5))-1 -> 0.42491935 | F41: =G41*F16 -> 581200000 | G41: =G$43 -> 0.4 | I41: =J41*I16 -> 5.382086e+08 | J41: =J$43 -> 0.44187898 | L41: =M41*L16 -> 4.1386584e+08 | M41: =M$43 -> 0.44169247 | O41: =P41*O16 -> 3.173004e+08 | P41: =P$43 -> 0.44192256 | R41: =S41*R16 -> 2.4710433e+08 | S41: =S$43 -> 0.3998452 | U41: =V41*U16 -> 2.5561619e+08 | V41: =V$43 -> 0.3994003
A42: Financial Institutions | C42: =(1+D42)*F42 -> 30208290 | D42: =(PRODUCT(1+G42,1+J42,1+M42,1+P42,1+S42)^(1/5))-1 -> 0.42491935 | F42: =G42*F17 -> 21200000 | G42: =G$43 -> 0.4 | I42: =J42*I17 -> 16791401 | J42: =J$43 -> 0.44187898 | L42: =M42*L17 -> 14575851 | M42: =M$43 -> 0.44169247 | O42: =P42*O17 -> 13699599 | P42: =P$43 -> 0.44192256 | R42: =S42*R17 -> 10795820 | S42: =S$43 -> 0.3998452 | U42: =V42*U17 -> 10783808 | V42: =V$43 -> 0.3994003
A43: DEPOSITS (International) | C43: =(1+D43)*F43 -> 8.5780145e+08 | D43: =(PRODUCT(1+G43,1+J43,1+M43,1+P43,1+S43)^(1/5))-1 -> 0.42491935 | F43: 602000000 | G43: =F43/F18 -> 0.4 | I43: =555000000 -> 555000000 | J43: =I43/I18 -> 0.44187898 | L43: 428000000 | M43: =L43/L18 -> 0.44169247 | O43: 331000000 | P43: =O43/O18 -> 0.44192256 | R43: 258300000 | S43: =R43/R18 -> 0.3998452 | U43: 266400000 | V43: =U43/U18 -> 0.3994003
A45: Fixed Deposits | C45: =(1+D45)*F45 -> 1.7406955e+09 | D45: =(PRODUCT(1+G45,1+J45,1+M45,1+P45,1+S45)^(1/5))-1 -> 0.11820255 | F45: 1556690667 | G45: =F45/(F20+(F$23*(F20/F$24))) -> 0.13284879 | I45: 1374260370 | J45: =I45/(I20+(I$23*(I20/I$24))) -> 0.12199666 | L45: 1386145657 | M45: =L45/(L20+(L$23*(L20/L$24))) -> 0.14559153 | O45: 1163304884 | P45: =O45/(O20+(O$23*(O20/O$24))) -> 0.097720909 | R45: 980474227 | S45: =R45/(R20+(R$23*(R20/R$24))) -> 0.093747719 | U45: 871603340 | V45: =U45/(U20+(U$23*(U20/U$24))) -> 0.094827928
A46: Saving Deposits | C46: =(1+D46)*F46 -> 2.2457072e+09 | D46: =(PRODUCT(1+G46,1+J46,1+M46,1+P46,1+S46)^(1/5))-1 -> 0.15680574 | F46: 1941300149 | G46: =F46/(F21+(F$23*(F21/F$24))) -> 0.14339639 | I46: 1747138168 | J46: =I46/(I21+(I$23*(I21/I$24))) -> 0.16438699 | L46: 1325720669 | M46: =L46/(L21+(L$23*(L21/L$24))) -> 0.15666308 | O46: 1216260416 | P46: =O46/(O21+(O$23*(O21/O$24))) -> 0.15927984 | R46: 1089985621 | S46: =R46/(R21+(R$23*(R21/R$24))) -> 0.16041371 | U46: 1006482193 | V46: =U46/(U21+(U$23*(U21/U$24))) -> 0.17490839
A47: Current Accounts | C47: =(1+D47)*F47 -> 9.1176835e+08 | D47: =(PRODUCT(1+G47,1+J47,1+M47,1+P47,1+S47)^(1/5))-1 -> 0.14474492 | F47: 796481678 | G47: =F47/(F22+(F$23*(F22/F$24))) -> 0.15650603 | I47: 826353573 | J47: =I47/(I22+(I$23*(I22/I$24))) -> 0.15329104 | L47: 628300746 | M47: =L47/(L22+(L$23*(L22/L$24))) -> 0.1368213 | O47: 651769799 | P47: =O47/(O22+(O$23*(O22/O$24))) -> 0.15269784 | R47: 456994397 | S47: =R47/(R22+(R$23*(R22/R$24))) -> 0.12473217 | U47: 417608521 | V47: =U47/(U22+(U$23*(U22/U$24))) -> 0.12150092
A48: Customer | C48: =(1+D48)*F48 -> 4.8799787e+09 | D48: =(PRODUCT(1+G48,1+J48,1+M48,1+P48,1+S48)^(1/5))-1 -> 0.13633949 | F48: 4294472494 | G48: =F48/F24 -> 0.1412516 | I48: 3947752111 | J48: =I48/I24 -> 0.14465929 | L48: 3340167072 | M48: =L48/L24 -> 0.14789971 | O48: 3031335099 | P48: =O48/O24 -> 0.12730818 | R48: 2527454245 | S48: =R48/R24 -> 0.12082099 | U48: 2295694054 | V48: =U48/U24 -> 0.12487457
A49: Financial Institutions | C49: =(1+D49)*F49 -> 87539601 | D49: =(PRODUCT(1+G49,1+J49,1+M49,1+P49,1+S49)^(1/5))-1 -> 0.15338257 | F49: 75898148 | G49: =F49/F25 -> 0.054642295 | I49: 194599725 | J49: =I49/I25 -> 0.10581823 | L49: 129175180 | M49: =L49/L25 -> 0.14712435 | O49: 350663299 | P49: =O49/O25 -> 0.22770344 | R49: 302917145 | S49: =R49/R25 -> 0.24272207 | U49: 141903115 | V49: =U49/U25 -> 0.13361875
A50: DEPOSITS (Total) | C50: =(1+D50)*F50 -> 5.0136926e+09 | D50: =(PRODUCT(1+G50,1+J50,1+M50,1+P50,1+S50)^(1/5))-1 -> 0.14720078 | F50: 4370370642 | G50: =F50/F26 -> 0.13746762 | I50: 4142351836 | J50: =I50/I26 -> 0.14221202 | L50: 3469342252 | M50: =L50/L26 -> 0.147877 | O50: 3381998398 | P50: =O50/O26 -> 0.15570895 | R50: 2830371390 | S50: =R50/R26 -> 0.15283608 | U50: 2437597169 | V50: =U50/U26 -> 0.15279867
A55: Customers | F55: 28951000000 | I55: 26071000000 | K55: 0 | L55: 21647000000 | O55: 19462000000 | R55: 16652000000 | U55: 14250000000
A56: Fixed Deposits | F56: 4350000000 | I56: 4794000000 | K56: 0 | L56: 4105000000 | O56: 3933000000 | R56: 3342000000 | U56: 3097000000
A57: Saving Deposits | F57: 12804000000 | I57: 10364000000 | K57: 0 | L57: 8208000000 | O57: 7479000000 | R57: 6669000000 | U57: 5649000000
A58: Current Accounts | F58: 10486000000 | I58: 10516000000 | K58: 0 | L58: 8907000000 | O58: =(O59+O60) -> 7829000000 | R58: =(R59+R60) -> 6465000000 | U58: =(U59+U60) -> 5370000000
A59: Current Accounts Remunerative | F59: 0 | I59: 1225000000 | K59: 0 | L59: 1157000000 | O59: 1010000000 | R59: 748000000 | U59: 598000000
A60: Current Accounts Non-remunerative | F60: 0 | I60: 9291000000 | K60: 0 | L60: 7751000000 | O60: 6819000000 | R60: 5717000000 | U60: 4772000000
A61: Others | F61: 1310000000 | I61: 398000000 | K61: 0 | L61: 427000000 | O61: 220000000 | R61: 176000000 | U61: 135000000
A62: Financial Institutions | F62: 1336000000 | I62: 1801000000 | K62: 0 | L62: 845000000 | O62: 1509000000 | R62: 1221000000 | U62: 1035000000
A63: Remunerative Deposits | F63: 925000000 | I63: 1221000000 | K63: 0 | L63: 724000000 | O63: 906000000 | R63: 729000000 | U63: 557000000
A64: Non-remunerative Deposits | F64: 411000000 | I64: 579000000 | K64: 0 | L64: 121000000 | O64: 603000000 | R64: 493000000 | U64: 478000000
A65: DEPOSITS (Domestic) | F65: 30287000000 | I65: 27872000000 | K65: 0 | L65: 22492000000 | O65: 20971000000 | R65: 17873000000 | U65: 15286000000
A67: Customers | F67: 30403000000 | I67: 27289000000 | L67: 22583000000 | O67: 20179000000 | R67: 17271000000 | U67: 14891000000
A68: Fixed Deposits | F68: 4876000000 | I68: 5310000000 | L68: 4503000000 | O68: 4227000000 | R68: 3631000000 | U68: 3410000000
A69: Saving Deposits | F69: 12971000000 | I69: 10469000000 | L69: 8298000000 | O69: 7562000000 | R69: 6734000000 | U69: 5709000000
A70: Current Accounts | F70: 11227000000 | I70: 11096000000 | L70: 9336000000 | O70: =(O72+O71) -> 8157000000 | R70: =(R72+R71) -> 6716000000 | U70: =(U72+U71) -> 5626000000
A71: Current Accounts Remunerative | F71: 0 | I71: 1255000000 | L71: 1174000000 | O71: 1019000000 | R71: 755000000 | U71: 604000000
A72: Current Accounts Non-remunerative | F72: 0 | I72: 9841000000 | L72: 8162000000 | O72: 7138000000 | R72: 5961000000 | U72: 5022000000
A73: Others | F73: 1329000000 | I73: 415000000 | L73: 447000000 | O73: 233000000 | R73: 189000000 | U73: 146000000
A74: Financial Institutions | F74: 1389000000 | I74: 1839000000 | L74: 878000000 | O74: 1540000000 | R74: 1248000000 | U74: 1062000000
A75: Remunerative Deposits | F75: 970000000 | I75: 1255000000 | L75: 748000000 | O75: 927000000 | R75: 750000000 | U75: 577000000
A76: Non-remunerative Deposits | F76: 420000000 | I76: 584000000 | L76: 130000000 | O76: 613000000 | R76: 498000000 | U76: 485000000
A77: DEPOSITS (Total) | F77: 31792000000 | I77: 29128000000 | L77: 23461000000 | O77: 21720000000 | R77: 18519000000 | U77: 15953000000
A81: Saving & Fixed Deposits | C81: =C46+C45 -> 3.9864026e+09 | F81: =F46+F45 -> 3497990816 | I81: =I46+I45 -> 3121398538 | L81: =L46+L45 -> 2711866326 | O81: =O46+O45 -> 2379565300 | R81: =R46+R45 -> 2070459848 | U81: =U46+U45 -> 1878085533
A82: Current & Financial Institution Deposit | C82: =C47+C49 -> 9.9930795e+08 | F82: =F47 -> 796481678 | I82: =I47 -> 826353573 | L82: =L47 -> 628300746 | O82: =O47 -> 651769799 | R82: =R47 -> 456994397 | U82: =U47 -> 417608521
A83: Deposit Expense | C83: =C81*C84 -> 2.5911617e+08 | F83: =F89 -> 460196912 | I83: =I89 -> 353949375 | L83: =L89 -> 196757107 | O83: =O89 -> 98637738 | R83: =R89 -> 108385506 | U83: =U89 -> 114247880
A84: Interest Expense % | C84: 0.065 | F84: =F83/F81 -> 0.13156035 | I84: =I83/I81 -> 0.11339448 | L84: =L83/L81 -> 0.072554132 | O84: =O83/O81 -> 0.041451999 | R84: =R83/R81 -> 0.052348519 | U84: =U83/U81 -> 0.060832096
A85: Saving Rate | C85: 10 | F85: ='Saving Account Rate'!D11 -> 0.17032787 | I85: ='Saving Account Rate'!D20 -> 0.19669863 | L85: ='Saving Account Rate'!D29 -> 0.12908904 | O85: ='Saving Account Rate'!D36 -> 0.062130137 | R85: ='Saving Account Rate'!D45 -> 0.071161202 | U85: ='Saving Account Rate'!D54 -> 0.10800685
A89: Deposits | C89: =C83 -> 2.5911617e+08 | F89: 460196912 | I89: 353949375 | L89: 196757107 | O89: 98637738 | R89: 108385506 | U89: 114247880
A90: Securities sold under repurchase agreement borrowings | C90: =AVERAGE(F90,I90,L90,O90,R90,U90) -> 39604242 | F90: 58439060 | I90: 72977249 | L90: 50773232 | O90: 16759954 | R90: 15423539 | U90: 23252416
A91: Borrowings | C91: =C101*C102 -> 21954078 | F91: 30300563 | I91: 29163689 | L91: 11550696 | O91: 5674142 | R91: 7131338 | U91: 9124238
A92: Subordinated debt | C92: =C104*C105 -> 3576900.4 | F92: 4096181 | I92: 4281784 | L92: 1891880 | O92: 1239075 | R92: 2603244 | U92: 2038901
A93: Cost of foreign currency swaps against foreign currency deposits / borrowings | C93: =AVERAGE(F93,I93,L93,O93,R93,U93) -> 6834930.2 | F93: 10985531 | I93: 6494349 | L93: 6420260 | O93: 5271210 | R93: 5668401 | U93: 6169830
A94: Lease liability against right-of-use assets | C94: =C98*C99 -> 3985416 | F94: 3551598 | I94: 3345591 | L94: 3145165 | O94: 3252794 | R94: 1920912 | U94: 1957331
A95: Interest Expense | C95: =SUM(C89:C94) -> 3.3507174e+08 | F95: ='P&L'!F4 -> 567569845 | I95: ='P&L'!H4 -> 470212037 | L95: ='P&L'!J4 -> 270538340 | O95: ='P&L'!L4 -> 130834913 | R95: ='P&L'!N4 -> 141132940 | U95: ='P&L'!P4 -> 156790596
A98: Opening Book Value (Right-of-use assets) | C98: ='P&L'!D147 -> 27408020 | F98: ='P&L'!F147 -> 24654745 | I98: ='P&L'!H147 -> 22818230 | L98: ='P&L'!J147 -> 19821558 | O98: ='P&L'!L147 -> 16855856 | R98: ='P&L'!N147 -> 15975664 | U98: ='P&L'!P147 -> 17810109
A99: Lease liability against right-of-use assets/Opening Book Value (Right-of-use assets) | C99: =AVERAGE(F99,I99,L99,O99,R99,U99) -> 0.14541058 | F99: =F94/F98 -> 0.14405333 | I99: =I94/I98 -> 0.14661922 | L99: =L94/L98 -> 0.15867395 | O99: =O94/O98 -> 0.19297709 | R99: =R94/R98 -> 0.12023988 | U99: =U94/U98 -> 0.1099
A101: Borrowings | C101: =SOFP!D18 -> 8.7659455e+08 | F101: =SOFP!F18 -> 826883400 | I101: =SOFP!H18 -> 665042679 | L101: =SOFP!J18 -> 583771399 | O101: =SOFP!L18 -> 436258005 | R101: =SOFP!N18 -> 544107826 | U101: =SOFP!P18 -> 382206306
A102: Borrowings Expense/Borrowing | C102: =AVERAGE(F102,I102,L102,O102,R102,U102) -> 0.025044735 | F102: =F91/F101 -> 0.0366443 | I102: =I91/I101 -> 0.043852357 | L102: =L91/L101 -> 0.019786334 | O102: =O91/O101 -> 0.013006391 | R102: =R91/R101 -> 0.013106479 | U102: =U91/U101 -> 0.023872547
A104: Subordinated debt | C104: =SOFP!D21 -> 21012076 | F104: =SOFP!F21 -> 20374000 | I104: =SOFP!H21 -> 19699000 | L104: =SOFP!J21 -> 18874000 | O104: =SOFP!L21 -> 12374000 | R104: =SOFP!N21 -> 22356000 | U104: =SOFP!P21 -> 22360000
A105: Interest Paid % | C105: =AVERAGE(F105,I105,L105,O105,R105,U105) -> 0.1702307 | F105: =F92/F104 -> 0.20104943 | I105: =I92/I104 -> 0.21736048 | L105: =L94/L104 -> 0.16664009 | O105: =O94/O104 -> 0.26287328 | R105: =R94/R104 -> 0.085923779 | U105: =U94/U104 -> 0.087537165
A107: Weighted Policy Rate | C107: 0.115 | F107: ='Policy Rate'!D103 -> 0.18032787 | I107: ='Policy Rate'!D112 -> 0.21386301 | L107: ='Policy Rate'!D121 -> 0.14582877 | O107: ='Policy Rate'!D129 -> 0.077787671 | R107: ='Policy Rate'!D141 -> 0.084439891 | U107: ='Policy Rate'!D150 -> 0.1245411

Sheet Saving Account Rate
A1: HABIB BANK LIMITED
A2: Saving Account Rate
A4: Date | B4: Rate | C4: Days in Effect | D4: Weighted Rate
A5: 45657 | B5: 0.135 | C5: =A5-A6+1 -> 31 | D5: =(B5*C5) -> 4.185
A6: 45627 | B6: 0.135 | C6: =A6-A7 -> 61 | D6: =(B6*C6) -> 8.235
A7: 45566 | B7: 0.16 | C7: =A7-A8 -> 61 | D7: =(B7*C7) -> 9.76
A8: 45505 | B8: 0.18 | C8: =A8-A9 -> 31 | D8: =(B8*C8) -> 5.58
A9: 45474 | B9: 0.19 | C9: =A9-A10 -> 182 | D9: =(B9*C9) -> 34.58
A10: 45292 | B10: 0.205
C11: =SUM(C5:C10) -> 366 | D11: =SUM(D5:D10)/C11 -> 0.17032787
A13: Date | B13: Rate | C13: Days in Effect | D13: Weighted Rate
A14: 45291 | B14: 0.205 | C14: =A14-A15+1 -> 184 | D14: =(B14*C14) -> 37.72
A15: 45108 | B15: 0.205 | C15: =A15-A16 -> 61 | D15: =(B15*C15) -> 12.505
A16: 45047 | B16: 0.195 | C16: =A16-A17 -> 30 | D16: =(B16*C16) -> 5.85
A17: 45017 | B17: 0.185 | C17: =A17-A18 -> 59 | D17: =(B17*C17) -> 10.915
A18: 44958 | B18: 0.155 | C18: =A18-A19 -> 31 | D18: =(B18*C18) -> 4.805
A19: 44927 | B19: 0.145
C20: =SUM(C14:C19) -> 365 | D20: =SUM(D14:D19)/C20 -> 0.19669863
A22: Date | B22: Rate | C22: Days in Effect | D22: Weighted Rate
A23: 44926 | B23: 0.145 | C23: =A23-A24+1 -> 31 | D23: =(B23*C23) -> 4.495
A24: 44896 | B24: 0.145 | C24: =A24-A25 -> 122 | D24: =(B24*C24) -> 17.69
A25: 44774 | B25: 0.135 | C25: =A25-A26 -> 61 | D25: =(B25*C25) -> 8.235
A26: 44713 | B26: 0.1225 | C26: =A26-A27 -> 31 | D26: =(B26*C26) -> 3.7975
A27: 44682 | B27: 0.1075 | C27: =A27-A28 -> 120 | D27: =(B27*C27) -> 12.9
A28: 44562 | B28: 0.0825
C29: =SUM(C23:C28) -> 365 | D29: =SUM(D23:D28)/C29 -> 0.12908904
A31: Date | B31: Rate | C31: Days in Effect | D31: Weighted Rate
A32: 44561 | B32: 0.0825 | C32: =A32-A33+1 -> 31 | D32: =(B32*C32) -> 2.5575
A33: 44531 | B33: 0.0725 | C33: =A33-A34 -> 61 | D33: =(B33*C33) -> 4.4225
A34: 44470 | B34: 0.0575 | C34: =A34-A35 -> 273 | D34: =(B34*C34) -> 15.6975
A35: 44197 | B35: 0.055 | D35: =(B35*C35) -> 0
C36: =SUM(C32:C35) -> 365 | D36: =SUM(D32:D35)/C36 -> 0.062130137
A38: Date | B38: Rate | C38: Days in Effect | D38: Weighted Rate
A39: 44196 | B39: 0.055 | C39: =A39-A40+1 -> 184 | D39: =(B39*C39) -> 10.12
A40: 44013 | B40: 0.055 | C40: =A40-A41 -> 30 | D40: =(B40*C40) -> 1.65
A41: 43983 | B41: 0.065 | C41: =A41-A42 -> 31 | D41: =(B41*C41) -> 2.015
A42: 43952 | B42: 0.075 | C42: =A42-A43 -> 30 | D42: =(B42*C42) -> 2.25
A43: 43922 | B43: 0.11 | C43: =A43-A44 -> 91 | D43: =(B43*C43) -> 10.01
A44: 43831 | B44: 0.1175
C45: =SUM(C39:C44) -> 366 | D45: =SUM(D39:D44)/C45 -> 0.071161202
A47: Date | B47: Rate | C47: Days in Effect | D47: Weighted Rate
A48: 43830 | B48: 0.1175 | C48: =A48-A49+1 -> 153 | D48: =(B48*C48) -> 17.9775
A49: 43678 | B49: 0.1175 | C49: =A49-A50 -> 61 | D49: =(B49*C49) -> 7.1675
A50: 43617 | B50: 0.1075 | C50: =A50-A51 -> 31 | D50: =(B50*C50) -> 3.3325
A51: 43586 | B51: 0.0925 | C51: =A51-A52 -> 89 | D51: =(B51*C51) -> 8.2325
A52: 43497 | B52: 0.0875 | C52: =A52-A53 -> 31 | D52: =(B52*C52) -> 2.7125
A53: 43466 | B53: 0.0825
C54: =SUM(C48:C53) -> 365 | D54: =SUM(D48:D53)/C54 -> 0.10800685

Sheet Market Treasury Bills
A1: STATE BANK OF PAKISTAN | B1: STATE BANK OF PAKISTAN | C1: STATE BANK OF PAKISTAN | E1: STATE BANK OF PAKISTAN | F1: STATE BANK OF PAKISTAN | G1: STATE BANK OF PAKISTAN
A2: DOMESTIC MARKETS AND MONETARY MANAGEMENT DEPARTMENT
A3: STATE BANK OF PAKISTAN
A5: AUCTION SUMMARY
A6: MARKET TREASURY BILLS
F7: (Rs in Million)
A8: Auction No. | B8: Auction Date | C8: Realized Amount | D8: Weighted Average Yield (%)
D9: 1-Month | E9: 3-Month | F9: 6-Month | G9: 12-Month
A10: 1st | B10: 35970 | C10: 23623.24 | E10: No Bid Received | F10: 0.157033 | G10: No Bid Received
A11: 2nd | B11: 35989 | C11: 7708.23 | E11: 0.146157 | F11: 0.154142 | G11: 0.16
A12: 3rd | B12: 35998 | C12: 2305.36 | E12: Bids Rejected | F12: 0.157402 | G12: Bids Rejected
A13: 4th | B13: 36011 | C13: 21261.33 | E13: 0.138174 | F13: 0.152905 | G13: 0.159
A14: 5th | B14: 36024 | C14: 19628.07 | E14: 0.137083 | F14: 0.149434 | G14: 0.157803
A15: 6th | B15: 36041 | C15: 20526.84 | E15: Bids Rejected | F15: 0.138548 | G15: 0.153924
A16: 7th | B16: 36066 | C16: 9255.2 | E16: Bids Rejected | F16: 0.135467 | G16: 0.151701
A17: 8th | B17: 36080 | C17: 1910.04 | E17: Bids Rejected | F17: Bids Rejected | G17: 0.151808
A18: 9th | B18: 36090 | C18: Bids Rejected | E18: Bids Rejected | F18: Bids Rejected | G18: Bids Rejected
A19: 10th | B19: 36102 | C19: 23149.34 | E19: Bids Rejected | F19: Bids Rejected | G19: 0.141285
A20: 11th | B20: 36115 | C20: 6981.53 | E20: 0.095002 | F20: 0.119609 | G20: 0.129944
A21: 12th | B21: 36132 | C21: 5998.96 | E21: Bids Rejected | F21: 0.119342 | G21: 0.129944
A22: 13th | B22: 36151 | C22: 2207.54 | E22: Bids Rejected | F22: 0.118724 | G22: 0.129809
A23: 14th | B23: 36169 | C23: 5310.86 | E23: Bids Rejected | F23: 0.121011 | G23: 0.129755
A24: 15th | B24: 36180 | C24: 8364.98 | E24: 0.121124 | F24: 0.124582 | G24: 0.131684
A25: 16th | B25: 36192 | C25: 20217.27 | E25: 0.124334 | F25: 0.128696 | G25: 0.1354
A26: 17th | B26: 36204 | C26: 15086.1 | E26: 0.127141 | F26: 0.132991 | G26: 0.138117
A27: 18th | B27: 36222 | C27: 10978.54 | E27: 0.123706 | F27: 0.129581 | G27: Bids Rejected
A28: 19th | B28: 36244 | C28: 3860.06 | E28: 0.10733 | F28: 0.113501 | G28: 0.118043
A29: 20th | B29: 36271 | C29: 211.15 | E29: Bids Rejected | F29: 0.105987 | G29: 0.114951
A30: 21st | B30: 36292 | C30: Bids Rejected | E30: Bids Rejected | F30: Bids Rejected | G30: Bids Rejected
A31: 22nd | B31: 36306 | C31: 2449.45 | E31: 0.083704 | F31: Bids Rejected | G31: Bids Rejected
A32: 23rd | B32: 36320 | C32: 10210.51 | E32: 0.075266 | F32: Bids Rejected | G32: Bids Rejected
A33: 24th | B33: 36334 | C33: 12580.09 | E33: 0.066599 | F33: Bids Rejected | G33: 0.100979
A34: 25th | B34: 36348 | C34: 2063.78 | E34: Bids Rejected | F34: Bids Rejected | G34: 0.103307
A35: 26th | B35: 36362 | C35: 6403.1 | E35: 0.069627 | F35: Bids Rejected | G35: 0.102901
A36: 27th | B36: 36383 | C36: 15569.91 | E36: 0.069443 | F36: Bids Rejected | G36: 0.101841
A37: 28th | B37: 36397 | C37: 9919.75 | E37: 0.078593 | F37: 0.094286 | G37: 0.101996
A38: 29th | B38: 36411 | C38: 17856.24 | E38: 0.087985 | F38: 0.100537 | G38: 0.103234
A39: 30th | B39: 36425 | C39: 5428.64 | E39: 0.089583 | F39: 0.102488 | G39: 0.107313
A40: 31st | B40: 36439 | C40: 2187.07 | E40: Bids Rejected | F40: 0.103554 | G40: Bids Rejected
A41: 32nd | B41: 36453 | C41: Bids Rejected | E41: Bids Rejected | F41: Bids Rejected | G41: Bids Rejected
A42: 33rd | B42: 36467 | C42: 26708.09 | E42: 0.087774 | F42: 0.099434 | G42: 0.106126
A43: 34th | B43: 36481 | C43: 5884.4 | E43: 0.088226 | F43: 0.101345 | G43: 0.108707
A44: 35th | B44: 36495 | C44: 1742.63 | E44: 0.088678 | F44: 0.10156 | G44: 0.107721
A45: 36th | B45: 36509 | C45: 1833.81 | E45: No Bid Received | F45: 0.100972 | G45: 0.103281
A46: 37th | B46: 36523 | C46: 201.77 | E46: No Bid Received | F46: Bids Rejected | G46: 0.103061
A47: 38th | B47: 36537 | C47: 95.94 | E47: Bids Rejected | F47: 0.084869 | G47: Bids Rejected
A48: 39th | B48: 36551 | C48: 2719.69 | E48: 0.080099 | F48: 0.084283 | G48: 0.089451
A49: 40th | B49: 36565 | C49: 8746.78 | E49: 0.075414 | F49: 0.0796 | G49: 0.084359
A50: 41st | B50: 36579 | C50: 2642.95 | E50: 0.072899 | F50: 0.074462 | G50: 0.078965
A51: 42nd | B51: 36593 | C51: 71.35 | E51: Bids Rejected | F51: Bids Rejected | G51: 0.078924
A52: 43rd | B52: 36607 | C52: 870.03 | E52: 0.072868 | F52: 0.07444 | G52: 0.078949
A53: 44th | B53: 36621 | C53: 8318.59 | E53: 0.071103 | F53: 0.071961 | G53: 0.076851
A54: 45th | B54: 36635 | C54: 4674.8 | E54: 0.069757 | F54: 0.071262 | G54: 0.075916
A55: 46th | B55: 36649 | C55: 20762.14 | E55: 0.069374 | F55: 0.070925 | G55: 0.075836
A56: 47th | B56: 36663 | C56: 2263.23 | E56: 0.069757 | F56: 0.072024 | G56: 0.076172
A57: 48th | B57: 36677 | C57: 1198.66 | E57: 0.069533 | F57: 0.072178 | G57: 0.076086
A58: 49th | B58: 36691 | C58: 984.3 | E58: 0.069308 | F58: Bids Rejected | G58: Bids Rejected
A59: 50th | B59: 36705 | C59: Bids Rejected | E59: Bids Rejected | F59: Bids Rejected | G59: Bids Rejected
A60: 51st | B60: 36719 | C60: 8750.29 | E60: 0.068486 | F60: 0.071376 | G60: Bids Rejected
A61: 52nd | B61: 36733 | C61: 7780.42 | E61: 0.070302 | F61: 0.072339 | G61: 0.077771
A62: 53rd | B62: 36747 | C62: 698.65 | E62: Bids Rejected | F62: 0.073816 | G62: 0.079595
A63: 54th | B63: 36761 | C63: 1520.62 | E63: Bids Rejected | F63: 0.073816 | G63: 0.080122
A64: 55th | B64: 36775 | C64: 255.08 | E64: Bids Rejected | F64: 0.074462 | G64: 0.081039
A65: 56th | B65: 36789 | C65: 11834.92 | E65: 0.079522 | F65: 0.081397 | G65: 0.089253
A66: 57th | B66: 36803 | C66: 11036.69 | E66: 0.102269 | F66: 0.104684 | G66: 0.109098
A67: 58th | B67: 36817 | C67: 189.6 | E67: Bids Rejected | F67: 0.110006 | G67: Bids Rejected
A68: 59th | B68: 36831 | C68: 12790.27 | E68: Bids Rejected | F68: 0.109923 | G68: 0.114789
A69: 60th | B69: 36845 | C69: 426.69 | E69: Bids Rejected | F69: 0.10956 | G69: Bids Rejected
A70: 61st | B70: 36859 | C70: 993.03 | E70: No Bid Received | F70: 0.109225 | G70: 0.114893
A71: 62nd | B71: 36873 | C71: 585.28 | E71: No Bid Received | F71: 0.10956 | G71: 0.114893
A72: 63rd | B72: 36901 | C72: Bids Rejected | E72: Bids Rejected | F72: Bids Rejected | G72: No Bid Received
A73: 64th | B73: 36915 | C73: 5217.19 | E73: 0.105026 | F73: 0.10956 | G73: Bids Rejected
A74: 65th | B74: 36929 | C74: 2861.88 | E74: 0.105026 | F74: 0.10956 | G74: 0.114425
A75: 66th | B75: 36943 | C75: 2926.2 | E75: 0.109589 | F75: Bids Rejected | G75: No Bid Received
A76: 67th | B76: 36957 | C76: 7510.58 | E76: 0.109589 | F76: Bids Rejected | G76: Bids Rejected
A77: 68th | B77: 36971 | C77: 13203.74 | E77: 0.111592 | F77: 0.115513 | G77: 0.119522
A78: 69th | B78: 36984 | C78: 18511.96 | E78: 0.110833 | F78: 0.115379 | G78: 0.11959
A79: 70th | B79: 36999 | C79: 4392.58 | E79: Bids Rejected | F79: 0.115375 | G79: 0.119849
A80: 71st | B80: 37013 | C80: 19718.56 | E80: 0.111258 | F80: 0.115095 | G80: 0.119717
A81: 72nd | B81: 37027 | C81: 4252.95 | E81: No Bid Received | F81: 0.115694 | G81: 0.119773
A82: 73rd | B82: 37041 | C82: 20613.56 | E82: 0.111669 | F82: 0.115994 | G82: 0.119905
A83: 74th | B83: 37055 | C83: 10915.78 | E83: 0.117856 | F83: 0.121749 | G83: 0.125266
A84: 75th | B84: 37069 | C84: 15491.42 | E84: 0.122214 | F84: 0.128756 | G84: 0.129353
A85: 76th | B85: 37083 | C85: 6132.91 | E85: 0.121495 | F85: 0.125551 | G85: Bids Rejected
A86: 77th | B86: 37097 | C86: 11315.59 | E86: 0.113329 | F86: 0.11579 | G86: 0.119843
A87: 78th | B87: 37111 | C87: 8415.58 | E87: 0.111746 | F87: 0.11364 | G87: 0.11734
A88: 79th | B88: 37125 | C88: 16532.72 | E88: 0.10038 | F88: 0.104667 | G88: 0.108221
A89: 80th | B89: 37139 | C89: 11430.17 | E89: 0.102247 | F89: 0.10486 | G89: 0.108392
A90: 81st | B90: 37153 | C90: 1178.84 | E90: 0.101838 | F90: 0.104969 | G90: 0.108699
A91: 82nd | B91: 37167 | C91: 7737.85 | E91: 0.100018 | F91: 0.103982 | G91: 0.107592
A92: 83rd | B92: 37181 | C92: 3231.11 | E92: Bids Rejected | F92: 0.102889 | G92: 0.107176
A93: 84th | B93: 37195 | C93: 9208.18 | E93: 0.081752 | F93: 0.085039 | G93: 0.089971
A94: 85th | B94: 37209 | C94: 7508.83 | E94: 0.079648 | F94: 0.083047 | G94: 0.088986
A95: 86th | B95: 37223 | C95: 9806.76 | E95: 0.079648 | F95: 0.082578 | G95: 0.087405
A96: 87th | B96: 37237 | C96: 2622.99 | E96: Bids Rejected | F96: 0.081398 | G96: 0.085421
A97: 88th | B97: 37251 | C97: 9307.36 | E97: 0.076496 | F97: 0.079284 | G97: 0.083995
A98: 89th | B98: 37265 | C98: 8089.56 | E98: Bids Rejected | F98: 0.077659 | G98: 0.082044
A99: 90th | B99: 37279 | C99: 11744.5 | E99: 0.061331 | F99: 0.063472 | G99: 0.068176
A100: 91st | B100: 37293 | C100: 24777.97 | E100: 0.05362 | F100: 0.05645 | G100: 0.063827
A101: 92nd | B101: 37307 | C101: 13093.08 | E101: Bids Rejected | F101: 0.063862 | G101: 0.069029
...

Sheet Pakistan Investment Bonds
A1: PAKISTAN INVESTMENT BONDS
A2: AUCTION PROFILE
A3: (FACE VALUE)
B4: Auction Settlement Date | C4: Tenor | D4: Coupon Rate | E4: Amount Accepted | F4: Weighted Average Yield%
A5: (Amount in millions)
A6: (17th Re-Opening) | C6: 10 - Year | D6: 0.0875 | E6: 733 | F6: 0.084738
C7: 20 - Year | D7: 0.1075 | E7: - | F7: No Bid Received
A8: 6865
A9: 47th - Regular (18th Re-Opening) | B9: June 13, 2018 | C9: 3 - Year | D9: 0.07 | E9: 2674.9 | F9: 0.074677
C10: 5 - Year | D10: 0.0775 | E10: 540.4 | F10: 0.084795
C11: 10 - Year | D11: 0.0875 | E11: 596.8 | F11: 0.086999
C12: 20 - Year | D12: 0.1075 | E12: - | F12: No Bid Received
A13: 3812.1
A14: 48th - Regular (Fresh) | B14: July 12, 2018 | C14: 3 - Year | D14: 0.0725 | E14: Bids Rejected
C15: 5 - Year | D15: 0.08 | E15: Bids Rejected
C16: 10 - Year | D16: 0.0875 | E16: No Bid Received
C17: 20 - Year | D17: 0.1075
A18: -
A19: 48th - Regular (1st Re-Opening) | B19: August 9, 2018 | C19: 3 - Year | D19: 0.0725 | E19: Bids Rejected
C20: 5 - Year | D20: 0.08 | E20: 15918 | F20: 0.0925
C21: 10 - Year | D21: 0.0875 | E21: Bids Rejected
C22: 20 - Year | D22: 0.1075 | E22: No Bid Received
A23: 15918
A24: 48th - Regular (2nd Re-Opening) | B24: September 6, 2018 | C24: 3 - Year | D24: 0.0725 | E24: Bids Rejected
C25: 5 - Year | D25: 0.08 | E25: 4668 | F25: 0.0925
C26: 10 - Year | D26: 0.0875 | E26: Bids Rejected
C27: 20 - Year | D27: 0.1075 | E27: No Bid Received
A28: 4668
A29: 48th - Regular (3rd Re-Opening) | B29: October 18, 2018 | C29: 3 - Year | D29: 0.0725 | E29: Bids Rejected
C30: 5 - Year | D30: 0.08 | E30: Bids Rejected
C31: 10 - Year | D31: 0.0875 | E31: Bids Rejected
C32: 20 - Year | D32: 0.1075 | E32: No Bid Received
A33: -
A34: 48th - Regular (4th Re-Opening) | B34: November 29, 2018 | C34: 3 - Year | D34: 0.0725 | E34: Bids Rejected
C35: 5 - Year | D35: 0.08 | E35: Bids Rejected
C36: 10 - Year | D36: 0.0875 | E36: No Bid Received
C37: 20 - Year | D37: 0.1075 | E37: No Bid Received
A38: -
A39: 48th - Regular (5th Re-Opening) | B39: December 27, 2018 | C39: 3 - Year | D39: 0.0725 | E39: 8665 | F39: 0.121915
C40: 5 - Year | D40: 0.08 | E40: 2350.1 | F40: 0.126997
C41: 10 - Year | D41: 0.0875 | E41: 11483.6 | F41: 0.131245
C42: 20 - Year | D42: 0.1075 | E42: No Bid Received
A43: 22498.7
A44: 48th - Regular (6th Re-Opening) | B44: January 24, 2019 | C44: 3 - Year | D44: 0.0725 | E44: 34081.9 | F44: 0.122209
C45: 5 - Year | D45: 0.08 | E45: 26712.5 | F45: 0.126978
C46: 10 - Year | D46: 0.0875 | E46: Bids Rejected
C47: 20 - Year | D47: 0.1075 | E47: Bids Rejected
A48: 60794.4
A49: 48th - Regular (7th Re-Opening) | B49: February 21, 2019 | C49: 3 - Year | D49: 0.0725 | E49: 115155.6 | F49: 0.120002
C50: 5 - Year | D50: 0.08 | E50: 54193.7 | F50: 0.124461
C51: 10 - Year | D51: 0.0875 | E51: 63229.8 | F51: 0.128267
C52: 20 - Year | D52: 0.1075 | E52: No Bid Received
A53: 232579.1
A54: 48th - Regular (8th Re-Opening) | B54: March 21, 2019 | C54: 3 - Year | D54: 0.0725 | E54: 22419 | F54: 0.121981
C55: 5 - Year | D55: 0.08 | E55: 24608.4 | F55: 0.125392
C56: 10 - Year | D56: 0.0875 | E56: 57523.5 | F56: 0.129681
C57: 20 - Year | D57: 0.1075 | E57: No Bid Received
A58: 104550.9
A59: 48th - Regular (9th Re-Opening) | B59: April 18, 2019 | C59: 3 - Year | D59: 0.0725 | E59: 162664.1 | F59: 0.121419
C60: 5 - Year | D60: 0.08 | E60: -
C61: 10 - Year | D61: 0.0875 | E61: -
C62: 20 - Year | D62: 0.1075 | E62: No Bid Received
A63: 162664.1
A64: 48th - Regular (10th Re-Opening) | B64: May 30, 2019 | C64: 3 - Year | D64: 0.0725 | E64: 67214.8 | F64: 0.136117
C65: 5 - Year | D65: 0.08 | E65: 36183.1 | F65: 0.137145
C66: 10 - Year | D66: 0.0875 | E66: 29753.8 | F66: 0.136
C67: 20 - Year | D67: 0.1075 | E67: No Bid Received
A68: 133151.7
A69: 48th - Regular (11th Re-Opening) | B69: June 27, 2019 | C69: 3 - Year | D69: 0.0725 | E69: 8658.1 | F69: 0.13677
C70: 5 - Year | D70: 0.08 | E70: 35046.3 | F70: 0.137687
C71: 10 - Year | D71: 0.0875 | E71: 91204.2 | F71: 0.13682
C72: 20 - Year | D72: 0.1075 | E72: No Bid Received
A73: 134908.6
A74: 48th - Regular (12th Re-Opening) | B74: July 25, 2019 | C74: 3 - Year | D74: 0.0725 | E74: 124364.9 | F74: 0.140206
C75: 5 - Year | D75: 0.08 | E75: 72091.8 | F75: 0.13774
C76: 10 - Year | D76: 0.0875 | E76: 28808.2 | F76: 0.134548
C77: 20 - Year | D77: 0.1075 | E77: No Bid Received
A78: 225264.9
A79: 48th - Regular (13th Re-Opening) | B79: August 22, 2019 | C79: 3 - Year | D79: 0.0725 | E79: 417927.6 | F79: 0.141519
C80: 5 - Year | D80: 0.08 | E80: 65221.4 | F80: 0.13486
C81: 10 - Year | D81: 0.0875 | E81: 30543.9 | F81: 0.131017
C82: 20 - Year | D82: 0.1075 | E82: Bids Rejected
A83: 513692.9
A84: 49th - Regular (Fresh Issuance) | B84: September 19, 2019 | C84: 3 - Year | D84: 0.09 | E84: 89648.8 | F84: 0.128683
C85: 5 - Year | D85: 0.095 | E85: 84437.7 | F85: 0.12376
C86: 10 - Year | D86: 0.1 | E86: 50416.3 | F86: 0.121482
C87: 20 - Year | D87: 0.11 | E87: Bids Rejected
A89: 49th - Regular (1st Re-Opening) | B89: October 31, 2019 | C89: 3 - Year | D89: 0.09 | E89: 52513.1 | F89: 0.11713
C90: 5 - Year | D90: 0.095 | E90: 37705 | F90: 0.115151
C91: 10 - Year | D91: 0.1 | E91: 35802.2 | F91: 0.112636
C92: 20 - Year | D92: 0.11 | E92: Bids Rejected | H92: 2019 | I92: Average Weighted Yields | J92: Coupon Rate
H93: 2 - Year | I93: {=IFERROR( AVERAGE( _xlfn._xlws.FILTER( $F$44:$F$102, ($C$44:$C$102 = $H93) * ($F$44:$F$102 > 0) ) ), "No matches" )} -> No matches | J93: {=IFERROR( AVERAGE( _xlfn._xlws.FILTER( $D$44:$D$102, ($C$44:$C$102 = $H93) * ($D$44:$D$102 > 0) ) ), "Zero" )} -> Zero
A94: 49th - Regular (2nd Re-Opening) | B94: November 14, 2019 | C94: 3 - Year | D94: 0.09 | E94: 59166.9 | F94: 0.11764 | H94: 3 - Year | I94: {=IFERROR( AVERAGE( _xlfn._xlws.FILTER( $F$104:$F$172, ($C$104:$C$172 = $H94) * ($F$104:$F$172 > 0) ) ), "No matches" )} -> 0.089533833 | J94: {=IFERROR( AVERAGE( _xlfn._xlws.FILTER( $D$44:$D$102, ($C$44:$C$102 = $H94) * ($D$44:$D$102 > 0) ) ), "Zero" )} -> 0.078333333
C95: 5 - Year | D95: 0.095 | E95: 52215 | F95: 0.113903 | H95: 5 - Year | I95: {=IFERROR( AVERAGE( _xlfn._xlws.FILTER( $F$104:$F$172, ($C$104:$C$172 = $H95) * ($F$104:$F$172 > 0) ) ), "No matches" )} -> 0.092676333 | J95: {=IFERROR( AVERAGE( _xlfn._xlws.FILTER( $D$44:$D$102, ($C$44:$C$102 = $H95) * ($D$44:$D$102 > 0) ) ), "Zero" )} -> 0.085
C96: 10 - Year | D96: 0.1 | E96: 22554.5 | F96: 0.1128 | H96: 10 - Year | I96: {=IFERROR( AVERAGE( _xlfn._xlws.FILTER( $F$104:$F$172, ($C$104:$C$172 = $H96) * ($F$104:$F$172 > 0) ) ), "No matches" )} -> 0.095229 | J96: {=IFERROR( AVERAGE( _xlfn._xlws.FILTER( $D$44:$D$102, ($C$44:$C$102 = $H96) * ($D$44:$D$102 > 0) ) ), "Zero" )} -> 0.091666667
C97: 20 - Year | D97: 0.11 | E97: Bid Rejected | H97: 15 - Year | I97: {=IFERROR( AVERAGE( _xlfn._xlws.FILTER( $F$104:$F$172, ($C$104:$C$172 = $H97) * ($F$104:$F$172 > 0) ) ), "No matches" )} -> 0.0994625 | J97: {=IFERROR( AVERAGE( _xlfn._xlws.FILTER( $D$44:$D$102, ($C$44:$C$102 = $H97) * ($D$44:$D$102 > 0) ) ), "No matches" )} -> No matches
H98: 20 - Year | I98: {=IFERROR( AVERAGE( _xlfn._xlws.FILTER( $F$104:$F$172, ($C$104:$C$172 = $H98) * ($F$104:$F$172 > 0) ) ), "No matches" )} -> 0.10662167 | J98: {=IFERROR( AVERAGE( _xlfn._xlws.FILTER( $D$44:$D$102, ($C$44:$C$102 = $H98) * ($D$44:$D$102 > 0) ) ), "Zero" )} -> 0.10833333
A99: 49th - Regular (3rd Re-Opening) | B99: December 12, 2019 | C99: 3 - Year | D99: 0.09 | E99: 58637.2 | F99: 0.116954 | H99: 30 - Year | I99: {=IFERROR( AVERAGE( _xlfn._xlws.FILTER( $F$104:$F$172, ($C$104:$C$172 = $H99) * ($F$104:$F$172 > 0) ) ), "No matches" )} -> No matches | J99: {=IFERROR( AVERAGE( _xlfn._xlws.FILTER( $D$44:$D$102, ($C$44:$C$102 = $H99) * ($D$44:$D$102 > 0) ) ), "No matches" )} -> No matches
C100: 5 - Year | D100: 0.095 | E100: 56046 | F100: 0.111511 | I100: =AVERAGE(I93:I99) -> 0.096704667 | J100: =AVERAGE(J93:J99) -> 0.090833333
C101: 10 - Year | D101: 0.1 | E101: 36760 | F101: 0.109453
...

Sheet Ijara Sukuk VRR
A1: Auction Number | B1: Tenor | C1: Auction Date | D1: Settlement Date | E1: Issue Date | F1: Maturity Date | G1: Cut-off Margin3 | H1: Rental Rate
H2: 1st | I2: 2nd | J2: 3rd | K2: 4th | L2: 5th | M2: 6th | N2: 7th | O2: 8th | P2: 9th | Q2: 10th
A3: GIS VRR-17 | B3: 5-Year | C3: 43937 | D3: 43943 | E3: 43943 | F3: 45769
A4: GIS VRR-18 | B4: 5-Year | C4: 43944 | D4: 43951 | E4: 43951 | F4: 45777 | G4: -125 | H4: 0.066329 | I4: 0.0595 | J4: 0.063963 | K4: 0.0753 | L4: 0.134613 | M4: 0.144403 | N4: 0.206945 | O4: 0.211376 | P4: 0.200668 | Q4: 0.129045
A5: GIS VRR-19 | B5: 5-Year | C5: 43972 | D5: 43980 | E5: 43980 | F5: 45806 | G5: -10 | H5: 0.076465 | I5: 0.070959 | J5: 0.074686 | K5: 0.1008 | L5: 0.146 | M5: 0.156289 | N5: 0.218157 | O5: 0.213583 | P5: 0.211845 | Q5: 0.127192
A6: GIS VRR-20 | B6: 5-Year | C6: 44000 | D6: 44006 | E6: 44006 | F6: 45832 | G6: -10 | H6: 0.073786 | I6: 0.070693 | J6: 0.074719 | K6: 0.112789 | L6: 0.148501 | M6: 0.167508 | N6: 0.218225 | O6: 0.212554 | P6: 0.198283 | Q6: 0.118313
A7: GIS VRR-21 | B7: 5-Year | C7: 44035 | D7: 44041 | E7: 44041 | F7: 45867 | G7: -20 | H7: 0.062666 | I7: 0.072001 | J7: 0.073206 | K7: 0.104527 | L7: 0.154806 | M7: 0.1765 | N7: 0.226701 | O7: 0.201951 | P7: 0.189908 | Q7: 0.112048
A8: GIS VRR-22 | B8: 5-Year | C8: 44168 | D8: 44174 | E8: 44174 | F8: 46000 | G8: -10 | H8: 0.070849 | I8: 0.074787 | J8: 0.109587 | K8: 0.148544 | L8: 0.164229 | M8: 0.218429 | N8: 0.212263 | O8: 0.207605 | P8: 0.127192 | Q8: 0.110128 | T8: Rental rate | U8: Policy Rate
A9: GIS VRR-23 | B9: 5-Year | C9: 44469 | D9: 44475 | E9: 44475 | F9: 46301 | G9: -10 | H9: 0.078488 | I9: 0.12145 | J9: 0.158461 | K9: 0.218566 | L9: 0.2275 | M9: 0.212035 | N9: 0.14133 | O9: 0.11823 | S9: 2019 | T9: 0.124 | U9: ='Policy Rate'!D150 -> 0.1245411
A10: GIS VRR-24 | B10: 5-Year | C10: 44495 | D10: 44498 | E10: 44498 | F10: 46324 | G10: -10 | H10: 0.087 | I10: 0.146113 | J10: 0.155903 | K10: 0.218445 | L10: 0.222876 | M10: 0.212168 | N10: 0.140545 | O10: 0.118473 | S10: 2020 | T10: =AVERAGE(H4:H8) -> 0.070019 | U10: ='Policy Rate'!D141 -> 0.084439891
A11: GIS VRR-25 | B11: 5-Year | C11: 44672 | D11: 44678 | E11: 44678 | F11: 46504 | G11: 0 | H11: 0.135279 | I11: 0.156903 | J11: 0.219445 | K11: 0.223876 | L11: 0.213168 | M11: 0.141545 | N11: 0.119473 | S11: 2021 | T11: =AVERAGE(H9:H10) -> 0.082744 | U11: ='Policy Rate'!D129 -> 0.077787671
A12: GIS VRR-26 | B12: 5-Year | C12: 44854 | D12: 44860 | E12: 44860 | F12: 46686 | G12: 0 | H12: 0.156903 | I12: 0.219445 | J12: 0.223876 | K12: 0.213168 | L12: 0.141545 | M12: 0.119473 | S12: 2022 | T12: =AVERAGE(H11:H12) -> 0.146091 | U12: ='Policy Rate'!D121 -> 0.14582877
A13: GIS VRR-27 | B13: 3-Year | C13: 44929 | D13: 44931 | E13: 44931 | F13: 46027 | G13: -25 | H13: 0.165627 | I13: 0.216725 | J13: 0.211134 | K13: 0.196927 | L13: 0.116401 | M13: 0.106474 | S13: 2023 | T13: =AVERAGE(H13:H27) -> 0.2151344 | U13: ='Policy Rate'!D112 -> 0.21386301
A14: GIS VRR-28 | B14: 1-Year | C14: 44973 | D14: 44977 | E14: 44977 | F14: 45342 | G14: 0 | H14: 0.1784 | I14: 0.22725 | S14: 2024 | T14: 0.181 | U14: ='Policy Rate'!D103 -> 0.18032787
A15: GIS VRR-29 | B15: 1-Year | C15: 44991 | D15: 44993 | E15: 44993 | F15: 45359 | G15: 75 | H15: 0.203206 | I15: 0.255368
A16: GIS VRR-30 | B16: 1-Year | C16: 45029 | D16: 45033 | E16: 45033 | F16: 45399 | G16: 75 | H16: 0.226768 | I16: 0.236
A17: GIS VRR-31 | B17: 1-Year | C17: 45064 | D17: 45068 | E17: 45068 | F17: 45434 | G17: 75 | H17: 0.226657 | I17: 0.222083
A18: GIS VRR-32 | B18: 1-Year | C18: 45099 | D18: 45103 | E18: 45103 | F18: 45469 | G18: 65 | H18: 0.225725 | I18: 0.220054
A19: GIS VRR-34 | B19: 5-Year | C19: 45099 | D19: 45103 | E19: 45103 | F19: 46930 | G19: 95 | H19: 0.228725 | I19: 0.223054 | J19: 0.208783 | K19: 0.128813 | L19: 0.119021
A20: GIS VRR-35 | B20: 1-Year | C20: 45117 | D20: 45119 | E20: 45119 | F20: 45485 | G20: 84 | H20: 0.227625 | I20: 0.218001
A21: GIS VRR-36 | B21: 3-Year | C21: 45117 | D21: 45119 | E21: 45119 | F21: 46215 | G21: 85 | H21: 0.227725 | I21: 0.218101 | J21: 0.205339 | K21: 0.125758 | L21: 0.115963
A22: GIS VRR-37 | B22: 1-Year | C22: 45141 | D22: 45145 | E22: 45511 | F22: 45511 | G22: 84 | H22: 0.237101 | I22: 0.212351
A23: GIS VRR-38 | B23: 1-Year | C23: 45187 | D23: 45189 | E23: 45189 | F23: 45555 | G23: -200 | H23: 0.227868 | I23: 0.183949
A24: GIS VRR-39 | B24: 1-Year | C24: 45204 | D24: 45208 | E24: 45208 | F24: 45574 | G24: -36 | H24: 0.2249 | I24: 0.209435
A25: GIS VRR-40 | B25: 1-Year | C25: 45260 | D25: 45264 | E25: 45264 | F25: 45630 | G25: -100 | H25: 0.203263 | I25: 0.198605
A26: GIS VRR-41 | B26: 3-Year | C26: 45260 | D26: 45264 | E26: 45264 | F26: 46360 | G26: -21 | H26: 0.211163 | I26: 0.206505 | J26: 0.126092 | K26: 0.109028
A27: GIS VRR-42 | B27: 5-Year | C27: 45260 | D27: 45264 | E27: 45264 | F27: 47091 | G27: -10 | H27: 0.212263 | I27: 0.207605 | J27: 0.127192 | K27: 0.110128

Sheet Ijara Sukuk FRR
A1: Auction Number | B1: Tenor | C1: Auction Date | D1: Date of Settlement | E1: Issue Date | F1: Maturity Date | G1: Target Announced | H1: Amount Offered | I1: Range of Rental Rate/Price | J1: Competitive Accepted | K1: Non Competitive Accepted | L1: Total Acceptance | M1: Fixed Rental Rate | N1: Cut off Price | O1: Cut off Yield*
A2: GIS-FRR 04 | B2: 5-Year | C2: 44035 | D2: 44041 | E2: 44041 | F2: 45867 | G2: 25000 | H2: 26500 | I2: 7.89 to 8.90 | J2: 20900 | K2: 100 | L2: 21000 | M2: 0.0837
A3: GIS-FRR 04 (1st RO) | B3: 5-Year | C3: 44063 | D3: 44069 | E3: 44041 | F3: 45867 | G3: 20000 | H3: 22645 | I3: 101.4713 - 95.6000 | J3: 17733 | K3: 100 | L3: 17833 | M3: 0.0837 | N3: 99.672 | O3: 0.0845
A4: GIS-FRR 04 (2nd RO) | B4: 5-Year | C4: 44091 | D4: 44097 | E4: 44041 | F4: 45867 | G4: 15000 | H4: 6825 | I4: 100.0500 - 98.5055 | J4: 5650 | K4: 112.5 | L4: 5762.5 | M4: 0.0837 | N4: 99.8056 | O4: 0.08415
A5: GIS-FRR 04 (3rd RO) | B5: 5-Year | C5: 44119 | D5: 44125 | E5: 44041 | F5: 45867 | G5: 15000 | H5: 7100 | I5: 98.5214 - 97.0000 | J5: BIDS REJECTED | K5: - | L5: - | M5: 0.0837
A6: GIS-FRR 05 | B6: 5-Year | C6: 44168 | D6: 44174 | E6: 44174 | F6: 46000 | G6: 15000 | H6: 5800 | I6: 8.65 to 9.15 | J6: BIDS REJECTED | K6: - | L6: -
A7: GIS-FRR 06 | B7: 5-Year | C7: 44182 | D7: 44188 | E7: 44188 | F7: 46014 | G7: 15000 | H7: 5600 | I7: 8.80 to 9.15 | J7: BIDS REJECTED | K7: - | L7: -
A8: GIS-FRR 07 | B8: 5-Year | C8: 44210 | D8: 44216 | E8: 44216 | F8: 46042 | G8: 15000 | H8: 8750 | I8: 9.25 to 9.52 | J8: 8250 | K8: - | L8: 8250 | M8: 0.0945 | T8: Fixed Rental Rate | U8: Policy Rate
A9: GIS-FRR 08 | B9: 5-Year | C9: 44469 | D9: 44475 | E9: 44475 | F9: 46301 | G9: 25000 | H9: 53830 | I9: 9.65 to 10.75 | J9: 12730 | K9: - | L9: 12730 | M9: 0.097 | S9: 2019 | T9: 0.12 | U9: ='Policy Rate'!D150 -> 0.1245411
A10: GIS-FRR 09 | B10: 5-Year | C10: 44495 | D10: 44498 | E10: 44498 | F10: 46324 | G10: 25000 | H10: 22967 | I10: 9.98 to 11.10 | J10: BIDS REJECTED | K10: - | L10: - | S10: 2020 | T10: =AVERAGE(M2:M7) -> 0.0837 | U10: ='Policy Rate'!D141 -> 0.084439891
A11: GIS-FRR 10 | B11: 5-Year | C11: 44511 | D11: 44517 | E11: 44517 | F11: 46343 | G11: 25000 | H11: 21548 | I11: 9.80 to 10.99 | J11: BIDS REJECTED | K11: - | L11: - | S11: 2021 | T11: =AVERAGE(M8:M12) -> 0.10183333 | U11: ='Policy Rate'!D129 -> 0.077787671
A12: GIS-FRR 11 | B12: 5-Year | C12: 44539 | D12: 44545 | E12: 44545 | F12: 46371 | G12: 25000 | H12: 109803 | I12: 11.00 to 12.84 | J12: 68003 | K12: - | L12: 68003 | M12: 0.114 | S12: 2022 | T12: =AVERAGE(M13:M25) -> 0.122175 | U12: ='Policy Rate'!D121 -> 0.14582877
A13: GIS-FRR 11 (1st RO) | B13: 5-Year | C13: 44567 | D13: 44573 | E13: 44545 | F13: 46371 | G13: 25000 | H13: 222715.4 | I13: 101.5000 - 96.4087 | J13: 163835.4 | K13: 692 | L13: 164527.4 | M13: 0.114 | N13: 100.9078 | O13: 0.1115 | S13: 2023 | T13: =AVERAGE(M26:M58) -> 0.181964 | U13: ='Policy Rate'!D112 -> 0.21386301
A14: GIS-FRR 11 (2nd RO) | B14: 5-Year | C14: 44602 | D14: 44608 | E14: 44545 | F14: 46371 | G14: 25000 | H14: 130250.5 | I14: 104.6493 - 99.9638 | J14: 64995.5 | K14: 2059.5 | L14: 67055 | M14: 0.114 | N14: 102.3653 | O14: 0.107501 | S14: 2024 | T14: =M58 -> 0.1575 | U14: ='Policy Rate'!D103 -> 0.18032787
A15: GIS-FRR 11 (3rd RO) | B15: 5-Year | C15: 44637 | D15: 44642 | E15: 44545 | F15: 46371 | G15: 25000 | H15: 69890.6 | I15: 103.0000 - 97.1420 | J15: 24105.6 | K15: 137.5 | L15: 24243.1 | M15: 0.114 | N15: 100.175 | O15: 0.113403
A16: GIS-FRR 12 | B16: 5-Year | C16: 44672 | D16: 44678 | E16: 44678 | F16: 46504 | G16: 25000 | H16: 43107.4 | I16: 11.10 to 14.00 | J16: 17599.9 | K16: 150 | L16: 17749.9 | M16: 0.1249
A17: GIS-FRR 12 (1st RO) | B17: 5-Year | C17: 44707 | D17: 44713 | E17: 44678 | F17: 46504 | G17: 25000 | H17: 49150.2 | I17: 100.2946 - 93.0814 | J17: 17400.2 | K17: 69.5 | L17: 17469.7 | M17: 0.1249 | N17: 98.3725 | O17: 0.1294
A18: GIS-FRR 12 (2nd RO) | B18: 5-Year | C18: 44732 | D18: 44735 | E18: 44678 | F18: 46504 | G18: 25000 | H18: 23508.3 | I18: 100.2000 - 91.5545 | J18: 6008.3 | K18: - | L18: 6008.3 | M18: 0.1249 | N18: 98.3725 | O18: 0.129407
A19: GIS-FRR 12 (3rd RO) | B19: 5-Year | C19: 44755 | D19: 44761 | E19: 44678 | F19: 46504 | G19: 25000 | H19: 29865.5 | I19: 100.0000 - 90.8499 | J19: 65.5 | K19: 199.5 | L19: 265 | M19: 0.1249 | N19: 99.2175 | O19: 0.127
A20: GIS-FRR 12 (4th RO) | B20: 5-Year | C20: 44791 | D20: 44797 | E20: 44678 | F20: 46504 | G20: 30000 | H20: 35719 | I20: 100.6181 - 94.9300 | J20: 19119 | K20: 200 | L20: 19319 | M20: 0.1249 | N20: 98.4471 | O20: 0.1293
A21: GIS-FRR 12 (5th RO) | B21: 5-Year | C21: 44826 | D21: 44832 | E21: 44678 | F21: 46504 | G21: 10000 | H21: 12525 | I21: 98.5885 - 96.6379 | J21: 25 | K21: 50 | L21: 75 | M21: 0.1249 | N21: 98.5885 | O21: 0.129002
A22: GIS-FRR 13 | B22: 5-Year | C22: 44854 | D22: 44860 | E22: 44860 | F22: 46686 | G22: 30000 | H22: 5590 | I22: 12.49 to 13.35 | J22: BIDS REJECTED | K22: - | L22: -
A23: GIS-FRR 14 | B23: 5-Year | C23: 44875 | D23: 44881 | E23: 44881 | F23: 46707 | G23: 30000 | H23: 25.5 | I23: 12.49 to 12.50 | J23: 25 | K23: 174.5 | L23: 199.5 | M23: 0.1249
A24: GIS-FRR 14 (1st RO) | B24: 5-Year | C24: 44896 | D24: 44902 | E24: 44881 | F24: 46707 | G24: 30000 | H24: 0.8 | I24: 100.0000 - 100.0000 | J24: BIDS REJECTED | K24: - | L24: - | M24: 0.1249
A25: GIS-FRR 14 (2nd RO) | B25: 5-Year | C25: 44903 | D25: 44907 | E25: 44881 | F25: 46707 | G25: 30000 | H25: NO BID RECEIVED | I25: - | J25: - | K25: - | L25: - | M25: 0.1249
A26: GIS-FRR 15 | B26: 3-Year | C26: 44929 | D26: 44931 | E26: 44931 | F26: 46027 | G26: 20000 | H26: NO BID RECEIVED | I26: - | J26: - | K26: - | L26: -
A27: GIS-FRR 14 (3rd RO) | B27: 5-Year | C27: 44929 | D27: 44931 | E27: 44881 | F27: 46707 | G27: 30000 | H27: NO BID RECEIVED | I27: - | J27: - | K27: - | L27: -
A28: GIS-FRR 16 | B28: 1-Year | C28: 44973 | D28: 44977 | E28: 44977 | F28: 45342 | G28: 10000 | H28: 0.5 | I28: 17.50 to 17.50 | J28: 0.5 | K28: - | L28: 0.5 | M28: 0.175
A29: GIS-FRR 17 | B29: 3-Year | C29: 44973 | D29: 44977 | E29: 44931 | F29: 46027 | G29: 10000 | H29: 2.5 | I29: 17.10 to 17.10 | J29: BIDS REJECTED | K29: - | L29: -
A30: GIS-FRR 14 (4th RO) | B30: 5-Year | C30: 44973 | D30: 44977 | E30: 44881 | F30: 46707 | G30: 10000 | H30: NO BID RECEIVED | I30: - | J30: NO BID RECEIVED | K30: - | L30: -
A31: GIS-FRR 18 | B31: 1-Year | C31: 44991 | D31: 44993 | E31: 44993 | F31: 45359 | G31: 10000 | H31: 6150 | I31: 20.00 to 23.95 | J31: 1150 | K31: - | L31: 1150 | M31: 0.207
A32: GIS-FRR 19 | B32: 3-Year | C32: 44991 | D32: 44993 | E32: 44993 | F32: 46089 | G32: 10000 | H32: NO BID RECEIVED | J32: - | K32: - | L32: -
A33: GIS-FRR 14 (5th RO) | B33: 5-Year | C33: 44991 | D33: 44993 | E33: 44881 | F33: 46707 | G33: 10000 | H33: NO BID RECEIVED | J33: - | K33: - | L33: - | M33: 0.1249
A34: GIS-FRR 20 | B34: 1-Year | C34: 45029 | D34: 45033 | E34: 45033 | F34: 45399 | G34: 10000 | H34: 14591.7 | I34: 20.00 to 22.25 | J34: 11290.6 | K34: 175 | L34: 11465.6 | M34: 0.2125
A35: GIS-FRR 21 | B35: 3-Year | C35: 45029 | D35: 45033 | E35: 45033 | F35: 46129 | G35: 10000 | H35: 25005 | I35: 17.99 to 18.24 | J35: 25005 | K35: - | L35: 25005 | M35: 0.1824
A36: GIS-FRR 14 (6th RO) | B36: 5-Year | C36: 45029 | D36: 45033 | E36: 44881 | F36: 46707 | G36: 10000 | H36: NO BID RECEIVED | J36: - | K36: - | L36: - | M36: 0.1249
A37: GIS-FRR 22 | B37: 1-Year | C37: 45064 | D37: 45068 | E37: 45068 | F37: 45434 | G37: 10000 | H37: 1251.6 | I37: 20.99 to 21.30 | J37: 1251.6 | K37: 125 | L37: 1376.6 | M37: 0.213
A38: GIS-FRR 21 (1st RO) | B38: 3-Year | C38: 45064 | D38: 45068 | E38: 45033 | F38: 46129 | G38: 10000 | H38: 0.1 | I38: 97.2300 - 97.2300 | J38: BIDS REJECTED | K38: - | L38: - | M38: 0.1824
A39: GIS-FRR 14 (7th RO) | B39: 5-Year | C39: 45064 | D39: 45068 | E39: 44881 | F39: 46707 | G39: 10000 | H39: NO BID RECEIVED | J39: - | K39: - | L39: - | M39: 0.1249
A40: GIS-FRR 23 | B40: 1-Year | C40: 45099 | D40: 45103 | E40: 45103 | F40: 45469 | G40: 20000 | H40: 691 | I40: 20.00 to 21.29 | J40: 691 | K40: 210 | L40: 901 | M40: 0.2129
A41: GIS-FRR 24 | B41: 3-Year | C41: 45099 | D41: 45103 | E41: 45103 | F41: 46199 | G41: 20000 | H41: 200172.5 | I41: 17.99 to 20.00 | J41: 75052.5 | K41: 50 | L41: 75102.5 | M41: 0.1849
A42: GIS-FRR 25 | B42: 5-Year | C42: 45099 | D42: 45103 | E42: 45103 | F42: 46930 | G42: 20000 | H42: NO BID RECEIVED | J42: - | K42: - | L42: -
A43: GIS-FRR 26 | B43: 1-Year | C43: 45117 | D43: 45119 | E43: 45119 | F43: 45485 | G43: 30000 | H43: 6387.3 | I43: 21.29 to 22.15 | J43: 6387.3 | K43: - | L43: 6387.3 | M43: 0.2215
A44: GIS-FRR 24 (1st RO) | B44: 3-Year | C44: 45117 | D44: 45119 | E44: 45103 | F44: 46199 | G44: 30000 | H44: 140037.5 | I44: 100.2768 - 98.3331 | J44: 115037.5 | K44: - | L44: 115037.5 | M44: 0.1849 | N44: 98.874 | O44: 0.1899
A45: GIS-FRR 27 | B45: 5-Year | C45: 45117 | D45: 45119 | E45: 45119 | F45: 46946 | G45: 30000 | H45: 75000 | I45: 15.99 to 15.99 | J45: BIDS REJECTED | K45: - | L45: -
A46: GIS-FRR 28 | B46: 1-Year | C46: 45141 | D46: 45145 | E46: 45145 | F46: 45511 | G46: 30000 | H46: 1810.9 | I46: 20.00 to 22.25 | J46: 1800.9 | K46: 360 | L46: 2160.9 | M46: 0.22
A47: GIS-FRR 24 (2nd RO) | B47: 3-Year | C47: 45141 | D47: 45145 | E47: 45103 | F47: 46199 | G47: 30000 | H47: 82245 | I47: 99.3648 - 96.7500 | J47: 68245 | K47: 140 | L47: 68385 | M47: 0.1849 | N47: 98.4069 | O47: 0.191999
A48: GIS-FRR 29 | B48: 5-Year | C48: 45141 | D48: 45145 | E48: 45145 | F48: 46972 | G48: 30000 | H48: 75000 | I48: 16.30 to 17.15 | J48: BIDS REJECTED | K48: - | L48: -
A49: GIS-FRR 30 | B49: 1-Year | C49: 45187 | D49: 45189 | E49: 45189 | F49: 45555 | G49: 20000 | H49: 10054.5 | I49: 21.75 to 24.00 | J49: 10051.7 | K49: 110 | L49: 10161.7 | M49: 0.2295
A50: GIS-FRR 24 (3rd RO) | B50: 3-Year | C50: 45187 | D50: 45189 | E50: 45103 | F50: 46199 | G50: 20000 | H50: 13778.5 | I50: 98.8355 - 95.9000 | J50: 278.5 | K50: 50 | L50: 328.5 | M50: 0.1849 | N50: 98.4449 | O50: 0.1919
A51: GIS-FRR 31 | B51: 5-Year | C51: 45187 | D51: 45189 | E51: 45189 | F51: 47016 | G51: 20000 | H51: 10900 | I51: 16.50 to 18.79 | J51: 100 | K51: 100 | L51: 200 | M51: 0.165
A52: GIS-FRR 32 | B52: 1-Year | C52: 45204 | D52: 45208 | E52: 45208 | F52: 45574 | G52: 40000 | H52: 291289.1 | I52: 21.50 to 23.49 | J52: 110419.1 | K52: 830 | L52: 111249.1 | M52: 0.2249
A53: GIS-FRR 24 (4th RO) | B53: 3-Year | C53: 45204 | D53: 45208 | E53: 45103 | F53: 46199 | G53: 40000 | H53: 167330 | I53: 100.0861 - 98.5048 | J53: 101200 | K53: 600 | L53: 101800 | M53: 0.1849 | N53: 98.9556 | O53: 0.1895
A54: GIS-FRR 31 (1st RO) | B54: 5-Year | C54: 45204 | D54: 45208 | E54: 45189 | F54: 47016 | G54: 40000 | H54: 40300 | I54: 100.0338 - 96.3493 | J54: 300 | K54: 100 | L54: 400 | M54: 0.165 | N54: 100.0338 | O54: 0.164806
A55: GIS-FRR 33 | B55: 3-Year | C55: 45260 | D55: 45264 | E55: 45264 | F55: 46360 | G55: 30000 | H55: 149920.7 | I55: 15.50 to 20.00 | J55: 30055 | K55: 4247 | L55: 34302 | M55: 0.1619
A56: GIS-FRR 34 | B56: 5-Year | C56: 45260 | D56: 45264 | E56: 45264 | F56: 47091 | G56: 40000 | H56: 59252 | I56: 14.50 to 16.87 | J56: 40002 | K56: 2445 | L56: 42447 | M56: 0.1575
A57: GIS-FRR 33 (1st RO) | B57: 3-Year | C57: 45281 | D57: 45286 | E57: 45264 | F57: 46360 | G57: 20000 | H57: 31350.5 | I57: 102.00 - 90.00 | J57: 90.5 | K57: 258.5 | L57: 349 | M57: 0.1619 | N57: 100.2842 | O57: 0.160505
A58: GIS-FRR 34 (1st RO) | B58: 5-Year | C58: 45281 | D58: 45286 | E58: 45264 | F58: 47091 | G58: 30000 | H58: 40010 | I58: 100.0022 - 90.0000 | J58: 10000 | K58: 396.5 | L58: 10396.5 | M58: 0.1575 | N58: 100.0022 | O58: 0.1574

Sheet HBL Stock Price Daily
A1: HBL | I1: KSE100
A2: Date | B2: Open | C2: High | D2: Low | E2: Close | F2: Volume | G2: Weekly Return | I2: Date | J2: Open | K2: High | L2: Low | M2: Close | N2: Volume | O2: Weekly Return
A3: 45912 | B3: 260 | C3: 264.5 | D3: 256 | E3: 261.54 | F3: 2807728 | G3: =E3/E4-1 -> 0.013053414 | I3: 45912 | J3: 156201.69 | K3: 156519.13 | L3: 154360.35 | M3: 154439.68 | N3: 241099022 | O3: =M3/M4-1 -> -0.010897569
A4: 45911 | B4: 257.5 | C4: 261.4 | D4: 257 | E4: 258.17 | F4: 922582 | G4: =E4/E5-1 -> -0.013488728 | I4: 45911 | J4: 157284.65 | K4: 157816.76 | L4: 156103.81 | M4: 156141.24 | N4: 402820222 | O4: =M4/M5-1 -> -0.0056014875
A5: 45910 | B5: 264 | C5: 264.9 | D5: 260.18 | E5: 261.7 | F5: 797345 | G5: =E5/E6-1 -> -0.033818209 | I5: 45910 | J5: 156571.73 | K5: 157479.42 | L5: 156079.52 | M5: 157020.79 | N5: 437129643 | O5: =M5/M6-1 -> 0.0029206676
A6: 45909 | B6: 274.1 | C6: 274.1 | D6: 262.4 | E6: 270.86 | F6: 4744653 | G6: =E6/E7-1 -> 0.019612272 | I6: 45909 | J6: 156640.09 | K6: 157563.52 | L6: 155044.25 | M6: 156563.52 | N6: 480306328 | O6: =M6/M7-1 -> 0.0030509849
A7: 45908 | B7: 261 | C7: 267.5 | D7: 261 | E7: 265.65 | F7: 3749318 | G7: =E7/E8-1 -> 0.11598891 | I7: 45908 | J7: 155057.33 | K7: 156199.28 | L7: 154944.87 | M7: 156087.3 | N7: 492409990 | O7: =M7/M8-1 -> 0.011732843
A8: 45905 | B8: 233 | C8: 244.44 | D8: 233 | E8: 238.04 | F8: 9247674 | G8: =E8/E9-1 -> 0.066487455 | I8: 45905 | J8: 153149.44 | K8: 154511.31 | L8: 153129.78 | M8: 154277.19 | N8: 471374828 | O8: =M8/M9-1 -> 0.010555546
A9: 45904 | B9: 226 | C9: 227 | D9: 219.52 | E9: 223.2 | F9: 2250610 | G9: =E9/E10-1 -> -0.017432647 | I9: 45904 | J9: 152599.44 | K9: 153411.05 | L9: 152264.96 | M9: 152665.72 | N9: 407266609 | O9: =M9/M10-1 -> 0.0030475972
A10: 45903 | B10: 223.8 | C10: 234 | D10: 223.5 | E10: 227.16 | F10: 5321459 | G10: =E10/E11-1 -> 0.028850944 | I10: 45903 | J10: 151320.49 | K10: 152805.3 | L10: 151320.49 | M10: 152201.87 | N10: 337866019 | O10: =M10/M11-1 -> 0.0081231071
A11: 45902 | B11: 202.5 | C11: 221.95 | D11: 201.8 | E11: 220.79 | F11: 8673875 | G11: =E11/E12-1 -> 0.082728521 | I11: 45902 | J11: 150318.61 | K11: 151075.67 | L11: 150081.4 | M11: 150975.48 | N11: 441999922 | O11: =M11/M12-1 -> 0.0066970227
A12: 45901 | B12: 199 | C12: 208.75 | D12: 197.6 | E12: 203.92 | F12: 6311350 | G12: =E12/E13-1 -> 0.13800993 | I12: 45901 | J12: 149079.23 | K12: 150066 | L12: 148500.2 | M12: 149971.12 | N12: 511821531 | O12: =M12/M13-1 -> 0.0091062462
A13: 45898 | B13: 174 | C13: 179.99 | D13: 173.5 | E13: 179.19 | F13: 3441747 | G13: =E13/E14-1 -> 0.10891763 | I13: 45898 | J13: 147591.81 | K13: 149234.94 | L13: 147488.46 | M13: 148617.77 | N13: 624598293 | O13: =M13/M14-1 -> 0.0086482946
A14: 45897 | B14: 165 | C14: 165.8 | D14: 160.05 | E14: 161.59 | F14: 816594 | G14: =E14/E15-1 -> -0.01119814 | I14: 45897 | J14: 147554.39 | K14: 148042 | L14: 147209.55 | M14: 147343.5 | N14: 306526022 | O14: =M14/M15-1 -> -0.0010205837
... A1238: 44089 | B1238: 136 | C1238: 137.5 | D1238: 135.1 | E1238: 135.49 | F1238: 390990 | G1238: =E1238/E1239-1 -> -0.0088514996 | I1238: 44089 | J1238: 42594.98 | K1238: 42831.01 | L1238: 42263.22 | M1238: 42346.42 | N1238: 411064768 | O1238: =M1238/M1239-1 -> -0.0043471504
A1239: 44088 | B1239: 136 | C1239: 137.02 | D1239: 135.26 | E1239: 136.7 | F1239: 436151 | I1239: 44088 | J1239: 42631.77 | K1239: 42722.59 | L1239: 42367.81 | M1239: 42531.31 | N1239: 289623250

Sheet Regression Daily
A1: SUMMARY OUTPUT
A3: Regression Statistics
A4: Multiple R | B4: 0.59477421
A5: R Square | B5: 0.35375636
A6: Adjusted R Square | B6: 0.35323266
A7: Standard Error | B7: 0.015501447
A8: Observations | B8: 1236
A10: ANOVA
B11: df | C11: SS | D11: MS | E11: F | F11: Significance F
A12: Regression | B12: 1 | C12: 0.16231835 | D12: 0.16231835 | E12: 675.49656 | F12: 3.9419197e-119
A13: Residual | B13: 1234 | C13: 0.29652386 | D13: 0.00024029486
A14: Total | B14: 1235 | C14: 0.45884221
B16: Coefficients | C16: Standard Error | D16: t Stat | E16: P-value | F16: Lower 95% | G16: Upper 95% | H16: Lower 95.0% | I16: Upper 95.0%
A17: Intercept | B17: -0.00045662721 | C17: 0.0004431376 | D17: -1.0304411 | E17: 0.30300489 | F17: -0.0013260137 | G17: 0.00041275925 | H17: -0.0013260137 | I17: 0.00041275925
A18: X Variable 1 | B18: 1.0414069 | C18: 0.040069035 | D18: 25.990317 | E18: 3.9419197e-119 | F18: 0.96279593 | G18: 1.1200179 | H18: 0.96279593 | I18: 1.1200179

Sheet HBL Stock Price Weekly
A1: HBL | I1: KSE100
A2: Date | B2: Open | C2: High | D2: Low | E2: Close | F2: Volume | G2: Weekly Return | I2: Date | J2: Open | K2: High | L2: Low | M2: Close | N2: Weekly Return
A3: Week of Sep 8, 2025 | B3: 260 | C3: 268 | D3: 255.8 | E3: 256.74 | F3: 8432070 | G3: =E3/E4-1 -> -0.010292587 | I3: 45908 | J3: 155057.33 | K3: 156199.28 | L3: 154944.87 | M3: 156087.3 | N3: =M3/M4-1 -> 0.040782385
A4: Week of Sep 1, 2025 | B4: 257.5 | C4: 263.89 | D4: 255.61 | E4: 259.41 | F4: 7056106 | G4: =E4/E5-1 -> 0.012489754 | I4: 45901 | J4: 149079.23 | K4: 150066 | L4: 148500.2 | M4: 149971.12 | N4: =M4/M5-1 -> 0.0077668089
A5: Week of Aug 25, 2025 | B5: 264 | C5: 264.9 | D5: 247 | E5: 256.21 | F5: 8857112 | G5: =E5/E6-1 -> -0.031268905 | I5: 45894 | J5: 149828.16 | K5: 150079.75 | L5: 148757.13 | M5: 148815.3 | N5: =M5/M6-1 -> 0.0041760793
A6: Week of Aug 18, 2025 | B6: 274.1 | C6: 274.99 | D6: 262.4 | E6: 264.48 | F6: 13513570 | G6: =E6/E7-1 -> -0.035272661 | I6: 45887 | J6: 999999.99 | K6: 148395.71 | L6: 146403.64 | M6: 148196.42 | N6: =M6/M7-1 -> 0.0086203048
A7: Week of Aug 11, 2025 | B7: 261 | C7: 279.49 | D7: 261 | E7: 274.15 | F7: 12395479 | G7: =E7/E8-1 -> 0.049056748 | I7: 45880 | J7: 145650.33 | K7: 147005.17 | L7: 145258.49 | M7: 146929.84 | N7: =M7/M8-1 -> 0.034333751
A8: Week of Aug 4, 2025 | B8: 233 | C8: 274.9 | D8: 233 | E8: 261.33 | F8: 40458768 | G8: =E8/E9-1 -> 0.12948956 | I8: 45873 | J8: 141962.94 | K8: 142323.34 | L8: 141440.48 | M8: 142052.64 | N8: =M8/M9-1 -> 0.019174839
A9: Week of Jul 28, 2025 | B9: 226 | C9: 234 | D9: 214 | E9: 231.37 | F9: 19744308 | G9: =E9/E10-1 -> 0.021546205 | I9: 45866 | J9: 139759.59 | K9: 140149.23 | L9: 139195.84 | M9: 139380.05 | N9: =M9/M10-1 -> 0.0084104352
A10: Week of Jul 21, 2025 | B10: 223.8 | C10: 240 | D10: 223.5 | E10: 226.49 | F10: 25883916 | G10: =E10/E11-1 -> 0.018298714 | I10: 45859 | J10: 139142.17 | K10: 139201.15 | L10: 138149.56 | M10: 138217.58 | N10: =M10/M11-1 -> 0.012564236
A11: Week of Jul 14, 2025 | B11: 202.5 | C11: 232.7 | D11: 201.8 | E11: 222.42 | F11: 29105473 | G11: =E11/E12-1 -> 0.10234425 | I11: 45852 | J11: 134937.43 | K11: 136841.49 | L11: 134937.43 | M11: 136502.53 | N11: =M11/M12-1 -> 0.023486442
A12: Week of Jul 7, 2025 | B12: 199 | C12: 208.75 | D12: 197.6 | E12: 201.77 | F12: 14182619 | G12: =E12/E13-1 -> 0.025723146 | I12: 45845 | J12: 132485.75 | K12: 133862.01 | L12: 132467.12 | M12: 133370.14 | N12: =M12/M13-1 -> 0.061633334
A13: Week of Jun 30, 2025 | B13: 174 | C13: 197.51 | D13: 173.5 | E13: 196.71 | F13: 24543271 | G13: =E13/E14-1 -> 0.13626386 | I13: 45838 | J13: 124884.07 | K13: 125748.58 | L13: 124500.2 | M13: 125627.31 | N13: =M13/M14-1 -> 0.08143278
A14: Week of Jun 23, 2025 | B14: 165 | C14: 176.8 | D14: 160.05 | E14: 173.12 | F14: 14148045 | G14: =E14/E15-1 -> 0.041010222 | I14: 45831 | J14: 118272 | K14: 118798.51 | L14: 115887.48 | M14: 116167.47 | N14: =M14/M15-1 -> -0.049563204
... A258: Week of Sep 28, 2020 | B258: 133.44 | C258: 134.5 | D258: 125.25 | E258: 131.04 | F258: 3234742 | G258: =E258/E259-1 -> -0.020700994 | I258: 44102 | J258: 41723.82 | K258: 41785.73 | L258: 40640.22 | M258: 40740.95 | N258: =M258/M259-1 -> -0.033982444
A259: Week of Sep 21, 2020 | B259: 134.49 | C259: 134.49 | D259: 130.5 | E259: 133.81 | F259: 2216527 | I259: 44095 | J259: 42524.17 | K259: 42553.23 | L259: 42120.88 | M259: 42174.13

Sheet Regression Weekly
A1: SUMMARY OUTPUT
A3: Regression Statistics
A4: Multiple R | B4: 0.26969171
A5: R Square | B5: 0.07273362
A6: Adjusted R Square | B6: 0.069082965
A7: Standard Error | B7: 0.047965553
A8: Observations | B8: 256
A10: ANOVA
B11: df | C11: SS | D11: MS | E11: F | F11: Significance F
A12: Regression | B12: 1 | C12: 0.045837753 | D12: 0.045837753 | E12: 19.923444 | F12: 1.2127038e-05
A13: Residual | B13: 254 | C13: 0.58437635 | D13: 0.0023006943
A14: Total | B14: 255 | C14: 0.63021411
B16: Coefficients | C16: Standard Error | D16: t Stat | E16: P-value | F16: Lower 95% | G16: Upper 95% | H16: Lower 95.0% | I16: Upper 95.0%
A17: Intercept | B17: 0.00080676615 | C17: 0.0030683042 | D17: 0.26293551 | E17: 0.79281344 | F17: -0.0052357913 | G17: 0.0068493236 | H17: -0.0052357913 | I17: 0.0068493236
A18: X Variable 1 | B18: 0.53708809 | C18: 0.12032706 | D18: 4.4635685 | E18: 1.2127038e-05 | F18: 0.30012228 | G18: 0.77405389 | H18: 0.30012228 | I18: 0.77405389

Sheet HBL Stock Price Monthly
A1: HBL | H1: KSE100
A2: Date | B2: Open | C2: High | D2: Low | E2: Close | F2: Weekly Return | H2: Date | I2: Open | J2: High | K2: Low | L2: Close | M2: Monthly Return
A3: 45898 | B3: 249.2 | C3: 249.2 | D3: 249.2 | E3: 249.2 | F3: =E3/E4-1 -> 0.10509978 | H3: 45898 | I3: 147591.81 | J3: 147591.81 | K3: 147591.81 | L3: 147591.81 | M3: =L3/L4-1 -> 0.058923236 | P3: 44073 | Q3: 45898
A4: 45869 | B4: 225.5 | C4: 225.5 | D4: 225.5 | E4: 225.5 | F4: =E4/E5-1 -> 0.29597701 | H4: 45869 | I4: 139379.14 | J4: 139379.14 | K4: 139379.14 | L4: 139379.14 | M4: =L4/L5-1 -> 0.11606821 | O4: KSE100 | P4: 41110.93 | Q4: 148617.78
A5: 45838 | B5: 174 | C5: 174 | D5: 174 | E5: 174 | F5: =E5/E6-1 -> 0.12979677 | H5: 45838 | I5: 124884.07 | J5: 124884.07 | K5: 124884.07 | L5: 124884.07 | M5: =L5/L6-1 -> 0.048223685 | O5: CAGR | P5: =((Q4/P4)^(1/5))-1 -> 0.29307196
A6: 45807 | B6: 154.01 | C6: 154.01 | D6: 154.01 | E6: 154.01 | F6: =E6/E7-1 -> 0.013890718 | H6: 45807 | I6: 119138.76 | J6: 119138.76 | K6: 119138.76 | L6: 119138.76 | M6: =L6/L7-1 -> 0.044471049
A7: 45777 | B7: 151.9 | C7: 151.9 | D7: 151.9 | E7: 151.9 | F7: =E7/E8-1 -> -0.013444177 | H7: 45777 | I7: 114066.12 | J7: 114066.12 | K7: 114066.12 | L7: 114066.12 | M7: =L7/L8-1 -> -0.033646626 | P7: 42244 | Q7: 45898
A8: 45743 | B8: 153.97 | C8: 153.97 | D8: 153.97 | E8: 153.97 | F8: =E8/E9-1 -> 0.0063398693 | H8: 45743 | I8: 118037.69 | J8: 118037.69 | K8: 118037.69 | L8: 118037.69 | M8: =L8/L9-1 -> 0.036412289 | O8: KSE100 | P8: 34447.47 | Q8: 148617.78
A9: 45716 | B9: 153 | C9: 153 | D9: 153 | E9: 153 | F9: =E9/E10-1 -> -0.11647514 | H9: 45716 | I9: 113890.67 | J9: 113890.67 | K9: 113890.67 | L9: 113890.67 | M9: =L9/L10-1 -> 0.0012719569 | O9: CAGR | P9: =((Q8/P8)^(1/10))-1 -> 0.15742096
A10: 45688 | B10: 173.17 | C10: 173.17 | D10: 173.17 | E10: 173.17 | F10: =E10/E11-1 -> 0.00034660043 | H10: 45688 | I10: 113745.99 | J10: 113745.99 | K10: 113745.99 | L10: 113745.99 | M10: =L10/L11-1 -> -0.025313021
A11: 45657 | B11: 173.11 | C11: 173.11 | D11: 173.11 | E11: 173.11 | F11: =E11/E12-1 -> -0.02747191 | H11: 45657 | I11: 116700.02 | J11: 116700.02 | K11: 116700.02 | L11: 116700.02 | M11: =L11/L12-1 -> 0.16242999
A12: 45625 | B12: 178 | C12: 178 | D12: 178 | E12: 178 | F12: =E12/E13-1 -> 0.29927007 | H12: 45625 | I12: 100393.16 | J12: 100393.16 | K12: 100393.16 | L12: 100393.16 | M12: =L12/L13-1 -> 0.10981739 | P12: 42244 | Q12: 44073
A13: 45596 | B13: 137 | C13: 137 | D13: 137 | E13: 137 | F13: =E13/E14-1 -> 0.06614786 | H13: 45596 | I13: 90459.17 | J13: 90459.17 | K13: 90459.17 | L13: 90459.17 | M13: =L13/L14-1 -> 0.11305485 | O13: KSE100 | P13: 34447.47 | Q13: 41110.93
A14: 45565 | B14: 128.5 | C14: 128.5 | D14: 128.5 | E14: 128.5 | F14: =E14/E15-1 -> 0.013566809 | H14: 45565 | I14: 81271.08 | J14: 81271.08 | K14: 81271.08 | L14: 81271.08 | M14: =L14/L15-1 -> 0.0346149 | O14: CAGR | P14: =((Q13/P13)^(1/10))-1 -> 0.017841132
A15: 45534 | B15: 126.78 | C15: 126.78 | D15: 126.78 | E15: 126.78 | F15: =E15/E16-1 -> -0.051260944 | H15: 45534 | I15: 78552.01 | J15: 78552.01 | K15: 78552.01 | L15: 78552.01 | M15: =L15/L16-1 -> -0.0022095634
A16: 45504 | B16: 133.63 | C16: 133.63 | D16: 133.63 | E16: 133.63 | F16: =E16/E17-1 -> 0.07247191 | H16: 45504 | I16: 78725.96 | J16: 78725.96 | K16: 78725.96 | L16: 78725.96 | M16: =L16/L17-1 -> 0.00034930793
A17: 45471 | B17: 124.6 | C17: 124.6 | D17: 124.6 | E17: 124.6 | F17: =E17/E18-1 -> 0.092982456 | H17: 45471 | I17: 78698.47 | J17: 78698.47 | K17: 78698.47 | L17: 78698.47 | M17: =L17/L18-1 -> 0.048216778
A18: 45443 | B18: 114 | C18: 114 | D18: 114 | E18: 114 | F18: =E18/E19-1 -> -0.025141098 | H18: 45443 | I18: 75078.43 | J18: 75078.43 | K18: 75078.43 | L18: 75078.43 | M18: =L18/L19-1 -> 0.045938094
A19: 45412 | B19: 116.94 | C19: 116.94 | D19: 116.94 | E19: 116.94 | F19: =E19/E20-1 -> 0.10372817 | H19: 45412 | I19: 71780.95 | J19: 71780.95 | K19: 71780.95 | L19: 71780.95 | M19: =L19/L20-1 -> 0.067657313
A20: 45380 | B20: 105.95 | C20: 105.95 | D20: 105.95 | E20: 105.95 | F20: =E20/E21-1 -> -0.078695652 | H20: 45380 | I20: 67232.2 | J20: 67232.2 | K20: 67232.2 | L20: 67232.2 | M20: =L20/L21-1 -> 0.053346337
A21: 45351 | B21: 115 | C21: 115 | D21: 115 | E21: 115 | F21: =E21/E22-1 -> 0.02954342 | H21: 45351 | I21: 63827.25 | J21: 63827.25 | K21: 63827.25 | L21: 63827.25 | M21: =L21/L22-1 -> 0.028264061
A22: 45322 | B22: 111.7 | C22: 111.7 | D22: 111.7 | E22: 111.7 | F22: =E22/E23-1 -> 0.0062156562 | H22: 45322 | I22: 62072.82 | J22: 62072.82 | K22: 62072.82 | L22: 62072.82 | M22: =L22/L23-1 -> -0.0024509312
A23: 45289 | B23: 111.01 | C23: 111.01 | D23: 111.01 | E23: 111.01 | F23: =E23/E24-1 -> -0.017436714 | H23: 45289 | I23: 62225.33 | J23: 62225.33 | K23: 62225.33 | L23: 62225.33 | M23: =L23/L24-1 -> 0.023646647
A24: 45260 | B24: 112.98 | C24: 112.98 | D24: 112.98 | E24: 112.98 | F24: =E24/E25-1 -> 0.19745628 | H24: 45260 | I24: 60787.9 | J24: 60787.9 | K24: 60787.9 | L24: 60787.9 | M24: =L24/L25-1 -> 0.17730715
A25: 45230 | B25: 94.35 | C25: 94.35 | D25: 94.35 | E25: 94.35 | F25: =E25/E26-1 -> 0.037041108 | H25: 45230 | I25: 51633 | J25: 51633 | K25: 51633 | L25: 51633 | M25: =L25/L26-1 -> 0.11124048
A26: 45197 | B26: 90.98 | C26: 90.98 | D26: 90.98 | E26: 90.98 | F26: =E26/E27-1 -> -0.081010101 | H26: 45197 | I26: 46464.29 | J26: 46464.29 | K26: 46464.29 | L26: 46464.29 | M26: =L26/L27-1 -> 0.0038360887
... A61: 44133 | B61: 132.1 | C61: 132.1 | D61: 132.1 | E61: 132.1 | F61: =E61/E62-1 -> 0.0015163002 | H61: 44133 | I61: 41032.65 | J61: 41032.65 | K61: 41032.65 | L61: 41032.65 | M61: =L61/L62-1 -> -0.0061162413
A62: 44104 | B62: 131.9 | C62: 131.9 | D62: 131.9 | E62: 131.9 | H62: 44104 | I62: 41285.16 | J62: 41285.16 | K62: 41285.16 | L62: 41285.16

Sheet Regression Monthly
A1: SUMMARY OUTPUT
A3: Regression Statistics
A4: Multiple R | B4: 0.64617634
A5: R Square | B5: 0.41754386
A6: Adjusted R Square | B6: 0.40732533
A7: Standard Error | B7: 0.080761933
A8: Observations | B8: 59
A10: ANOVA
B11: df | C11: SS | D11: MS | E11: F | F11: Significance F
A12: Regression | B12: 1 | C12: 0.26651836 | D12: 0.26651836 | E12: 40.861446 | F12: 3.2509379e-08
A13: Residual | B13: 57 | C13: 0.37178192 | D13: 0.0065224898
A14: Total | B14: 58 | C14: 0.63830028
B16: Coefficients | C16: Standard Error | D16: t Stat | E16: P-value | F16: Lower 95% | G16: Upper 95% | H16: Lower 95.0% | I16: Upper 95.0%
A17: Intercept | B17: -0.013842486 | C17: 0.011502803 | D17: -1.2034011 | E17: 0.23379544 | F17: -0.036876451 | G17: 0.0091914794 | H17: -0.036876451 | I17: 0.0091914794
A18: X Variable 1 | B18: 1.2900967 | C18: 0.20182055 | D18: 6.3922958 | E18: 3.2509379e-08 | F18: 0.88595799 | G18: 1.6942354 | H18: 0.88595799 | I18: 1.6942354
